Workbook

Sheet README
A1: FDC Limited — potential supplier & backup-supplier database
A2: Compiled 16 October 2026 from public sources (company sites, catalogues, associations, exhibitor lists, annual reports, rating rationales, regulator pages, public trade-record summaries). No paid databases.
A4: What this is
A5: Purpose | B5: Long list of POTENTIAL suppliers and backup suppliers for FDC Limited across six materials. Every company is a potential supplier only: no qualification, audit, sample approval or existing FDC relationship is implied or claimed.
A6: Status | B6: Interim version. The public web-search and page-reading tools were rate-limited during compilation, so most records rest on search-result titles and URLs rather than pages read in full. Research continues; see 'Coverage gaps' below.
A7: How to use the workbook
A8: Companies | B8: One row per deduplicated legal entity, with every material category it supports. Group affiliates in other countries (e.g. Bericap India vs BERICAP GmbH) are kept as separate entities.
A9: Category sheets | B9: One row per company x category ('supplier line'), sorted by subcategory, then pharma/ORS relevance, region (India first: West, North, South, Central, East, Northeast, Pan-India, then International) and evidence confidence.
A10: All Supplier Lines | B10: Every supplier line in one filterable table; the Summary sheet counts from here.
A11: Sources | B11: One row per source URL per supplier line, hyperlinked.
A12: Category definitions and separations
A13: Dextrose / glucose | B13: Crystalline dextrose (anhydrous / monohydrate). Pharma grades (IP/BP/USP/EP, pyrogen-free, CEP/DMF) and food grades are separated by subcategory. Liquid glucose / glucose syrup, maltodextrin, fructose and sorbitol are recorded only in 'Related products kept separate'. Starch processors with no crystalline dextrose found are kept as upstream/backup with their own subcategory.
A14: Corn / maize | B14: Upstream input to starch and dextrose. Wet-millers, bulk traders/aggregators, FPCs, platforms and procurement agencies. Seed-only, sweet-corn, popcorn and snack businesses excluded. FDC is not assumed to buy maize directly.
A15: PET resin | B15: Bottle-grade and film-grade separated; virgin resin manufacture separated from recycling (food-grade bottle-to-bottle vs non-food) and from distribution. Food-contact status is recorded as 'claimed' unless a regulator source was read.
A16: PET bottles and preforms | B16: Subcategory states preforms only, bottles only, or both. HDPE/PP/LDPE lines are noted under 'Related products kept separate'. Sizes, neck finishes and plant locations are captured where a source gave them.
A17: Caps and closures | B17: Screw, tamper-evident, child-resistant, dispensing and ROPP closures, plus liners/induction seals. Caps are not assumed to be PET; materials are recorded only where a source stated them.
A18: BOPET base film vs laminate converters | B18: The Polyester/BOPET category is split: 'BOPET Base Film' holds base-film makers, metallizers/coaters and film distributors; 'Laminate Converters' holds printers/laminators making sachets, pouches and rollstock. BOPP, CPP, PE film, foil and cartons are noted separately where relevant.
A19: Column notes
A20: Legal name verified | B20: Yes = registered name seen on a company page, filing, rating rationale or registry page. No = trade name only; confirm on MCA (India) or the local registry before contracting.
A21: Evidence confidence | B21: High = company's own page read and confirms the product. Medium = company-domain result, annual report, rating rationale, association/exhibitor listing or reputable trade press. Low = third-party B2B listing or a single weak source.
A22: Priority match (keyword-derived) | B22: Automatic flag from the recorded applications / grades / notes text: 'Pharma / ORS', 'Nutrition / food / beverage' or 'Not stated in sources'. It is a sorting aid, not a qualification.
A23: Capacity, revenue, rating, ownership | B23: Filled only where a public source gave them; blank means not found, not zero.
A24: Caveats before RFQ
A25: Verification | B25: Before shortlisting: confirm grade certificates (CoA, pharmacopoeial compliance, DMF/CEP letters of access), food-contact declarations (EU 10/2011, US FDA, FSSAI/BIS), ISO 15378 / FSSC 22000 certificates, and plant audits. Low-confidence B2B entries may be traders rather than manufacturers.
A26: Sources | B26: Public sources only: company sites, B2B storefronts, trade press, exhibitor listings, rating-agency pages, regulator pages and registry summaries. No paid databases were used.

Sheet Summary
A1: Coverage summary (counts recalculate from the 'All Supplier Lines' sheet)
A3: Segment | B3: India-West | C3: India-North | D3: India-South | E3: India-Central | F3: India-East | G3: India-Northeast | H3: India-Pan | I3: International | J3: Total
A4: Dextrose/Glucose | B4: =COUNTIFS('All Supplier Lines'!$F$2:$F$107,$A4,'All Supplier Lines'!$N$2:$N$107,B$3) -> 4 | C4: =COUNTIFS('All Supplier Lines'!$F$2:$F$107,$A4,'All Supplier Lines'!$N$2:$N$107,C$3) -> 1 | D4: =COUNTIFS('All Supplier Lines'!$F$2:$F$107,$A4,'All Supplier Lines'!$N$2:$N$107,D$3) -> 0 | E4: =COUNTIFS('All Supplier Lines'!$F$2:$F$107,$A4,'All Supplier Lines'!$N$2:$N$107,E$3) -> 0 | F4: =COUNTIFS('All Supplier Lines'!$F$2:$F$107,$A4,'All Supplier Lines'!$N$2:$N$107,F$3) -> 1 | G4: =COUNTIFS('All Supplier Lines'!$F$2:$F$107,$A4,'All Supplier Lines'!$N$2:$N$107,G$3) -> 0 | H4: =COUNTIFS('All Supplier Lines'!$F$2:$F$107,$A4,'All Supplier Lines'!$N$2:$N$107,H$3) -> 4 | I4: =COUNTIFS('All Supplier Lines'!$F$2:$F$107,$A4,'All Supplier Lines'!$N$2:$N$107,I$3) -> 27 | J4: =SUM(B4:I4) -> 37
A5: Corn/Maize | B5: =COUNTIFS('All Supplier Lines'!$F$2:$F$107,$A5,'All Supplier Lines'!$N$2:$N$107,B$3) -> 5 | C5: =COUNTIFS('All Supplier Lines'!$F$2:$F$107,$A5,'All Supplier Lines'!$N$2:$N$107,C$3) -> 3 | D5: =COUNTIFS('All Supplier Lines'!$F$2:$F$107,$A5,'All Supplier Lines'!$N$2:$N$107,D$3) -> 1 | E5: =COUNTIFS('All Supplier Lines'!$F$2:$F$107,$A5,'All Supplier Lines'!$N$2:$N$107,E$3) -> 1 | F5: =COUNTIFS('All Supplier Lines'!$F$2:$F$107,$A5,'All Supplier Lines'!$N$2:$N$107,F$3) -> 1 | G5: =COUNTIFS('All Supplier Lines'!$F$2:$F$107,$A5,'All Supplier Lines'!$N$2:$N$107,G$3) -> 0 | H5: =COUNTIFS('All Supplier Lines'!$F$2:$F$107,$A5,'All Supplier Lines'!$N$2:$N$107,H$3) -> 2 | I5: =COUNTIFS('All Supplier Lines'!$F$2:$F$107,$A5,'All Supplier Lines'!$N$2:$N$107,I$3) -> 0 | J5: =SUM(B5:I5) -> 13
A6: PET Resin | B6: =COUNTIFS('All Supplier Lines'!$F$2:$F$107,$A6,'All Supplier Lines'!$N$2:$N$107,B$3) -> 1 | C6: =COUNTIFS('All Supplier Lines'!$F$2:$F$107,$A6,'All Supplier Lines'!$N$2:$N$107,C$3) -> 0 | D6: =COUNTIFS('All Supplier Lines'!$F$2:$F$107,$A6,'All Supplier Lines'!$N$2:$N$107,D$3) -> 1 | E6: =COUNTIFS('All Supplier Lines'!$F$2:$F$107,$A6,'All Supplier Lines'!$N$2:$N$107,E$3) -> 0 | F6: =COUNTIFS('All Supplier Lines'!$F$2:$F$107,$A6,'All Supplier Lines'!$N$2:$N$107,F$3) -> 1 | G6: =COUNTIFS('All Supplier Lines'!$F$2:$F$107,$A6,'All Supplier Lines'!$N$2:$N$107,G$3) -> 0 | H6: =COUNTIFS('All Supplier Lines'!$F$2:$F$107,$A6,'All Supplier Lines'!$N$2:$N$107,H$3) -> 3 | I6: =COUNTIFS('All Supplier Lines'!$F$2:$F$107,$A6,'All Supplier Lines'!$N$2:$N$107,I$3) -> 1 | J6: =SUM(B6:I6) -> 7
A7: PET Bottles & Preforms | B7: =COUNTIFS('All Supplier Lines'!$F$2:$F$107,$A7,'All Supplier Lines'!$N$2:$N$107,B$3) -> 8 | C7: =COUNTIFS('All Supplier Lines'!$F$2:$F$107,$A7,'All Supplier Lines'!$N$2:$N$107,C$3) -> 1 | D7: =COUNTIFS('All Supplier Lines'!$F$2:$F$107,$A7,'All Supplier Lines'!$N$2:$N$107,D$3) -> 6 | E7: =COUNTIFS('All Supplier Lines'!$F$2:$F$107,$A7,'All Supplier Lines'!$N$2:$N$107,E$3) -> 0 | F7: =COUNTIFS('All Supplier Lines'!$F$2:$F$107,$A7,'All Supplier Lines'!$N$2:$N$107,F$3) -> 1 | G7: =COUNTIFS('All Supplier Lines'!$F$2:$F$107,$A7,'All Supplier Lines'!$N$2:$N$107,G$3) -> 0 | H7: =COUNTIFS('All Supplier Lines'!$F$2:$F$107,$A7,'All Supplier Lines'!$N$2:$N$107,H$3) -> 2 | I7: =COUNTIFS('All Supplier Lines'!$F$2:$F$107,$A7,'All Supplier Lines'!$N$2:$N$107,I$3) -> 1 | J7: =SUM(B7:I7) -> 19
A8: Caps & Closures | B8: =COUNTIFS('All Supplier Lines'!$F$2:$F$107,$A8,'All Supplier Lines'!$N$2:$N$107,B$3) -> 2 | C8: =COUNTIFS('All Supplier Lines'!$F$2:$F$107,$A8,'All Supplier Lines'!$N$2:$N$107,C$3) -> 0 | D8: =COUNTIFS('All Supplier Lines'!$F$2:$F$107,$A8,'All Supplier Lines'!$N$2:$N$107,D$3) -> 0 | E8: =COUNTIFS('All Supplier Lines'!$F$2:$F$107,$A8,'All Supplier Lines'!$N$2:$N$107,E$3) -> 0 | F8: =COUNTIFS('All Supplier Lines'!$F$2:$F$107,$A8,'All Supplier Lines'!$N$2:$N$107,F$3) -> 0 | G8: =COUNTIFS('All Supplier Lines'!$F$2:$F$107,$A8,'All Supplier Lines'!$N$2:$N$107,G$3) -> 0 | H8: =COUNTIFS('All Supplier Lines'!$F$2:$F$107,$A8,'All Supplier Lines'!$N$2:$N$107,H$3) -> 4 | I8: =COUNTIFS('All Supplier Lines'!$F$2:$F$107,$A8,'All Supplier Lines'!$N$2:$N$107,I$3) -> 13 | J8: =SUM(B8:I8) -> 19
A9: BOPET base film | B9: =COUNTIFS('All Supplier Lines'!$F$2:$F$107,$A9,'All Supplier Lines'!$N$2:$N$107,B$3) -> 1 | C9: =COUNTIFS('All Supplier Lines'!$F$2:$F$107,$A9,'All Supplier Lines'!$N$2:$N$107,C$3) -> 1 | D9: =COUNTIFS('All Supplier Lines'!$F$2:$F$107,$A9,'All Supplier Lines'!$N$2:$N$107,D$3) -> 0 | E9: =COUNTIFS('All Supplier Lines'!$F$2:$F$107,$A9,'All Supplier Lines'!$N$2:$N$107,E$3) -> 1 | F9: =COUNTIFS('All Supplier Lines'!$F$2:$F$107,$A9,'All Supplier Lines'!$N$2:$N$107,F$3) -> 0 | G9: =COUNTIFS('All Supplier Lines'!$F$2:$F$107,$A9,'All Supplier Lines'!$N$2:$N$107,G$3) -> 0 | H9: =COUNTIFS('All Supplier Lines'!$F$2:$F$107,$A9,'All Supplier Lines'!$N$2:$N$107,H$3) -> 2 | I9: =COUNTIFS('All Supplier Lines'!$F$2:$F$107,$A9,'All Supplier Lines'!$N$2:$N$107,I$3) -> 2 | J9: =SUM(B9:I9) -> 7
A10: Laminate converters | B10: =COUNTIFS('All Supplier Lines'!$F$2:$F$107,$A10,'All Supplier Lines'!$N$2:$N$107,B$3) -> 2 | C10: =COUNTIFS('All Supplier Lines'!$F$2:$F$107,$A10,'All Supplier Lines'!$N$2:$N$107,C$3) -> 1 | D10: =COUNTIFS('All Supplier Lines'!$F$2:$F$107,$A10,'All Supplier Lines'!$N$2:$N$107,D$3) -> 0 | E10: =COUNTIFS('All Supplier Lines'!$F$2:$F$107,$A10,'All Supplier Lines'!$N$2:$N$107,E$3) -> 0 | F10: =COUNTIFS('All Supplier Lines'!$F$2:$F$107,$A10,'All Supplier Lines'!$N$2:$N$107,F$3) -> 0 | G10: =COUNTIFS('All Supplier Lines'!$F$2:$F$107,$A10,'All Supplier Lines'!$N$2:$N$107,G$3) -> 0 | H10: =COUNTIFS('All Supplier Lines'!$F$2:$F$107,$A10,'All Supplier Lines'!$N$2:$N$107,H$3) -> 1 | I10: =COUNTIFS('All Supplier Lines'!$F$2:$F$107,$A10,'All Supplier Lines'!$N$2:$N$107,I$3) -> 0 | J10: =SUM(B10:I10) -> 4
A11: Total supplier lines | B11: =SUM(B4:B10) -> 23 | C11: =SUM(C4:C10) -> 7 | D11: =SUM(D4:D10) -> 8 | E11: =SUM(E4:E10) -> 2 | F11: =SUM(F4:F10) -> 4 | G11: =SUM(G4:G10) -> 0 | H11: =SUM(H4:H10) -> 18 | I11: =SUM(I4:I10) -> 44 | J11: =SUM(J4:J10) -> 106
A13: By evidence confidence / priority match
A14: Segment | B14: High | C14: Medium | D14: Low | E14: Pharma / ORS | F14: Nutrition / food / beverage | G14: Not stated in sources
A15: Dextrose/Glucose | B15: =COUNTIFS('All Supplier Lines'!$F$2:$F$107,$A15,'All Supplier Lines'!$Y$2:$Y$107,B$14) -> 3 | C15: =COUNTIFS('All Supplier Lines'!$F$2:$F$107,$A15,'All Supplier Lines'!$Y$2:$Y$107,C$14) -> 18 | D15: =COUNTIFS('All Supplier Lines'!$F$2:$F$107,$A15,'All Supplier Lines'!$Y$2:$Y$107,D$14) -> 16 | E15: =COUNTIFS('All Supplier Lines'!$F$2:$F$107,$A15,'All Supplier Lines'!$M$2:$M$107,E$14) -> 28 | F15: =COUNTIFS('All Supplier Lines'!$F$2:$F$107,$A15,'All Supplier Lines'!$M$2:$M$107,F$14) -> 5 | G15: =COUNTIFS('All Supplier Lines'!$F$2:$F$107,$A15,'All Supplier Lines'!$M$2:$M$107,G$14) -> 4
A16: Corn/Maize | B16: =COUNTIFS('All Supplier Lines'!$F$2:$F$107,$A16,'All Supplier Lines'!$Y$2:$Y$107,B$14) -> 1 | C16: =COUNTIFS('All Supplier Lines'!$F$2:$F$107,$A16,'All Supplier Lines'!$Y$2:$Y$107,C$14) -> 9 | D16: =COUNTIFS('All Supplier Lines'!$F$2:$F$107,$A16,'All Supplier Lines'!$Y$2:$Y$107,D$14) -> 3 | E16: =COUNTIFS('All Supplier Lines'!$F$2:$F$107,$A16,'All Supplier Lines'!$M$2:$M$107,E$14) -> 0 | F16: =COUNTIFS('All Supplier Lines'!$F$2:$F$107,$A16,'All Supplier Lines'!$M$2:$M$107,F$14) -> 0 | G16: =COUNTIFS('All Supplier Lines'!$F$2:$F$107,$A16,'All Supplier Lines'!$M$2:$M$107,G$14) -> 0
A17: PET Resin | B17: =COUNTIFS('All Supplier Lines'!$F$2:$F$107,$A17,'All Supplier Lines'!$Y$2:$Y$107,B$14) -> 0 | C17: =COUNTIFS('All Supplier Lines'!$F$2:$F$107,$A17,'All Supplier Lines'!$Y$2:$Y$107,C$14) -> 6 | D17: =COUNTIFS('All Supplier Lines'!$F$2:$F$107,$A17,'All Supplier Lines'!$Y$2:$Y$107,D$14) -> 1 | E17: =COUNTIFS('All Supplier Lines'!$F$2:$F$107,$A17,'All Supplier Lines'!$M$2:$M$107,E$14) -> 1 | F17: =COUNTIFS('All Supplier Lines'!$F$2:$F$107,$A17,'All Supplier Lines'!$M$2:$M$107,F$14) -> 6 | G17: =COUNTIFS('All Supplier Lines'!$F$2:$F$107,$A17,'All Supplier Lines'!$M$2:$M$107,G$14) -> 0
A18: PET Bottles & Preforms | B18: =COUNTIFS('All Supplier Lines'!$F$2:$F$107,$A18,'All Supplier Lines'!$Y$2:$Y$107,B$14) -> 0 | C18: =COUNTIFS('All Supplier Lines'!$F$2:$F$107,$A18,'All Supplier Lines'!$Y$2:$Y$107,C$14) -> 5 | D18: =COUNTIFS('All Supplier Lines'!$F$2:$F$107,$A18,'All Supplier Lines'!$Y$2:$Y$107,D$14) -> 14 | E18: =COUNTIFS('All Supplier Lines'!$F$2:$F$107,$A18,'All Supplier Lines'!$M$2:$M$107,E$14) -> 12 | F18: =COUNTIFS('All Supplier Lines'!$F$2:$F$107,$A18,'All Supplier Lines'!$M$2:$M$107,F$14) -> 2 | G18: =COUNTIFS('All Supplier Lines'!$F$2:$F$107,$A18,'All Supplier Lines'!$M$2:$M$107,G$14) -> 5
A19: Caps & Closures | B19: =COUNTIFS('All Supplier Lines'!$F$2:$F$107,$A19,'All Supplier Lines'!$Y$2:$Y$107,B$14) -> 0 | C19: =COUNTIFS('All Supplier Lines'!$F$2:$F$107,$A19,'All Supplier Lines'!$Y$2:$Y$107,C$14) -> 13 | D19: =COUNTIFS('All Supplier Lines'!$F$2:$F$107,$A19,'All Supplier Lines'!$Y$2:$Y$107,D$14) -> 6 | E19: =COUNTIFS('All Supplier Lines'!$F$2:$F$107,$A19,'All Supplier Lines'!$M$2:$M$107,E$14) -> 18 | F19: =COUNTIFS('All Supplier Lines'!$F$2:$F$107,$A19,'All Supplier Lines'!$M$2:$M$107,F$14) -> 0 | G19: =COUNTIFS('All Supplier Lines'!$F$2:$F$107,$A19,'All Supplier Lines'!$M$2:$M$107,G$14) -> 1
A20: BOPET base film | B20: =COUNTIFS('All Supplier Lines'!$F$2:$F$107,$A20,'All Supplier Lines'!$Y$2:$Y$107,B$14) -> 0 | C20: =COUNTIFS('All Supplier Lines'!$F$2:$F$107,$A20,'All Supplier Lines'!$Y$2:$Y$107,C$14) -> 7 | D20: =COUNTIFS('All Supplier Lines'!$F$2:$F$107,$A20,'All Supplier Lines'!$Y$2:$Y$107,D$14) -> 0 | E20: =COUNTIFS('All Supplier Lines'!$F$2:$F$107,$A20,'All Supplier Lines'!$M$2:$M$107,E$14) -> 1 | F20: =COUNTIFS('All Supplier Lines'!$F$2:$F$107,$A20,'All Supplier Lines'!$M$2:$M$107,F$14) -> 6 | G20: =COUNTIFS('All Supplier Lines'!$F$2:$F$107,$A20,'All Supplier Lines'!$M$2:$M$107,G$14) -> 0
A21: Laminate converters | B21: =COUNTIFS('All Supplier Lines'!$F$2:$F$107,$A21,'All Supplier Lines'!$Y$2:$Y$107,B$14) -> 0 | C21: =COUNTIFS('All Supplier Lines'!$F$2:$F$107,$A21,'All Supplier Lines'!$Y$2:$Y$107,C$14) -> 4 | D21: =COUNTIFS('All Supplier Lines'!$F$2:$F$107,$A21,'All Supplier Lines'!$Y$2:$Y$107,D$14) -> 0 | E21: =COUNTIFS('All Supplier Lines'!$F$2:$F$107,$A21,'All Supplier Lines'!$M$2:$M$107,E$14) -> 4 | F21: =COUNTIFS('All Supplier Lines'!$F$2:$F$107,$A21,'All Supplier Lines'!$M$2:$M$107,F$14) -> 0 | G21: =COUNTIFS('All Supplier Lines'!$F$2:$F$107,$A21,'All Supplier Lines'!$M$2:$M$107,G$14) -> 0
A23: Unique companies | B23: =COUNTA(Companies!$A$2:$A$98) -> 97
A24: Companies in 2+ categories | B24: =COUNTIF(Companies!$J$2:$J$98,">1") -> 9
A25: Source links (all lines) | B25: =COUNTA(Sources!$D$2:$D$323) -> 322
A27: Note: 'Priority match' is a keyword flag from the recorded applications/grades/notes text, not a qualification. Maize rows are counted as upstream inputs.

Sheet Companies
A1: Company ID | B1: Company (legal / registered name) | C1: Trade / brand name | D1: Legal name verified | E1: Website | F1: HQ | G1: Country | H1: Region | I1: Material categories supported | J1: No. of categories | K1: Roles | L1: Ownership | M1: Capacity (published) | N1: Revenue (published) | O1: Credit rating | P1: Certifications (as stated) | Q1: Best evidence confidence | R1: No. of sources | S1: Sources
A2: C0001 | B2: Ahimsa Industries Limited | C2: Ahimsa Industries | D2: No | G2: India | H2: India-West | I2: PET Bottles & Preforms | J2: 1 | K2: Manufacturer (claims, unverified) | Q2: Low | R2: 2 | S2: https://www.dial4trade.com/ahimsa-industries/pet-preforms-pdid-744484.htm https://petpla.net/wikipetia/index.php/Ahmisa_Industries_Limited
A3: C0002 | B3: Amcor (India operations; registered entity not verified) | C3: Amcor India | D3: No | E3: https://www.amcor.com | F3: India | G3: India | H3: India-Pan | I3: Laminate converters | J3: 1 | K3: Converter | L3: MNC subsidiary - Amcor group; acquired Phoenix Flexibles (Packaging Gateway headline) | Q3: Medium | R3: 4 | S3: https://packagingsouthasia.com/packaging-production/amcor-india-opens-seventh-plant-in-india-at-bharuch https://www.packaging-gateway.com/news/amcor-acquire-phoenix-flexibles/ https://esmmagazine.com/packaging-design/amcor-acquires-flexible-packaging-plant-in-india-247427 https://www.petnology.com/online/news-detail/amcor-announces-acquisition-of-scalable-flexible-packaging-plant-in-high-growth-indian-market
A4: C0003 | B4: Apollo Healthcare Resources | D4: No | F4: Singapore | G4: Singapore | H4: International | I4: Dextrose/Glucose | J4: 1 | K4: Distributor | P4: GMP, CEP, USDMF, JDMF, KDMF, WC, EDMF/ASMF, FDA, ISO 9001, BSE/TSE (as listed on PharmaOffer; not verified) | Q4: Low | R4: 1 | S4: https://pharmaoffer.com/api-excipient-supplier/dextrose-anhydrate/cep
A5: C0004 | B5: Aptar Pharma India Private Limited | C5: Aptar Pharma | D5: No | E5: https://aptar.com | F5: Mumbai, Maharashtra, India | G5: India | H5: India-West | I5: Caps & Closures | J5: 1 | K5: Manufacturer | L5: MNC subsidiary of AptarGroup Inc. (NYSE: ATR) | Q5: Medium | R5: 3 | S5: https://m.indiamart.com/aptar/aboutus.html https://www.indianpharmapost.com/news/aptar-expands-mumbai-operations-as-it-adds-local-production-of-pharma-inhalation-tech-22137 https://www.packaginginsights.com/news/aptar-pharma-expands-presence-in-india.html
A6: C0005 | B6: AptarGroup, Inc. | C6: Aptar Pharma | D6: No | E6: https://www.aptar.com | F6: Crystal Lake, Illinois, USA | G6: USA | H6: International | I6: Caps & Closures | J6: 1 | K6: Manufacturer | L6: Listed (NYSE: ATR) | Q6: Low | R6: 1 | S6: https://www.aptar.com/pharmaceutical/technologies/child-resistant-senior-friendly/
A7: C0006 | B7: Archer-Daniels-Midland Company | C7: ADM (CLINTOSE®) | D7: No | E7: https://www.adm.com | F7: Chicago, Illinois, USA | G7: USA | H7: International | I7: Dextrose/Glucose | J7: 1 | K7: Manufacturer | L7: Listed – NYSE: ADM (general knowledge) | Q7: Medium | R7: 3 | S7: https://www.tilleydistributionproducts.com/products/clintose-dextrose-a https://tilleydistributionproducts.com/products/clintose-dextrose-vf https://knowde.com/stores/adm/products/adm-dextrose-monohydrate
A8: C0007 | B8: Arshine Pharmaceutical Co., Limited | C8: Arshine | D8: No | F8: China | G8: China | H8: International | I8: Dextrose/Glucose | J8: 1 | K8: Distributor; Exporter | P8: GMP, CEP, USDMF, EDMF/ASMF, FDA, BSE/TSE (as listed on PharmaOffer; not verified) | Q8: Low | R8: 1 | S8: https://pharmaoffer.com/api-excipient-supplier/dextrose-anhydrate/cep
A9: C0008 | B9: Avantor, Inc. | C9: VWR / J.T.Baker® / Macron Fine Chemicals™ | D9: No | E9: https://www.avantorsciences.com | F9: Pennsylvania, USA | G9: USA | H9: International | I9: Dextrose/Glucose | J9: 1 | K9: Supplier/repackager (J.T.Baker brand); Distributor (VWR) | L9: Listed – NYSE: AVTR (general knowledge) | Q9: Medium | R9: 4 | S9: https://b2b-ca.vwr.com/store/product/en/4541456/dextrose-anhydrous-97-5-102-0-by-anhydrous-basis-usp-multi-compendial-j-t-baker https://b2b-us.vwr.com/store/product/4541456/null https://b2b-cn.vwr.com/store/product/8030185/null https://www.avantorsciences.com/pt/en/search/USLP070318BIOP00008
A10: C0009 | B10: BERICAP GmbH & Co. KG | C10: Bericap | D10: No | E10: https://bericap.com | F10: Budenheim, Germany | G10: Germany | H10: International | I10: Caps & Closures | J10: 1 | K10: Manufacturer | L10: Private | Q10: Medium | R10: 3 | S10: https://bericap.com/home-care-pharma-supplies/landingpage-otc-pharmaceuticals/ https://www.packaging-gateway.com/products/bericap-closure-solutions-home-care-pharma-supplies/ https://packagingeurope.com/bericap-presents-closure-solutions-at-packaging-innovations/5782.article
A11: C0010 | B11: Bericap India Private Limited | C11: BERICAP | D11: Yes | E11: https://bericap.com | F11: Pune, Maharashtra, India (RoC Pune per CIN) | G11: India | H11: India-West | I11: Caps & Closures | J11: 1 | K11: Manufacturer | L11: MNC subsidiary of BERICAP GmbH & Co. KG (Germany); former JV with Essel Propack, Bericap acquired Essel's stake | M11: Trade press (Aug 2018) reported Bericap doubling its India plant; figure not captured | Q11: Medium | R11: 4 | S11: https://www.InstaFinancials.com/company/bericap-india-private-limited/U25202PN2001PTC140929 https://www.plasticsnews.com/article/20180828/NEWS/180829902/bericap-doubling-india-plant/ https://www.plastemart.com/news-plastics-information/bericap-to-acquire-essel-propack´s-share-in-indian-jv/8930 https://bericap.com/product/hc-ev-28-27-pco-1881/
A12: C0011 | B12: Berlin Packaging | C12: Berlin Packaging EU | D12: No | E12: https://berlinpackaging.eu | F12: Chicago, Illinois, USA | G12: USA | H12: International | I12: Caps & Closures | J12: 1 | K12: Distributor | Q12: Low | R12: 1 | S12: https://berlinpackaging.eu/en-be/markets/healthcare/packaging/child-resistant-closures
A13: C0012 | B13: Berry Global, Inc. | C13: Berry Global Healthcare | D13: No | E13: https://www.berryglobal.com | F13: Evansville, Indiana, USA | G13: USA | H13: International | I13: Caps & Closures | J13: 1 | K13: Manufacturer | L13: Berry Global Group, Inc. (SEC registrant, CIK 1378992). Berry agreed a merger with Amcor in 2024-25; current ownership status not verified in this session. | Q13: Medium | R13: 5 | S13: https://www.berryglobal.com/en/product/product-item/13191479 https://www.berryglobal.com/en/product/product-item/13567185 https://packagingeurope.com/news/berry-global-offers-range-of-pet-bottle-and-closure-solutions-for-child-safe-and-tamper-evident-medicine-packaging/9429.article https://packagingscotland.com/2023/02/berry-group-healthcare-launches-comprehensive-new-child-resistant-range/ https://www.sec.gov/Archives/edgar/data/0001378992/000137899218000039/form10k.htm
A14: C0013 | B14: Biesterfeld AG | C14: Biesterfeld | D14: No | E14: https://www.biesterfeld.com | F14: Hamburg, Germany | G14: Germany | H14: International | I14: Dextrose/Glucose | J14: 1 | K14: Distributor | Q14: Medium | R14: 2 | S14: https://www.biesterfeld.com/en/gb/product/dextrose-glucose https://www.biesterfeld.com/en/at/product/dextrose-glucose/
A15: C0014 | B15: Cargill S.L.U. | C15: Cargill | D15: No | E15: https://www.cargill.com/pharmaceutical/pharma-products/glucose-monohydrates-dextrose | F15: Spain | G15: Spain | H15: International | I15: Dextrose/Glucose | J15: 1 | K15: Manufacturer | L15: Subsidiary of Cargill, Incorporated (USA, private) | P15: CEP (glucose monohydrate), FDA, CoA – as listed on PharmaOffer (third-party listing) | Q15: Medium | R15: 5 | S15: https://pharmaoffer.com/api-excipient-supplier/excipients/glucose-monohydrate/cep https://pharmaoffer.com/api-excipient-supplier/glucose-monohydrate/cep https://www.cargill.com/pharmaceutical/pharma-products/glucose-monohydrates-dextrose https://www.cargill.com/products/pharmaceutical/products/glucose-monohydrates/ https://pharmacompass.com/ndc-api/cargill-slu
A16: C0015 | B16: Cargill, Incorporated | C16: Cargill (C*Dex) | D16: No | E16: https://www.cargill.com | F16: Minnesota, USA | G16: USA | H16: International | I16: Dextrose/Glucose | J16: 1 | K16: Manufacturer | L16: Private (general knowledge) | Q16: Medium | R16: 2 | S16: https://www.cargill.com/food-bev/emea/c-dex-dextrose https://www.cargill.com/food-bev/ap/dextrose
A17: C0016 | B17: Chemco Plastic Industries | C17: Chemco Group | Chemco | D17: No | E17: https://www.chemcogroup.com | G17: India | H17: India-West | I17: PET Bottles & Preforms; PET Resin | J17: 2 | K17: Manufacturer; Recycler | Recycler | L17: Private group (Chemco Group) | P17: FSSAI approval for food-grade rPET (trade press headline 'Chemco gets FSSAI nod') | Q17: Medium | R17: 7 | S17: https://www.packaginginsights.com/news/chemco-pet-bottle-recycling-india.html https://www.plastemart.com/news-plastics-information/chemco-group-pioneering-circularity-with-in-house-rpet-production/75112 https://www.industrialautomationindia.in/news/chemco-group-food-grade-rpet-facility-sanand https://themachinemaker.com/news/chemco-group-launches-%e2%82%b9125-crore-food-grade-rpet-bottle-recycling-plant-in-gujarat/ https://packagingsouthasia.com/type-of-article/industry-news/chemco-gets-fssai-nod/ https://m.indiamart.com/chemcoplastic https://www.packaging-gateway.com/news/chemco-gujarat-rpet-recycling-plant/
A18: C0017 | B18: Chr. Olesen | C18: Chr. Olesen | D18: No | F18: Denmark | G18: Denmark | H18: International | I18: Dextrose/Glucose | J18: 1 | K18: Distributor | P18: FDA, USDMF, CoA listed; Eurofins GMP audit report Sep 2023 (PharmaOffer listing) | Q18: Low | R18: 2 | S18: https://pharmaoffer.com/api-excipient-supplier/excipients/glucose-monohydrate/cep https://pharmaoffer.com/api-excipient-supplier/glucose-monohydrate/cep
A19: C0018 | B19: Closure Systems International | C19: CSI | D19: No | H19: International | I19: Caps & Closures | J19: 1 | K19: Manufacturer | Q19: Medium | R19: 3 | S19: https://www.packaginginsights.com/news/closure-systems-international-child-resistant-closure.html https://www.silicon.co.uk/press-release/closure-systems-international-launches-defender-lok-crc-product-line https://finance.yahoo.com/news/closure-systems-international-introduces-child-142709276.html
A20: C0019 | B20: Comar | C20: Comar | D20: No | G20: USA | H20: International | I20: Caps & Closures | J20: 1 | K20: Manufacturer | Q20: Medium | R20: 3 | S20: https://www.healthcarepackaging.com/industries/pharmaceuticals/press-release/13287374/comar-childresistant-closures https://app.qualifyze.com/directory/supplier/comar-71f904da https://directory.designnews.com/comar-inc-comp225738.html
A21: C0020 | B21: Constantia Flexibles (India operations; registered entity not verified) | C21: Constantia Flexibles | D21: No | E21: https://cflex.com | F21: Ahmedabad, Gujarat, India | G21: India | H21: India-West | I21: Laminate converters | J21: 1 | K21: Converter | L21: MNC subsidiary - Constantia Flexibles group | Q21: Medium | R21: 6 | S21: https://cflex.com/newsroom/constantia-flexibles-to-expand-production-capacity-in-india https://www.printweek.in/News/constantia-flexibles-invest-rs-100-crore-ahmedabad-plant-28024 https://packagingsouthasia.com/packaging-production/constantia-flexibles-to-invest-inr-100-crore-in-a-new-india-plant/ https://www.dcatvci.org/?p=6358 https://www.packaging-gateway.com/news/constantia-flexibles-expand-production-capacity-indian-facility/ https://www.packaging-gateway.com/projects/parikhpackagingfacil/
A22: C0021 | B22: Cosmos (Grupo Cosmos) | C22: Cosmos | D22: No | E22: https://www.cosmos.com.mx | F22: Mexico | G22: Mexico | H22: International | I22: Dextrose/Glucose | J22: 1 | K22: Distributor | Q22: Medium | R22: 1 | S22: https://www.cosmos.com.mx/producto/dextrosa-4bfp/dextrosa-anhidra-d7jd/dextrosa-anhidra-grado-farmaceutico-ddbs/
A23: C0022 | B23: Crystal Polymers | D23: No | E23: https://m.indiamart.com/crystal-poly/ | G23: India | H23: India-South | I23: PET Bottles & Preforms | J23: 1 | K23: Manufacturer (claimed on B2B listing; not verified) | Q23: Low | R23: 1 | S23: https://m.indiamart.com/crystal-poly/profile.html
A24: C0023 | B24: CSPC Shengxue Glucose Co., Ltd. | C24: CSPC Shengxue (石药圣雪) | D24: No | F24: Hebei, China | G24: China | H24: International | I24: Dextrose/Glucose | J24: 1 | K24: Manufacturer | L24: CSPC group company (CSPC Pharmaceutical Group is HKEX-listed, 1093 – general knowledge; current shareholding not verified) | P24: US DMF (PharmaCompass listing) | Q24: Medium | R24: 3 | S24: https://pharmacompass.com/us-drug-master-files-dmfs/anhydrous-dextrose https://www.pharmacompass.com/about/cspc-shengxue-glucose https://doc.irasia.com/listco/hk/cspc/annual/2018/screspress.pdf
A25: C0024 | B25: Dalmia Polypro Industries Private Limited | C25: Dalmia Polypro | D25: No | G25: India | H25: India-Pan | I25: PET Resin | J25: 1 | K25: Recycler | L25: Private; investee of Circulate Capital (2020); raising USD 30 mn from US DFC | Q25: Medium | R25: 5 | S25: https://www.erema.com/en/public-relations-news/dalmia-polypro-to-install-erema-systems-for-pet-und-fuer-po-recycling--3233/ https://packagingsouthasia.com/application/dalmia-polypros-food-grade/ https://www.outlookbusiness.com/news/dalmia-polypro-to-raise-usd-30-mn-from-us-dfc-to-build-facility-in-maharashtra https://www.circulatecapital.com/wp-content/uploads/2022/12/DalmiaPolyproIndustriesPL-x-CC_-Press-Release_2020-12-10-.pdf https://www.packaging-gateway.com/news/slmg-dalmia-india-plant/
A26: C0025 | B26: Drug Plastics & Glass Company, Inc. | C26: Drug Plastics | D26: Yes | G26: USA | H26: International | I26: Caps & Closures | J26: 1 | K26: Manufacturer | Q26: Low | R26: 3 | S26: https://trademarks.justia.com/owners/drug-plastics-glass-company-inc-135913 https://www.pharmaceutical-tech.com/suppliers/drug-plastics-glass-co-inc https://niemagazine.com/resources/sourcebook/6455/drug-plastics-glass-co-inc/
A27: C0026 | B27: EICL Limited | C27: Bharat Starch Industries (starch division); 'Haathi' brand | D27: Yes | E27: https://eicl.in | F27: Gurugram, Haryana, India (office listed on company site) | G27: India | H27: India-North | I27: Corn/Maize | J27: 1 | K27: Processor (starch wet-miller); Manufacturer | L27: Thapar Group lineage; Indian Starch & Chemicals Ltd (1937), later renamed Bharat Starch Industries Ltd, became part of EICL in 2001 (company page) | M27: 80,000 MTPA starch processing base, multi-feedstock (company page, dated (c)2015) | Q27: Medium | R27: 2 | S27: https://eicl.in/?p=284 https://eicl.in/?p=572
A28: C0027 | B28: Elchemy | C28: Elchemy | D28: No | E28: https://elchemy.com/ | F28: India | G28: India | H28: India-Pan | I28: Dextrose/Glucose | J28: 1 | K28: Distributor; Marketplace/platform | L28: Private | Q28: Low | R28: 1 | S28: https://elchemy.com/product/dextrose-monohydrate-1509
A29: C0028 | B29: Ester Industries Limited | C29: Ester | D29: Yes | E29: https://www.esterindustries.com | G29: India | H29: India-Pan | I29: BOPET base film | J29: 1 | K29: Manufacturer | L29: Listed (NSE: ESTER) | O29: CRISIL - rationales dated 13 May 2024 and 22 Jul 2025 (rating level not read this run) | Q29: Medium | R29: 2 | S29: https://www.crisil.com/mnt/winshare/Ratings/RatingList/RatingDocs/EsterIndustriesLimited_July 22_ 2025_RR_374336.html https://www.crisil.com/mnt/winshare/Ratings/RatingList/RatingDocs/EsterIndustriesLimited_May 13_ 2024_RR_343559.html
A30: C0029 | B30: Ganesha Ecosphere Limited | C30: GO Rewise | D30: No | G30: India | H30: India-Pan | I30: PET Resin | J30: 1 | K30: Recycler; Manufacturer | L30: Listed (NSE: GANECOS) | Q30: Medium | R30: 4 | S30: https://nsearchives.nseindia.com/corporate/GANECOS_03092025232921_annual_report.pdf https://recyclinginside.com/news/bottle-to-fibre-and-bottle-to-bottle-two-starlinger-pet-recycling-lines-for-indian-recycling-brand-go-rewise/ https://www.wasterecyclingmag.com/news/plastic-recycling/bottle-to-fibre-and-bottle-to-bottle-two-starlinger-pet-recycling-lines-for-indian-recycling-brand-go-rewise https://www.innovationintextiles.com/trailblazing-pet-recycling-in-india
A31: C0030 | B31: Garware Hi-Tech Films Limited | C31: Garware | D31: Yes | E31: https://www.garwarehitechfilms.com | G31: India | H31: India-West | I31: BOPET base film | J31: 1 | K31: Manufacturer | L31: Listed (NSE: GRWRHITECH) | Q31: Medium | R31: 2 | S31: https://machinist.in/2025/09/garware-hi-tech-films-starts-commercial-production-of-new-ppf-line-at-waluj-facility/ https://www.garwarehitechfilms.com/wp-content/uploads/2023/03/Investors-Presentation-May-2021.pdf.pdf
A32: C0031 | B32: Gerresheimer (India operations) | C32: Gerresheimer | D32: No | E32: https://www.gerresheimer.com | F32: Düsseldorf, Germany (India operations) | G32: Germany | H32: India-Pan | I32: Caps & Closures | J32: 1 | K32: Manufacturer | L32: MNC; Gerresheimer AG (listed, Frankfurt) | Q32: Medium | R32: 1 | S32: https://gerresheimer.com/en/company/newsroom/corporate-news/detail/cphi-india-gerresheimer-customers-value-child-resistant-pharmaceutical-packaging-1
A33: C0032 | B33: Global Closure Systems | C33: GCS | D33: No | H33: International | I33: Caps & Closures | J33: 1 | K33: Manufacturer | Q33: Medium | R33: 4 | S33: https://manufacturingchemist.com/global-closure-systems-gcs-launches-pharmasafe-child-resistant-closure-91334 https://www.healthcarepackaging.com/home/press-release/13290585/global-closure-systems-exhibits-at-pharmapack-europe-2016 https://pharmtech.com/view/global-closure-systems-exhibits-cphi-2015 https://www.plasteurope.com/news/GLOBAL_CLOSURE_SYSTEMS_t228478
A34: C0033 | B34: Guala Closures S.p.A. | C34: Guala Closures | D34: Yes | E34: https://www.gualaclosures.com | F34: Alessandria, Italy | G34: Italy | H34: International | I34: Caps & Closures | J34: 1 | K34: Manufacturer | Q34: Medium | R34: 4 | S34: https://www.gualaclosures.com/pharma https://www.gualaclosures.com/sites/default/files/files/allegati/2025-10/PR%20-%20GUALA%20CLOSURES%20ENTERS%20INTO%20PHARMACEUTICAL%20CLOSURES%20MARKET%20_%20Final.pdf https://www.gualaclosures.com/guala-closures-pharmapack-kwk-strengthening-its-presence-pharmaceutical-sector https://www.wolftheiss.com/insights/wolf-theiss-advises-guala-closures-s-p-a-on-the-acquisition-of-austrian-packaging-company-kunststoffwerk-kremsmunster-gmbh/
A35: C0034 | B35: Gujarat Ambuja Exports Limited | C35: GAEL / Ambuja Group | D35: Yes | E35: https://www.ambujagroup.com/ | F35: Ahmedabad, Gujarat, India | G35: India | H35: India-West | I35: Corn/Maize; Dextrose/Glucose | J35: 2 | K35: Manufacturer; Processor (maize wet-miller) | Processor (maize wet-miller); Manufacturer | L35: Listed (NSE: GAEL; BSE) | Listed (NSE: GAEL; BSE: 524226) | M35: New 1,200 TPD maize processing unit commenced commercial production Mar-2025 (NSE filing title); group total not verified this session | O35: CARE press releases Jan-2025, Aug-2025, Sep-2025, Dec-2025 and CRISIL rationales Apr-2023 exist; ratings not read (fetch rate-limited) | P35: Certificates page exists on company site (contents not read) | Q35: High | R35: 7 | S35: https://www.ambujagroup.com/ https://www.ambujagroup.com/starch-derivatives https://www.ambujagroup.com/dextrose-anhydrous-powder https://www.ambujagroup.com/dextrose-monohydrate-powder https://www.wrightresearch.in/stocks/stock/GAEL/ https://nsearchives.nseindia.com/corporate/GAEL_26032025100331_Commercial_Production_1200TPD_Maize.pdf https://www.careratings.com/upload/CompanyFiles/PR/202512121257_Gujarat_Ambuja_Exports_Limited.pdf
A36: C0035 | B36: Gulshan Polyols Limited | C36: Gulshan Polyols | D36: Yes | G36: India | H36: India-North | I36: Corn/Maize | J36: 1 | K36: Processor (starch wet-miller); Manufacturer | L36: Listed (BSE: 532457) | M36: 300 TPD corn grinding (UP); planned 1,000 TPD maize grinding (Bihar); ethanol 560 KLPD+ total (Assam 500 KLPD added June 2024) | Q36: Medium | R36: 3 | S36: https://www.indiainfoline.com/company/gulshan-polyols-ltd/summary https://www.gurufocus.com/stock/BOM:532457/transcripts/8616616 https://www.plindia.com/stocks/gulshan-polyols-ltd/
A37: C0036 | B37: Harsh Impex | D37: No | F37: Odisha, India | G37: India | H37: India-East | I37: PET Bottles & Preforms | J37: 1 | K37: Claims manufacturer (B2B listing only; plant not verified) | Q37: Low | R37: 3 | S37: https://www.globallinker.com/products/trusted-pet-preform-manufacturers-in-odisha-harsh-impex-best-price-8457231 https://www.globallinker.com/seller/harsh-impex https://yourstory.com/companies/harsh-impex
A38: C0037 | B38: Hawkins, Inc. | C38: Hawkins | D38: No | E38: https://www.hawkinsinc.com | F38: Minnesota, USA | G38: USA | H38: International | I38: Dextrose/Glucose | J38: 1 | K38: Distributor (page titled 'Dextrose Manufacturer, Supplier & Distributor'; own dextrose production not verified) | L38: Listed – NASDAQ: HWKN (general knowledge) | Q38: Medium | R38: 1 | S38: https://www.hawkinsinc.com/groups/pharmaceutical/dextrose/
A39: C0038 | B39: Hitesh Plastics | C39: Hitesh Plastics | D39: No | F39: India (location not verified this session) | G39: India | H39: India-West; India-Pan | I39: Caps & Closures; PET Bottles & Preforms | J39: 2 | K39: Manufacturer | L39: Acquired by Manjushree Technopack (Advent International-backed), 2022 | Acquired by Manjushree Technopack Ltd (Advent International-backed), Aug 2022 per petpla.net/PrintWeek | Q39: Medium | R39: 6 | S39: https://news.ventureintelligence.com/ma/manjushree-technopack-to-acquire-caps-maker-hitesh-plastics https://www.printweek.in/News/manjushree-technopack-backed-by-advent-to-acquire-hitesh-plastics-56469 https://www.petnology.com/online/news-detail/manjushree-technopack-acquires-hitesh-plastics https://www.printweek.in/news/manjushree-technopack-backed-by-advent-to-acquire-hitesh-plastics-56469 https://petpla.net/2022/08/08/manjushree-technopack-acquires-hitesh-plastics/ https://packagingsouthasia.com/type-of-article/manjushree-technopack-plant/
A40: C0039 | B40: Huhtamaki India Limited | C40: Huhtamaki India (formerly Huhtamaki PPL) | D40: No | E40: https://www.huhtamaki.com/en/flexible-packaging/about-us/india/ | F40: Thane, Maharashtra, India | G40: India | H40: India-West | I40: Laminate converters | J40: 1 | K40: Converter | L40: Listed in India (NSE: HUHTAMAKI per Morningstar listing URL); part of the Huhtamaki group (company India page on huhtamaki.com) | Q40: Medium | R40: 5 | S40: https://www.huhtamaki.com/en/flexible-packaging/about-us/india/ https://www.plastemart.com/news-plastics-information/huhtamaki-india-limited-a-leading-flexible-packaging-converter-for-fmcg-and-food-brands/75108 https://en.wikipedia.org/wiki/Huhtamaki_PPL https://dfd.dr.morningstar.com.au/investments/security/NSE/HUHTAMAKI https://production.huhtamaki.com/en-in/flexible-packaging
A41: C0040 | B41: Hänseler AG | C41: Hänseler | D41: No | F41: Switzerland | G41: Switzerland | H41: International | I41: Dextrose/Glucose | J41: 1 | K41: Distributor; CDMO (per listing) | P41: GMP, FDA, MSDS, CoA (PharmaOffer listing) | Q41: Low | R41: 1 | S41: https://pharmaoffer.com/api-excipient-supplier/glucose-anhydrous
A42: C0041 | B42: Ingredion Incorporated | C42: Ingredion (CERELOSE®); Ingredion Pharma Solutions | D42: No | E42: https://www.ingredion.com | F42: Westchester, Illinois, USA | G42: USA | H42: International | I42: Dextrose/Glucose | J42: 1 | K42: Manufacturer | L42: Listed – NYSE: INGR (general knowledge) | P42: US DMF (PharmaCompass listing) | Q42: High | R42: 3 | S42: https://ingredion.com/content/dam/ingredion/technical-documents/na/CERELOSE%20Anhydrous%20Dextrose%20024010%20Technical%20Specification.pdf https://pharmacompass.com/us-drug-master-files-dmfs/anhydrous-dextrose https://pharmaoffer.com/api-excipient-supplier/company/ingredion
A43: C0042 | B43: Innopac Packagings | C43: Petainer | D43: No | G43: India | H43: India-West | I43: PET Bottles & Preforms | J43: 1 | K43: Manufacturer | Q43: Low | R43: 1 | S43: https://packagingsouthasia.com/zarchive/petainer-innopac-packagings-plant-at-bhiwandi/
A44: C0043 | B44: IVL Dhunseri Petrochem Industries Private Limited | C44: IVL Dhunseri | D44: Yes | E44: https://www.indoramaventures.com/en/worldwide/2001/ivl-dhunseri-petrochem-industries-private-limited | G44: India | H44: India-East | I44: PET Resin | J44: 1 | K44: Manufacturer | L44: JV of Indorama Ventures PCL (Thailand) and Dhunseri group; the legal name appears on Indorama's worldwide-sites page | Q44: Medium | R44: 3 | S44: https://www.indoramaventures.com/en/worldwide/2001/ivl-dhunseri-petrochem-industries-private-limited https://www.textileworld.com/textile-world/fiber-world/2016/02/indorama-ventures-and-dhunseri-form-joint-venture-in-india/ https://chemengonline.com/indorama-to-form-pet-manufacturing-joint-venture-in-india
A45: C0044 | B45: Jay Somnath Starch Product | D45: Yes | E45: https://www.jaysomnathstarch.in/ | F45: Rajkot, Gujarat, India | G45: India | H45: India-West | I45: Dextrose/Glucose | J45: 1 | K45: Manufacturer (claimed on own site; crystallisation plant not verified) | L45: Private firm (GSTIN 24AASFJ8076F1ZX; PAN pattern indicates a partnership firm) | Q45: Low | R45: 3 | S45: https://www.jaysomnathstarch.in/dextrose-anhydrous-powder.htm https://www.jaysomnathstarch.in/dextrose-monohydrate-powder.htm https://piceapp.com/gst-number-search/jay-somnath-starch-product-24aasfj8076f1zx/
A46: C0045 | B46: Jindal Poly Films Limited | C46: Jindal Poly Films | D46: Yes | E46: https://www.jindalpoly.com | G46: India | H46: India-Pan | I46: BOPET base film | J46: 1 | K46: Manufacturer | L46: Listed (NSE: JINDALPOLY) | O46: CRISIL - rationales dated 30 May 2025, 18 May 2026, 14 Aug 2026 (rating level not read this run) | Q46: Medium | R46: 2 | S46: https://www.crisil.com/mnt/winshare/Ratings/RatingList/RatingDocs/JindalPolyFilmsLimited_August 14_ 2026_RR_401765.html https://www.crisil.com/mnt/winshare/Ratings/RatingList/RatingDocs/JindalPolyFilmsLimited_May 18_ 2026_RR_395327.html
A47: C0046 | B47: Kunststoffwerk Kremsmünster GmbH | C47: KWK | D47: Yes | E47: https://www.kwk.at | F47: Kremsmünster, Austria | G47: Austria | H47: International | I47: Caps & Closures | J47: 1 | K47: Manufacturer | L47: Acquired by Guala Closures S.p.A. (2025) | N47: c. EUR 18 million over 12 months (per Il Giornale d'Italia report on acquisition, 2025) | Q47: Medium | R47: 4 | S47: https://www.wolftheiss.com/insights/wolf-theiss-advises-guala-closures-s-p-a-on-the-acquisition-of-austrian-packaging-company-kunststoffwerk-kremsmunster-gmbh/ https://www.ilgiornaleditalia.it/news/mondo-imprese/739210/guala-closures-acquisisce-kwk-leader-del-settore-del-packaging-farmaceutico-con-ricavi-di-18-milioni-di-euro-in-12-mesi.html https://plasticker.de/Plastics_News_47298_Guala_Closures_Packaging_Specialist_Acquires_KWK_Kunststoffwerk_Kremsmnster__Entry_into_the_Pharmaceutical_Closure_Market https://www.kwk.at/
A48: C0047 | B48: Lab Alley (Laboratory Alley LLC) | C48: Lab Alley | D48: No | E48: https://www.laballey.com | F48: Texas, USA | G48: USA | H48: International | I48: Dextrose/Glucose | J48: 1 | K48: Distributor; Repackager | Q48: Low | R48: 2 | S48: https://www.laballey.com/products/dextrose-monohydrate-fcc-grade-powder https://media.laballey.com/docbuilder/dextrose-monohydrate-fcc-grade-powder-country-of-origin-document-652e9c01db492.pdf
A49: C0048 | B49: Manjushree Technopack Limited | C49: Manjushree | D49: Yes | E49: https://www.manjushreeindia.com | F49: Bengaluru, Karnataka, India | G49: India | H49: India-Pan | I49: Caps & Closures; PET Bottles & Preforms | J49: 2 | K49: Manufacturer | L49: Private; backed by Advent International; acquired Hitesh Plastics (caps maker) 2022 and Oricon Enterprises' plastics packaging business | Private, unlisted (shares trade on unlisted platforms); Advent International exited per an Altius Investech blog title. The current owner was not verified this session. | Private; Advent International-backed (per other team file citing Advent case page; not re-verified here). An IndiaMART storefront at the URL slug 'manjushree-technopark-limited' is titled 'Alternicq Limited - Manufacturer of Plastic Container & Pet Bottles from Bengaluru', and an IndiaInfoline 'alternicq-ltd' summary surfaced in a Manjushree search, suggesting a possible change of name to Alternicq Limited - NOT verified. | Private; backed by Advent International (per PrintWeek headline 'Manjushree Technopack backed by Advent to acquire Hitesh Plastics' and Advent International case page); acquired Hitesh Plastics (2022) | Q49: Medium | R49: 20 | S49: https://manjushreeindia.com/wp-content/uploads/2024/10/Caps-Closures.pdf https://www.manjushreeindia.com/wp-content/uploads/2024/03/Manjushree-Corporate-Presentation.pdf https://news.ventureintelligence.com/ma/manjushree-technopack-to-acquire-caps-maker-hitesh-plastics https://petpla.net/2022/08/08/manjushree-technopack-acquires-hitesh-plastics/ https://manjushreeindia.com/wp-content/uploads/2024/10/Preforms.pdf https://www.manjushreeindia.com/wp-content/uploads/2023/07/MTL-Corporate-Presentation.pdf https://www.printweek.in/news/india-packaging-leader-manjushree-technopack-acquires-delhi-varahi-22700 https://petpla.net/?p=3756 https://packagingsouthasia.com/packaging-production/manjushree-technopack-commissions-new-plant-at-silvassa/ https://www.indiamart.com/manjushree-technopack-ltd/aboutus.html https://altiusinvestech.com/blog/advent-internationals-3x-bagger-a-strategic-exit-from-manjushree-in-5-years/ https://en.wikipedia.org/wiki/Manjushree_Technopack https://www.indiamart.com/manjushree-techno-pack-limited/profile.html https://www.indiamart.com/manjushree-technopark-limited/ https://www.tradeindia.com/Seller-2683598-MANJUSHREE-TECHNOPACK-LTD-/ https://www.tradeindia.com/products/pet-bisleri-bottles-6089274.html https://mysuruinfrahub.com/manjushree-technopack-limited-to-setup-a-plastic-packaging-plant-at-chamarajanagar/ https://www.indiainfoline.com/company/alternicq-ltd/summary https://www.adventinternational.com/ideas/the-endless-life-cycle-of-plastic-manjushree-technopack/ https://sbnri.com/p/pre-ipo/Manjushree-Technopack-Ltd.-jxbE69gV
A50: C0049 | B50: Mark Pack | C50: Markpack | Mark Pack | D50: No | E50: https://m.indiamart.com/markpack | G50: India | H50: India-South | I50: PET Bottles & Preforms | J50: 1 | K50: Manufacturer (claimed on B2B listing; not verified) | Trader (claims manufacturer) | Q50: Low | R50: 5 | S50: https://m.indiamart.com/mark-pack/pet-bottles.html https://m.indiamart.com/markpack/pet-plastic-bottles.html https://m.indiamart.com/markpack/pet-jars.html https://m.indiamart.com/mark-pack/plastic-bottle.html https://m.indiamart.com/markpack
A51: C0050 | B51: Megapet Containers Pvt Ltd | C51: Megapet Containers | D51: No | F51: Pardi, Vapi, Gujarat, India | G51: India | H51: India-West | I51: PET Bottles & Preforms | J51: 1 | K51: Manufacturer (claims, unverified) | Q51: Low | R51: 1 | S51: https://www.indianyellowpages.com/vapi/megapet-containers-pvt-ltd-9175302
A52: C0051 | B52: Monarch Chemicals Ltd | C52: Monarch Chemicals | D52: No | E52: https://www.monarchchemicals.co.uk | F52: United Kingdom | G52: United Kingdom | H52: International | I52: Dextrose/Glucose | J52: 1 | K52: Distributor | Q52: Low | R52: 1 | S52: https://www.monarchchemicals.co.uk/Chemicals/A-to-Z/665-/Dextrose-Monohydrate
A53: C0052 | B53: National Agricultural Cooperative Marketing Federation of India Ltd | C53: NAFED | D53: No | E53: https://www.nafed-india.com | F53: New Delhi, India | G53: India | H53: India-Pan | I53: Corn/Maize | J53: 1 | K53: Cooperative/Government agency; Aggregator | L53: National-level cooperative under Govt of India Ministry of Cooperation | National cooperative under the Multi-State Co-operative Societies Act | M53: Agreed to procure 1 lakh tonnes of maize from Telangana (CropGPT report) | Q53: Medium | R53: 5 | S53: https://iamrenew.com/green-energy/nafed-nccf-can-sell-maize-to-ethanol-makers-at-base-rate/amp https://advancedbiofuelsusa.info/govt-to-buy-maize-at-msp-raise-output-to-meet-biofuel-needs https://www.qcintel.com/biofuels/article/indian-goverment-issues-sop-for-corn-procurement-for-ethanol-output-21584.html https://cropgpt.ai/nafed-agrees-to-procure-1-lakh-tonnes-of-maize-from-telangana-sets-up-procurement-centres-and-assures-minimum-support-price-for-farmers https://www.indiancooperative.com/co-op-news-snippets/price-fall-triggers-msp-push-by-nafed-nccf/
A54: C0053 | B54: National Cooperative Consumers' Federation of India Ltd | C54: NCCF | D54: No | E54: https://nccf-india.com | F54: New Delhi, India | G54: India | H54: India-Pan | I54: Corn/Maize | J54: 1 | K54: Cooperative/Government agency; Aggregator | L54: National-level cooperative (Govt of India) | National cooperative | Q54: Low | R54: 4 | S54: https://iamrenew.com/green-energy/nafed-nccf-can-sell-maize-to-ethanol-makers-at-base-rate/amp https://krishijagran.com/news/maize-to-be-procured-by-govt-at-msp-increased-production-targeted-to-meet-biofuel-requirements/?amp=1 https://www.indiancooperative.com/co-op-news-snippets/price-fall-triggers-msp-push-by-nafed-nccf/ https://www.angelone.in/news/economy/centre-extends-maize-msp-procurement-deadline-for-kharif-2025-26-till-april-30
A55: C0054 | B55: Nishant Mouldings Private Limited | D55: Yes | E55: https://m.indiamart.com/nishantmouldings | G55: India | H55: India-South | I55: PET Bottles & Preforms | J55: 1 | K55: Manufacturer (per company name/listings; plant not verified) | Q55: Low | R55: 3 | S55: https://m.indiamart.com/nishantmouldings https://www.exporthub.com/nishant-mouldings/ https://www.dial4trade.com/nishant-moulding/pet-preforms-pdid-6788384.htm
A56: C0055 | B56: Nordmann, Rassmann GmbH | C56: Nordmann | D56: No | E56: https://www.nordmann.global | F56: Hamburg, Germany | G56: Germany | H56: International | I56: Dextrose/Glucose | J56: 1 | K56: Distributor | Q56: Medium | R56: 1 | S56: https://www.nordmann.global/en/products/dextrose
A57: C0056 | B57: Origin Pharma Packaging | C57: Origin | D57: No | H57: International | I57: Caps & Closures | J57: 1 | K57: Supplier (manufacturing status not verified) | Q57: Low | R57: 3 | S57: https://www.pharmaceutical-technology.com/contractors/packaging/origin/pressreleases/pressorigin-pharma-packaging-child-safety https://pharmaceutical-technology.com/contractors/cleanroom/origin/pressreleases/child-resistant-packaging https://www.pharmaceutical-technology.com/contractors/packaging/origin/
A58: C0057 | B58: Parle Agro | C58: Parle Agro | D58: No | E58: https://parleagro.com/ | F58: Mumbai, Maharashtra, India | G58: India | H58: India-Pan | I58: PET Bottles & Preforms | J58: 1 | K58: Manufacturer (in-house preforms; third-party sale implied by the site page, not verified) | L58: Private | Q58: Low | R58: 1 | S58: https://parleagro.com/preforms
A59: C0058 | B59: PCIPL (pciplindia.com) | C59: PCIPL | D59: No | E59: https://pciplindia.com/ | F59: India (not verified) | G59: India | H59: India-Pan | I59: Dextrose/Glucose | J59: 1 | K59: Distributor (presumed; not verified) | Q59: Low | R59: 1 | S59: https://pciplindia.com/product-detail/dextrose-monohydrate
A60: C0059 | B60: Pearl Polymers Ltd | C60: Pearl Pet | D60: Yes | F60: New Delhi, Delhi, India | G60: India | H60: India-North | I60: PET Bottles & Preforms | J60: 1 | K60: Manufacturer (per trade-press title; not verified this session) | L60: Listed on BSE and NSE (ticker PEARLPOLY); founded 1971 (per Kotak Securities stock page title) | Listed (BSE/NSE: PEARLPOLY); founded 1971 (per Kotak Securities page title) | Q60: Medium | R60: 5 | S60: https://packagingsouthasia.com/packaging-production/pet-pioneer-pearl/ https://www.roic.ai/quote/PEARLPOLY.BO https://www.screener.in/company/PEARLPOLY https://kotaksecurities.com/stocks/bse-pearl-polymers-ltd https://www.tickertape.in/stocks/pearl-polymers-PRLP
A61: C0060 | B61: Petainer | C61: Petainer | D61: No | E61: https://www.petainer.com | H61: International | I61: PET Bottles & Preforms | J61: 1 | K61: Manufacturer | Q61: Medium | R61: 1 | S61: https://www.petainer.com/pet-plastic-preforms/bottle-preform-28mm-pco
A62: C0061 | B62: Polyplex Corporation Limited | C62: Polyplex | D62: Yes | E62: https://www.polyplex.com | G62: India | H62: India-North | I62: BOPET base film | J62: 1 | K62: Manufacturer | L62: Listed (NSE: POLYPLEX; BSE: 524051) | Q62: Medium | R62: 3 | S62: https://www.angelone.in/news/stocks-share-market/polyplex-corporation-expands-its-horizons-with-new-bopet-film-plant-in-india https://filingreader.com/news-wire/mumbai/2025-09-15/polyplex-highlights-global-expansion-sustainable-growth-strategy https://www.screener.in/company/524051
A63: C0062 | B63: Pondicherry Polymers | D63: No | F63: Puducherry, India (inferred from company name; not verified) | G63: India | H63: India-South | I63: PET Bottles & Preforms | J63: 1 | K63: Manufacturer (claimed on B2B listing; not verified) | Q63: Low | R63: 1 | S63: https://www.dial4trade.com/pondicherry-polymers/pet-performs-pdid-1228244.htm
A64: C0063 | B64: Pranav Plastics | C64: Pranav Plastics | D64: No | E64: https://www.pranavplasticsindia.com | F64: Nashik, Maharashtra, India | G64: India | H64: India-West | I64: PET Bottles & Preforms | J64: 1 | K64: Trader; Retailer | Q64: Low | R64: 1 | S64: https://www.pranavplasticsindia.com/pharma-pet-bottles.html
A65: C0064 | B65: PT Esco Chemicals Mitra Utama | C65: Esco Chemicals | D65: No | F65: Indonesia | G65: Indonesia | H65: International | I65: Dextrose/Glucose | J65: 1 | K65: Distributor; Importer | Q65: Low | R65: 1 | S65: https://en.indotrading.com/escochemicalsmitrautama/dextrose-monohydrate-ex-p470664.aspx
A66: C0065 | B66: Quadra (Quadra Chemicals) | C66: Quadra | D66: No | E66: https://www.quadragroup.store | F66: Canada | G66: Canada | H66: International | I66: Dextrose/Glucose | J66: 1 | K66: Distributor | Q66: Low | R66: 1 | S66: https://www.quadragroup.store/products/meritose-200-pharma-p15325
A67: C0066 | B67: Radcom Packaging Private Limited | C67: Radcom Packaging | D67: No | G67: India | H67: India-West | I67: PET Bottles & Preforms | J67: 1 | K67: Manufacturer (claims, unverified) | Q67: Low | R67: 4 | S67: https://pharmasource.global/directory/radcom-packaging-pvt-ltd/ https://www.cphi-online.com/company/radcom-packaging-pvt-ltd/ https://m.indiamart.com/radcompackaging/hdpe-pet-containers-4-nutraceuticals-supplements.html https://m.indiamart.com/radcompackaging/pet-cream-jars-and-pp-cream-jars.html
A68: C0067 | B68: Raja Tradelinks Pvt Ltd | C68: RTL | D68: No | F68: India (city not verified this session) | G68: India | H68: India-Pan | I68: Caps & Closures | J68: 1 | K68: Supplier (role not verified) | Q68: Low | R68: 1 | S68: https://www.pharmaceutical-tech.com/products/raja-tradelinks-pvt-ltd-rtl/aluminium-ropp-caps
A69: C0068 | B69: Ramshree Chemicals | D69: No | E69: https://www.ramshreechemicals.in/ | F69: India (city not verified) | G69: India | H69: India-Pan | I69: Dextrose/Glucose | J69: 1 | K69: Trader (claims manufacturer); Supplier; Exporter | Q69: Low | R69: 1 | S69: https://www.ramshreechemicals.in/dextrose-monohydrate-3400354.html
A70: C0069 | B70: Regaal Resources Limited | C70: Regaal | Regaal Resources | D70: Yes | E70: https://regaalresources.com/ | F70: India (corporate office not verified) | Kolkata, West Bengal, India (corporate office) | G70: India | H70: India-East | I70: Corn/Maize; Dextrose/Glucose | J70: 2 | K70: Processor (maize wet-miller); Manufacturer | Processor (starch wet-miller); Manufacturer | L70: Listed after IPO (IPO coverage by Samco/JK BFSL) | Incorporated 2012, converted to public company 2022; IPO opened 12 Aug 2025 (Business Today); listed | M70: 1,650 TPD maize crushing after doubling (Rs 389 crore Kishanganj expansion; trade-press headlines) | 750 TPD maize crushing installed; doubled to 1,650 TPD at Kishanganj (Business Upturn / TipRanks headlines) | N70: Full-year revenue ~Rs 1,134 crore (Trade Brains headline; fiscal year not stated in headline) | Q70: Medium | R70: 10 | S70: https://regaalresources.com/ https://agrospectrumindia.com/news/5/34078/regaal-resources-doubles-capacity-to-1650-tpd-commissions-new-lg-and-mpd-facility-in-bihar-with-rs-389-cr-investment.html https://tradebrains.in/regaal-resources-doubles-crushing-capacity-to-1650-tpd-full-year-revenue-touches-1134-crore/ https://www.outlookbusiness.com/news/regaal-resources-doubles-maize-processing-capacity-with-389-cr-expansion-at-kishanganj-bihar https://www.samco.in/ipo/regaal-resources-ipo https://x.com/LnprCapital/status/1957687364702335124?lang=en https://www.businessupturn.com/business/corporates/regaal-resources-doubles-maize-processing-capacity-to-1650-tpd-in-kishanganj https://www.tipranks.com/news/company-announcements/regaal-resources-doubles-maize-capacity-becomes-eastern-indias-largest-specialty-producer https://chemindigest.com/regaal-resources-commissions-lg-and-mpd-facility-in-bihar/ https://www.businesstoday.in/amp/markets/ipo-corner/story/regaal-resources-ipo-opens-today-check-reviews-ratings-latest-gmp-more-488973-2025-08-12
A71: C0070 | B71: Reliance Industries Limited | C71: Relpet | D71: Yes | E71: https://www.ril.com | F71: Mumbai, Maharashtra, India | G71: India | H71: India-Pan | I71: PET Resin | J71: 1 | K71: Manufacturer; Recycler | L71: Listed (NSE: RELIANCE) | Q71: Medium | R71: 6 | S71: https://rilstaticasset.akamaized.net/sites/default/files/2022-12/py_rpt_g5801_spec.pdf https://plastics.ulprospector.com/plastics/en/generics/37/materials/4048 https://www.specialchem.com/plastics/supplier/reliance-industries/relpet https://Knowde.com/stores/reliance-industries-ltd/products/relpet-g5801 https://www.indianchemicalnews.com/petro-chemical/lite/reliance-to-double-its-pet-recycling-capacity-to-5-bn-bottles-9971 https://petpla.net/2023/02/01/pet-raw-material-and-recyclate-from-india/
A72: C0071 | B72: Riddhi Siddhi Gluco Biols Limited | C72: RSGBL | D72: No | E72: https://riddhisiddhi.co.in/ | F72: Ahmedabad, Gujarat, India | G72: India | H72: India-West | I72: Corn/Maize | J72: 1 | K72: Processor (maize wet-miller) | L72: Listed (BSE); acquired Cargill India's corn wet-milling division | M72: 300,000 MT corn milling facility (Karnataka) per trade-press headline | Q72: Medium | R72: 4 | S72: https://riddhisiddhi.co.in/pdf/other-events-and-disclosure/press-release-19-01-2026.pdf https://www.world-grain.com/articles/22710-rsgbl-acquires-cargill-corn-mill-in-india https://insights.munich-startup.de/news/feed/riddhi-siddhi-gluco-biols-acquires-cargill-s-300-000-mt-corn-milling-facility-in-karnataka https://themachinemaker.com/news/rsgbl-completes-acquisition-of-corn-wet-milling-facility-from-cargill-in-karnataka/
A73: C0072 | B73: Roquette Frères | C73: Roquette | D73: No | E73: https://www.roquette.com | F73: Lestrem, Hauts-de-France, France | G73: France | H73: International | I73: Dextrose/Glucose | J73: 1 | K73: Manufacturer | L73: Private, family-owned group (general knowledge; not verified from a fetched page) | P73: US DMF (anhydrous dextrose) per PharmaCompass DMF listing; EDQM GMP page exists on PharmaCompass (not read) | Q73: High | R73: 5 | S73: https://www.roquette.com/health-pharma/injectable-dialysis-specialty-apis/lycadex-pf-dextrose-monohydrate https://www.roquette.com/pharma-and-nutraceuticals-pyrogen-free-dextrose-monohydrate https://fr.roquette.com/-/media/roquette-sharepoint-libraries/marcomonline---pharma/roquette-pharma-injectable-dialysis-specialty-api-brochure.pdf https://manufacturingchemist.com/roquette-completes-injectable-carbohydrate-plant-at-lestrem-63951 https://pharmacompass.com/us-drug-master-files-dmfs/anhydrous-dextrose
A74: C0073 | B74: Roquette India Private Limited | C74: Roquette India (formerly Roquette Riddhi Siddhi) | Roquette India | D74: No | E74: https://www.roquette.com/ | F74: India | G74: India | H74: India-West; India-Pan | I74: Corn/Maize; Dextrose/Glucose | J74: 2 | K74: Manufacturer (starch derivatives in India); MNC subsidiary; Importer/marketer of group pharma excipients (inferred – verify) | Processor (maize wet-miller); Manufacturer | L74: Subsidiary of Roquette Frères (France); Roquette took over the Riddhi Siddhi Gluco Biols corn wet-milling business (strategic partner 2005-06, business demerged 2009-10, Roquette asset acquisition reported 2012) | MNC subsidiary (Roquette Freres, France) | Q74: Medium | R74: 10 | S74: https://www.roquette.com/pharma-lycadex-pf-dextrose-monohydrate-pyrogen-free https://www.roquette.com/health-pharma/biologics-product-finder/lycadex-biopharma-dextrose-monohydrate-low-endotoxin https://www.roquette.com/health-pharma/pharmaceutical-product-catalog/glucidex-21-dehydrated-glucose-syrup-india https://www.roquette.com/press-releases/product-capabilities-viramgam-india https://www.roquette.com/press-releases/roquette-celebrates-10-years-operation-pantnagar https://www.indianchemicalnews.com/general/lite/roquette-inaugurates-spray-tower-at-pantnagar-site-in-india-11507 https://www.potatopro.com/node/8764 https://www.riddhisiddhi.co.in/about.html https://www.roquette.com/media-center/press-center/2019-08-28-roquette-india-viramgam-s-unit-inauguration https://www.foodnavigator.com/Article/2012/06/01/Roquette-Indian-starch-JV-to-drive-market-traction
A75: C0074 | B75: rPET InWaste, s.r.o. | C75: rPET InWaste | D75: Yes | G75: Czech Republic | H75: International | I75: PET Resin | J75: 1 | K75: Recycler | Q75: Medium | R75: 1 | S75: https://circulareconomy.europa.eu/platform/en/good-practices/rpet-inwaste-sro-enabling-pet-bottle-bottle-recycling
A76: C0075 | B76: Sayaji Industries Limited | C76: Maize Products (Sayaji Group) | Sayaji | D76: Yes | E76: https://www.maizeproducts.com/ | F76: Ahmedabad, Gujarat, India | G76: India | H76: India-West | I76: Corn/Maize; Dextrose/Glucose | J76: 2 | K76: Manufacturer; Processor (maize wet-miller) | Processor (maize wet-miller); Manufacturer | L76: Listed (BSE; ISIN INE327G01032); flagship of Sayaji Group, est. 1941 | Listed (BSE) | M76: 750 MTPD maize grinding (Fi Global exhibitor profile) | O76: CARE press releases Oct-2018 and Nov-2019 exist; current rating not read | Q76: Medium | R76: 5 | S76: https://www.maizeproducts.com/industry-solutions/dextrose-monohydrate/ https://exhibitors.figlobal.com/net/company/26/90/94/result269094-565.html https://upstox.com/stocks/sayaji-industries-limited/INE327G01032 https://www.careratings.com/upload/CompanyFiles/PR/Sayaji Industries Limited-03-11-2019.pdf https://www.kotaksecurities.com/stocks/bse-sayaji-industries-ltd
A77: C0076 | B77: Shandong Tianli Pharmaceutical Co., Ltd. | C77: Tianli Pharmaceutical | D77: No | F77: Shandong, China | G77: China | H77: International | I77: Dextrose/Glucose | J77: 1 | K77: Manufacturer | P77: US DMF (PharmaCompass listing) | Q77: Medium | R77: 3 | S77: https://pharmacompass.com/us-drug-master-files-dmfs/anhydrous-dextrose https://www.pharmacompass.com/dmf-37618 https://www.pharmacompass.com/dmf-35737
A78: C0077 | B78: Shanghai Unitebiz | C78: Shanghai Unitebiz | D78: No | F78: Shanghai, China | G78: China | H78: International | I78: Dextrose/Glucose | J78: 1 | K78: Exporter; Trader (manufacturing not verified) | Q78: Low | R78: 1 | S78: https://b2usa.com/hotsite/shanghaiunitebiz/dextrose-monohydrate-food-grade-high-qua
A79: C0078 | B79: Sheth PET Polymers Private Limited | C79: Sheth PET | D79: No | E79: https://www.shethpet.in | F79: Thane, Maharashtra, India | G79: India | H79: India-West | I79: PET Bottles & Preforms | J79: 1 | K79: Manufacturer (claimed by company site title) | Q79: Medium | R79: 2 | S79: https://www.shethpet.in/pharma-pet-bottle.html https://th.globallinker.com/network/rubber-plastics-polymers/sme/sheth-pet-polymers-private-limited-241415
A80: C0079 | B80: Sibi Polymers | D80: No | E80: https://m.indiamart.com/sibi-polymers/ | G80: India | H80: India-South | I80: PET Bottles & Preforms | J80: 1 | K80: Manufacturer (claimed on B2B listing; not verified) | Q80: Low | R80: 1 | S80: https://m.indiamart.com/sibi-polymers/
A81: C0080 | B81: Silgan Dispensing Systems | C81: Silgan Dispensing (Silgan Holdings) | D81: No | E81: https://silgandispensing.com | G81: USA | H81: International | I81: Caps & Closures | J81: 1 | K81: Manufacturer | L81: Silgan Holdings Inc. (listed, NASDAQ: SLGN) - parent relationship from general knowledge, not verified this session | Q81: Low | R81: 3 | S81: https://silgandispensing.com/wp-content/uploads/2026/07/260504-Dispensing-Closures-Catalogue-HR-1.pdf https://silgandispensing.com/wp-content/uploads/2026/01/Dispensing-Closures-Catalogue-06.25-HR.pdf https://silgandispensing.com/wp-content/uploads/2018/01/20SDS0755_Closures-Product-Guide_r3.pdf
A82: C0081 | B82: Sonapet Industries | D82: No | E82: https://m.indiamart.com/sonapetindustries | G82: India | H82: India-South | I82: PET Bottles & Preforms | J82: 1 | K82: Manufacturer (claimed on B2B listing; not verified) | Q82: Low | R82: 3 | S82: https://m.indiamart.com/sonapetindustries https://m.indiamart.com/sonapetindustries/about-us.html https://m.indiamart.com/sonapetindustries/plastic-container.html
A83: C0082 | B83: SRF Limited | C83: SRF Packaging Films | D83: No | E83: https://www.srf.com | G83: India | H83: India-Central | I83: BOPET base film | J83: 1 | K83: Manufacturer | L83: Listed (NSE: SRF) | Q83: Medium | R83: 3 | S83: https://disclosures.ifc.org/project-detail/ESRS/37933/srf-india-bopet https://www.packaging-gateway.com/news/srf-plans-to-invest-58m-in-bopet-production-facility-in-indore-india-090216-4805002/ https://www.plasteurope.com/news/detail.asp?id=246416
A84: C0083 | B84: SRF Limited - Hungary BOPET operation | C84: SRF Hungary | D84: No | E84: https://www.srf.com | G84: Hungary | H84: International | I84: BOPET base film | J84: 1 | K84: Manufacturer | L84: Subsidiary of SRF Limited (India) | Q84: Medium | R84: 1 | S84: https://www.plasteurope.com/news/detail.asp?id=246416
A85: C0084 | B85: SRF Limited - Thailand BOPET operation | C85: SRF Thailand | D85: No | E85: https://www.srf.com | G85: Thailand | H85: International | I85: BOPET base film | J85: 1 | K85: Manufacturer | L85: Subsidiary of SRF Limited (India) | Q85: Medium | R85: 1 | S85: https://www.plasteurope.com/news/detail.asp?id=246416
A86: C0085 | B86: Srichakra Polyplast | C86: Srichakra | D86: No | G86: India | H86: India-South | I86: PET Resin | J86: 1 | K86: Recycler; Manufacturer | L86: Private; investee of Circulate Capital (press release Mar 2022) | M86: Trade press (petpla.net, Apr 2025) reports bottle-grade rPET capacity tripled; figure not read | Q86: Medium | R86: 6 | S86: https://www.indianpharmapost.com/sustainability/srichakra-receives-european-food-safety-approval-for-its-food-grade-recycled-rpet-11622 https://www.petnology.com/magazine/article/srichakra-becomes-the-first-indian-recycling-company-to-receive-a-positive-safety-assessment-from-european-food-safety-authority https://petpla.net/2025/04/28/srichakra-triples-bottle-grade-rpet-production-capacities/ https://www.foodanddrinktechnology.com/news/48696/recycled-pet-for-indias-first-100-rpet-beverage-bottle-produced-by-srichakra-polyplast/ https://petpla.net/2021/11/08/bottle-to-bottle-recycling-line-at-srichakra-polyplast-in-india/ https://www.circulatecapital.com/wp-content/uploads/2022/11/Srichakra_Press-Release_March-9-2022.docx.pdf
A87: C0086 | B87: Tekni-Plex, Inc. | C87: Tri-Seal (a Tekni-Plex company) | D87: No | E87: https://tekni-plex.com | G87: USA | H87: International | I87: Caps & Closures | J87: 1 | K87: Manufacturer | Q87: Medium | R87: 4 | S87: https://tekni-plex.com/en/articles/tri-seal-luxe-seal-2-pc-embossed-induction-seal-closer-liners https://www.healthcarepackaging.com/home/press-release/13289282/tekniplex-induction-seals https://www.oemmagazine.org/home/product/15693541/triseal-a-tekniplex-co-triseal-embossed-induction-seal-closure-liners https://tekni-plex.com/en/articles/tri-seal-unveils-latest-pouch-lidding-structures-for-medical-device-and-pharma-applications-at-mdm-west
A88: C0087 | B88: Telangana State Co-operative Marketing Federation Limited | C88: TS MARKFED | D88: No | F88: Hyderabad, Telangana, India | G88: India | H88: India-South | I88: Corn/Maize | J88: 1 | K88: Cooperative/Government agency; Aggregator | Q88: Medium | R88: 3 | S88: https://www.indiancooperative.com/co-op-news-snippets/maize-procurement-telangana-markfed-coordinating-with-nafed/ https://www.siasat.com/telangana-govt-opens-maize-procurement-centres-after-brs-pressure-harish-rao-3438607/ https://www.siasat.com/telanganas-maize-crisis-exposes-gaps-in-procurement-storage-systems-3468406/
A89: C0088 | B89: Tereos | C89: Tereos (Meritose) | D89: No | E89: https://www.tereos.com | F89: France | G89: France | H89: International | I89: Dextrose/Glucose | J89: 1 | K89: Manufacturer | P89: CEP, GMP, CoA – as listed on PharmaOffer (third-party listing) | Q89: Medium | R89: 3 | S89: https://pharmaoffer.com/api-excipient-supplier/excipients/glucose-monohydrate/cep https://pharmaoffer.com/api-excipient-supplier/company/tereos https://www.quadragroup.store/products/meritose-200-pharma-p15325
A90: C0089 | B90: The Sukhjit Starch and Chemicals Limited | C90: Sukhjit Group | Sukhjit Starch (SSCL) | Sukhjit Starch; Sukhjit Biocorn (Nashik/Yeola project) | D90: Yes | E90: https://www.sukhjitgroup.com/ | F90: Phagwara, Punjab, India | Phagwara, Punjab, India (general knowledge) | G90: India | H90: India-North | I90: Corn/Maize; Dextrose/Glucose | J90: 2 | K90: Processor (maize wet-miller); Manufacturer | Processor (starch wet-miller); Manufacturer | Processor (maize wet-miller); Manufacturer | L90: Listed (NSE: SUKHJITS; BSE) | Promoted by the Sardana family and associates; subsidiary Sukhjit Mega Food Park & Infra Ltd; publicly traded (stock pages on IIFL/Arihant Capital) | Listed (BSE) | M90: 1,600 TPD maize grinding (CRISIL rationale, 9 Aug 2024) | Rs 500 crore MoU for Nashik maize unit (Indian Chemical News); Rs 760 crore Yeola MIDC agro-processing plant (Free Press Journal) | N90: Operating income Rs 1,370.86 crore FY2024 (FY2023: Rs 1,435.25 crore); PAT Rs 55.62 crore FY2024 (CRISIL) | O90: CRISIL rating rationales dated 12 Jun 2026, 8 Aug 2025, 9 Aug 2024 and others exist; CARE rationales 2019/2022 (rating values not read) | CRISIL A+/Stable (long term) and CRISIL A1 (short term), reaffirmed, 9 Aug 2024 | CRISIL rationales Feb-2023 and Jul-2023 exist; not read | Q90: Medium | R90: 11 | S90: https://www.crisil.com/mnt/winshare/Ratings/RatingList/RatingDocs/TheSukhjitStarchandChemicalsLimited_June 12_ 2026_RR_394602.html https://www.careratings.com/upload/CompanyFiles/PR/20092022074241_The_Sukhjit_Starch_&_Chemicals_Limited.pdf https://filingreader.com/news-wire/mumbai/2026-05-06/sukhjit-starch-to-shut-phagwara-unit-for-maintenance https://www.morningstar.com.au/investments/security/NSE/SUKHJITS https://www.crisil.com/mnt/winshare/Ratings/RatingList/RatingDocs/TheSukhjitStarchandChemicalsLimited_August 09_ 2024_RR_350173.html https://www.crisil.com/mnt/winshare/Ratings/RatingList/RatingDocs/TheSukhjitStarchandChemicalsLimited_July 18_ 2024_RR_347845.html https://www.careratings.com/upload/CompanyFiles/PR/The Sukhjit Starch & Chemicals Limited-10-09-2017.pdf https://www.indiainfoline.com/company/sukhjit-starch-chemicals-ltd/summary https://www.indianchemicalnews.com/general/sukhjit-starch-signs-rs-500-crore-mou-with-maharashtra-for-nashik-maize-unit-31805 https://www.freepressjournal.in/pune/nashik-sukhjit-biocorn-to-invest-760-crore-in-yeola-midc-agro-processing-plant https://www.crisil.com/mnt/winshare/Ratings/RatingList/RatingDocs/TheSukhjitStarchandChemicalsLimited_July 20, 2023_RR_323242.html
A91: C0090 | B91: Tianjia (tianjiachem.com) | C91: Tianjia | D91: No | E91: https://www.tianjiachem.com | F91: China | G91: China | H91: International | I91: Dextrose/Glucose | J91: 1 | K91: Exporter; Trader (manufacturing not verified) | Q91: Low | R91: 1 | S91: https://www.tianjiachem.com/dextrose-anhydrous-product/
A92: C0091 | B92: Tilley Distribution | C92: Tilley | D92: No | E92: https://www.tilleydistributionproducts.com | F92: USA | G92: USA | H92: International | I92: Dextrose/Glucose | J92: 1 | K92: Distributor | Q92: Medium | R92: 2 | S92: https://www.tilleydistributionproducts.com/products/clintose-dextrose-a https://tilleydistributionproducts.com/products/clintose-dextrose-vf
A93: C0092 | B93: Tirupati Starch & Chemicals Limited | C93: Tirupati Starch | D93: Yes | F93: Indore, Madhya Pradesh, India (not re-verified) | G93: India | H93: India-Central | I93: Corn/Maize | J93: 1 | K93: Processor (maize wet-miller); Manufacturer | L93: Listed (BSE: 524582) | Q93: Low | R93: 2 | S93: https://musaffa.com/stock/524582.BO/ https://www.indiainfoline.com/company/tirupati-starch-chemicals-ltd-management/summary/3872
A94: C0093 | B94: UFlex Limited | C94: UFlex | D94: Yes | E94: https://www.uflexltd.com | F94: Noida, Uttar Pradesh, India | G94: India | H94: India-North | I94: Laminate converters | J94: 1 | K94: Manufacturer; Converter | L94: Listed company (BSE corporate filings seen) | Q94: Medium | R94: 4 | S94: https://www.printweek.in/news/uflex-highlights-its-pharma-packaging-solutions-at-cphi-2019-42519 https://packagingsouthasia.com/events/uflex-launches-stick-pack-machine-at-cphi-and-p-mec-2019/ https://www.plastemart.com/news-plastics-information/UFlex-Limited-A-Global-Leader-in-Flexible-Packaging-Films/75103 https://www.packaginginsights.com/profile-directory/uflex-limited.html
A95: C0094 | B95: Universal Starch-Chem Allied Limited | C95: Universal Starch | D95: Yes | E95: https://www.universalstarch.com/ | F95: Dondaicha, Shindkheda, Dhule, Maharashtra, India | Maharashtra, India | G95: India | H95: India-West | I95: Corn/Maize; Dextrose/Glucose | J95: 2 | K95: Manufacturer; Processor (corn wet-miller); Exporter | Processor (maize wet-miller); Manufacturer | L95: Listed company (Bloomberg ticker UNIVSTAR:IN seen in search results) | Listed (BSE: 524408); founded 1973 | P95: FDA, GMP, ISO 9001 (icons on company's CPHI Online profile – claimed by company) | Q95: Medium | R95: 5 | S95: https://www.cphi-online.com/company/universal-starch-chem-allied-ltd/ https://www.cphi-online.com/product/dextrose-monohydrate-3/ https://www.bloomberg.com/profile/company/UNIVSTAR:IN https://m.indiamart.com/universalstarch/corn-starch.html https://www.sharescart.com/company/univer-starch-chem/
A96: C0095 | B96: Weifang Shengtai Medicine Co., Ltd. | C96: Weifang Shengtai / Shengtai Pharmaceutical | D96: No | F96: Weifang, Shandong, China | G96: China | H96: International | I96: Dextrose/Glucose | J96: 1 | K96: Manufacturer | L96: Operating company of Shengtai Pharmaceutical, Inc. (formerly US OTC: SGTI) per Yahoo Finance profile/BioSpace releases; current ownership not verified | P96: CEP, FDA, CoA (PharmaOffer listing); Eurofins GMP audit report dated Sep 2024 shown on PharmaOffer; US DMF (PharmaCompass) | Q96: Medium | R96: 7 | S96: https://pharmaoffer.com/api-excipient-supplier/excipients/glucose-monohydrate/cep https://pharmacompass.com/us-drug-master-files-dmfs/anhydrous-dextrose https://www.cphi-online.com/company/weifang-shengtai-medicine-co-ltd/ https://www.cphi-online.com/product/dextrose-anhydrous-3/ https://www.cphi-online.com/product/dextrose-monohydrate-4/ https://www.biospace.com/shengtai-pharmaceutical-inc-sets-up-new-sales-departments-to-accommodate-anticipated-ramp-in-operations-of-new-glucose-facility https://hk.finance.yahoo.com/quote/SGTI/profile
A97: C0096 | B97: Xenex Labs | C97: Xenex Labs | D97: No | E97: https://www.xenexlabs.com | F97: USA | G97: USA | H97: International | I97: Dextrose/Glucose | J97: 1 | K97: Distributor | Q97: Low | R97: 1 | S97: https://www.xenexlabs.com/products/dextrose-anhydrous-powder-usp-25kg
A98: C0097 | B98: Xiwang Pharmaceutical Co., Ltd. | C98: Xiwang Pharma | D98: No | F98: Zouping, Shandong, China | G98: China | H98: International | I98: Dextrose/Glucose | J98: 1 | K98: Manufacturer | L98: Xiwang Group company (by name; not verified). HQ location from general knowledge of Xiwang Group, not a fetched page. | P98: CEP, CoA (PharmaOffer listing); US DMF x2 (PharmaCompass) | Q98: Medium | R98: 4 | S98: https://pharmaoffer.com/api-excipient-supplier/excipients/glucose-monohydrate/cep https://pharmacompass.com/us-drug-master-files-dmfs/anhydrous-dextrose https://www.pharmacompass.com/dmf-26450 https://pharmaoffer.com/api-excipient-supplier/company/xiwang-pharma

Sheet Dextrose
A1: Dextrose — 37 supplier lines. Crystalline dextrose only; liquid glucose, maltodextrin and fructose are listed under 'Related products kept separate'.
A2: Company ID | B2: Company (legal / registered name) | C2: Trade / brand name | D2: Legal name verified | E2: Subcategory | F2: Relevant products | G2: Grades / specs / sizes / materials | H2: Related products kept separate (out of scope) | I2: Role | J2: Applications | K2: Priority match (keyword-derived) | L2: Region | M2: HQ | N2: Country | O2: Plants | P2: Website | Q2: Certifications (as stated) | R2: Capacity (published) | S2: Revenue (published) | T2: Ownership | U2: Credit rating | V2: Suitability / verification notes | W2: Evidence confidence | X2: Also listed under | Y2: No. of sources | Z2: Sources
A3: C0073 | B3: Roquette India Private Limited | C3: Roquette India (formerly Roquette Riddhi Siddhi) | D3: No | E3: Dextrose – pharma grade | F3: Roquette group: LYCADEX PF (dextrose monohydrate, pyrogen-free); LYCADEX BioPharma (dextrose monohydrate, low endotoxin); GLUCIDEX 21 dehydrated glucose syrup listed as an India product | G3: Dextrose monohydrate pyrogen-free / low-endotoxin (group pharma range). Whether LYCADEX is produced in India or imported not verified. | H3: GLUCIDEX maltodextrin/dehydrated glucose syrup; starches; polyols | I3: Manufacturer (starch derivatives in India); MNC subsidiary; Importer/marketer of group pharma excipients (inferred – verify) | J3: Pharma (parenteral/oral), biopharma cell culture, food | K3: Pharma / ORS | L3: India-Pan | M3: India | N3: India | O3: Pantnagar (Uttarakhand) and Viramgam (Gujarat) per Roquette press releases; other Indian sites of the former Riddhi Siddhi corn wet-milling business not verified here | P3: https://www.roquette.com/ | T3: Subsidiary of Roquette Frères (France); Roquette took over the Riddhi Siddhi Gluco Biols corn wet-milling business (strategic partner 2005-06, business demerged 2009-10, Roquette asset acquisition reported 2012) | V3: Strong pharma-dextrose pedigree at group level (LYCADEX PF pyrogen-free). Indian manufacture of crystalline dextrose not verified in this pass; Riddhi Siddhi's historic timeline shows dextrose monohydrate capacity before the demerger. Confirm with Roquette India whether pharma dextrose is supplied from Indian plants or imported. | W3: Medium | X3: Corn/Maize | Y3: 8 | Z3: https://www.roquette.com/pharma-lycadex-pf-dextrose-monohydrate-pyrogen-free https://www.roquette.com/health-pharma/biologics-product-finder/lycadex-biopharma-dextrose-monohydrate-low-endotoxin https://www.roquette.com/health-pharma/pharmaceutical-product-catalog/glucidex-21-dehydrated-glucose-syrup-india https://www.roquette.com/press-releases/product-capabilities-viramgam-india https://www.roquette.com/press-releases/roquette-celebrates-10-years-operation-pantnagar https://www.indianchemicalnews.com/general/lite/roquette-inaugurates-spray-tower-at-pantnagar-site-in-india-11507 https://www.potatopro.com/node/8764 https://www.riddhisiddhi.co.in/about.html
A4: C0041 | B4: Ingredion Incorporated | C4: Ingredion (CERELOSE®); Ingredion Pharma Solutions | D4: No | E4: Dextrose – pharma grade | F4: CERELOSE® Anhydrous Dextrose 024010 (technical specification on ingredion.com); anhydrous dextrose (US DMF via Ingredion Pharma Solutions) | G4: Anhydrous dextrose; 1 US DMF listed under 'Ingredion Pharma Solutions' (PharmaCompass; number not captured); spec sheet content not read | I4: Manufacturer | J4: pharma; food | K4: Pharma / ORS | L4: International | M4: Westchester, Illinois, USA | N4: USA | P4: https://www.ingredion.com | Q4: US DMF (PharmaCompass listing) | T4: Listed – NYSE: INGR (general knowledge) | V4: Own technical-spec PDF for CERELOSE® anhydrous dextrose surfaced in search (could not be fetched). Ingredion also owns Rafhan Maize (Pakistan) – not separately verified in this session. | W4: High | Y4: 3 | Z4: https://ingredion.com/content/dam/ingredion/technical-documents/na/CERELOSE%20Anhydrous%20Dextrose%20024010%20Technical%20Specification.pdf https://pharmacompass.com/us-drug-master-files-dmfs/anhydrous-dextrose https://pharmaoffer.com/api-excipient-supplier/company/ingredion
A5: C0072 | B5: Roquette Frères | C5: Roquette | D5: No | E5: Dextrose – pharma grade | F5: LYCADEX® PF – Dextrose monohydrate (pyrogen-free); anhydrous dextrose (US DMF listed under Roquette on PharmaCompass); dextrose datasheet for plant-care use | G5: Monohydrate, pyrogen-free (PF) grade marketed for injectables/dialysis (Roquette 'Injectable, Dialysis & Specialty APIs' range); anhydrous dextrose covered by 1 US DMF per PharmaCompass (DMF number not captured); pharmacopoeia references and feedstock not confirmed in this session | I5: Manufacturer | J5: pharma – parenteral/injectables, dialysis solutions; specialty APIs | K5: Pharma / ORS | L5: International | M5: Lestrem, Hauts-de-France, France | N5: France | O5: Lestrem, France (new injectable-carbohydrate plant per trade-press headline) | P5: https://www.roquette.com | Q5: US DMF (anhydrous dextrose) per PharmaCompass DMF listing; EDQM GMP page exists on PharmaCompass (not read) | T5: Private, family-owned group (general knowledge; not verified from a fetched page) | V5: Company's own product pages (seen as search results) name LYCADEX® PF pyrogen-free dextrose monohydrate in its injectable/dialysis range – strong fit for ORS/IV-grade needs. Grade/pharmacopoeia claims are the company's own; page content could not be fetched (rate-limited), so specs not verified. | W5: High | Y5: 5 | Z5: https://www.roquette.com/health-pharma/injectable-dialysis-specialty-apis/lycadex-pf-dextrose-monohydrate https://www.roquette.com/pharma-and-nutraceuticals-pyrogen-free-dextrose-monohydrate https://fr.roquette.com/-/media/roquette-sharepoint-libraries/marcomonline---pharma/roquette-pharma-injectable-dialysis-specialty-api-brochure.pdf https://manufacturingchemist.com/roquette-completes-injectable-carbohydrate-plant-at-lestrem-63951 https://pharmacompass.com/us-drug-master-files-dmfs/anhydrous-dextrose
A6: C0014 | B6: Cargill S.L.U. | C6: Cargill | D6: No | E6: Dextrose – pharma grade | F6: Glucose monohydrate (dextrose) – pharmaceutical grade | G6: Glucose monohydrate; Ph. Eur. CEP holder per PharmaOffer CEP listing (CEP number not captured); product origin Spain | I6: Manufacturer | J6: pharma | K6: Pharma / ORS | L6: International | M6: Spain | N6: Spain | P6: https://www.cargill.com/pharmaceutical/pharma-products/glucose-monohydrates-dextrose | Q6: CEP (glucose monohydrate), FDA, CoA – as listed on PharmaOffer (third-party listing) | T6: Subsidiary of Cargill, Incorporated (USA, private) | V6: Listed as producer with CEP for glucose monohydrate (PharmaOffer). Cargill's own pharmaceutical page for 'glucose monohydrates (dextrose)' surfaced in search but could not be fetched. Verify CEP number/validity on EDQM database. | W6: Medium | Y6: 5 | Z6: https://pharmaoffer.com/api-excipient-supplier/excipients/glucose-monohydrate/cep https://pharmaoffer.com/api-excipient-supplier/glucose-monohydrate/cep https://www.cargill.com/pharmaceutical/pharma-products/glucose-monohydrates-dextrose https://www.cargill.com/products/pharmaceutical/products/glucose-monohydrates/ https://pharmacompass.com/ndc-api/cargill-slu
A7: C0023 | B7: CSPC Shengxue Glucose Co., Ltd. | C7: CSPC Shengxue (石药圣雪) | D7: No | E7: Dextrose – pharma grade | F7: Anhydrous dextrose (US DMF holder) | G7: Anhydrous dextrose; 1 US DMF listed (PharmaCompass; number not captured) | I7: Manufacturer | J7: pharma | K7: Pharma / ORS | L7: International | M7: Hebei, China | N7: China | Q7: US DMF (PharmaCompass listing) | T7: CSPC group company (CSPC Pharmaceutical Group is HKEX-listed, 1093 – general knowledge; current shareholding not verified) | V7: US DMF holder for anhydrous dextrose per PharmaCompass. No company page fetched; capacity unknown. | W7: Medium | Y7: 3 | Z7: https://pharmacompass.com/us-drug-master-files-dmfs/anhydrous-dextrose https://www.pharmacompass.com/about/cspc-shengxue-glucose https://doc.irasia.com/listco/hk/cspc/annual/2018/screspress.pdf
A8: C0076 | B8: Shandong Tianli Pharmaceutical Co., Ltd. | C8: Tianli Pharmaceutical | D8: No | E8: Dextrose – pharma grade | F8: Anhydrous dextrose (US DMF holder) | G8: Anhydrous dextrose; 1 US DMF listed (PharmaCompass). DMF pages 37618 and 35737 surfaced in a search for this company – mapping not confirmed | I8: Manufacturer | J8: pharma | K8: Pharma / ORS | L8: International | M8: Shandong, China | N8: China | Q8: US DMF (PharmaCompass listing) | V8: Listed as US DMF holder for anhydrous dextrose. No company page fetched; verify grade (oral vs injectable) and CEP status directly. | W8: Medium | Y8: 3 | Z8: https://pharmacompass.com/us-drug-master-files-dmfs/anhydrous-dextrose https://www.pharmacompass.com/dmf-37618 https://www.pharmacompass.com/dmf-35737
A9: C0088 | B9: Tereos | C9: Tereos (Meritose) | D9: No | E9: Dextrose – pharma grade | F9: Glucose monohydrate (pharma, CEP); 'Meritose 200 Pharma' listed by distributor Quadra | G9: Glucose monohydrate with Ph. Eur. CEP per PharmaOffer (CEP number not captured); product origin France | I9: Manufacturer | J9: pharma; food | K9: Pharma / ORS | L9: International | M9: France | N9: France | P9: https://www.tereos.com | Q9: CEP, GMP, CoA – as listed on PharmaOffer (third-party listing) | V9: Listed as producer with CEP for glucose monohydrate. Link of 'Meritose' brand to Tereos is from search context, not a fetched page. Verify CEP on EDQM. | W9: Medium | Y9: 3 | Z9: https://pharmaoffer.com/api-excipient-supplier/excipients/glucose-monohydrate/cep https://pharmaoffer.com/api-excipient-supplier/company/tereos https://www.quadragroup.store/products/meritose-200-pharma-p15325
A10: C0095 | B10: Weifang Shengtai Medicine Co., Ltd. | C10: Weifang Shengtai / Shengtai Pharmaceutical | D10: No | E10: Dextrose – pharma grade | F10: Dextrose Anhydrous; Dextrose Monohydrate (CPHI-Online product listings); glucose monohydrate (CEP); anhydrous dextrose (US DMF) | G10: Anhydrous and monohydrate; Ph. Eur. CEP for glucose monohydrate (PharmaOffer); 1 US DMF for anhydrous dextrose listed as 'Weifang Shengtai Pharmaceutical' (PharmaCompass; number not captured); corn starch also produced, so maize feedstock likely (not confirmed) | H10: Glucose syrup; maltose syrup; corn starch | I10: Manufacturer | J10: pharma; food | K10: Pharma / ORS | L10: International | M10: Weifang, Shandong, China | N10: China | Q10: CEP, FDA, CoA (PharmaOffer listing); Eurofins GMP audit report dated Sep 2024 shown on PharmaOffer; US DMF (PharmaCompass) | T10: Operating company of Shengtai Pharmaceutical, Inc. (formerly US OTC: SGTI) per Yahoo Finance profile/BioSpace releases; current ownership not verified | V10: Holds both CEP and US DMF per aggregators – one of the main Chinese pharma-dextrose sources. BioSpace releases describe a new glucose facility. Company website not identified; details from CPHI-Online exhibitor listings and regulatory aggregators. | W10: Medium | Y10: 7 | Z10: https://pharmaoffer.com/api-excipient-supplier/excipients/glucose-monohydrate/cep https://pharmacompass.com/us-drug-master-files-dmfs/anhydrous-dextrose https://www.cphi-online.com/company/weifang-shengtai-medicine-co-ltd/ https://www.cphi-online.com/product/dextrose-anhydrous-3/ https://www.cphi-online.com/product/dextrose-monohydrate-4/ https://www.biospace.com/shengtai-pharmaceutical-inc-sets-up-new-sales-departments-to-accommodate-anticipated-ramp-in-operations-of-new-glucose-facility https://hk.finance.yahoo.com/quote/SGTI/profile
A11: C0097 | B11: Xiwang Pharmaceutical Co., Ltd. | C11: Xiwang Pharma | D11: No | E11: Dextrose – pharma grade | F11: Glucose monohydrate (CEP); anhydrous dextrose (US DMFs) | G11: Monohydrate with Ph. Eur. CEP (PharmaOffer); 2 US DMFs for anhydrous dextrose listed under 'XIWANG Pharmaceutical Co Ltd' (PharmaCompass; DMF 26450 surfaced in search for this company, mapping not confirmed) | I11: Manufacturer | J11: pharma | K11: Pharma / ORS | L11: International | M11: Zouping, Shandong, China | N11: China | Q11: CEP, CoA (PharmaOffer listing); US DMF x2 (PharmaCompass) | T11: Xiwang Group company (by name; not verified). HQ location from general knowledge of Xiwang Group, not a fetched page. | V11: CEP + US DMF holder per aggregators – strong candidate for pharma-grade (incl. likely injectable) dextrose from China. Company site not reached; verify CEP/DMF status directly. | W11: Medium | Y11: 4 | Z11: https://pharmaoffer.com/api-excipient-supplier/excipients/glucose-monohydrate/cep https://pharmacompass.com/us-drug-master-files-dmfs/anhydrous-dextrose https://www.pharmacompass.com/dmf-26450 https://pharmaoffer.com/api-excipient-supplier/company/xiwang-pharma
A12: C0015 | B12: Cargill, Incorporated | C12: Cargill (C*Dex) | D12: No | E12: Dextrose – food grade | F12: C*Dex™ dextrose (EMEA food & beverage); dextrose (Asia-Pacific food & beverage) | G12: Grade details not captured (pages could not be fetched) | I12: Manufacturer | J12: food; beverage | K12: Pharma / ORS | L12: International | M12: Minnesota, USA | N12: USA | P12: https://www.cargill.com | T12: Private (general knowledge) | V12: Food-grade dextrose pages on cargill.com for EMEA and Asia-Pacific surfaced in search; content not fetched. Pharma grade is covered by Cargill S.L.U. record. | W12: Medium | Y12: 2 | Z12: https://www.cargill.com/food-bev/emea/c-dex-dextrose https://www.cargill.com/food-bev/ap/dextrose
A13: C0034 | B13: Gujarat Ambuja Exports Limited | C13: GAEL / Ambuja Group | D13: Yes | E13: Dextrose – grade unspecified | F13: Dextrose Monohydrate Powder (also labelled 'Glucose Powder'); Dextrose Anhydrous Powder | G13: Monohydrate and anhydrous, powder; feedstock maize. Pharmacopoeial grade (IP/BP/USP) not shown on the starch-derivatives page. | H13: Maize starch; liquid glucose; maltodextrin; sorbitol 70% solution; pregelatinised starch; maltitol syrup; glucose syrup solids; high-maltose corn syrup; dextrose syrup | I13: Manufacturer; Processor (maize wet-miller) | J13: Food; pharma (not stated on page – verify) | K13: Pharma / ORS | L13: India-West | M13: Ahmedabad, Gujarat, India | N13: India | O13: Maize/starch units listed on company site: Dalpur, Himmatnagar (Sabarkantha, Gujarat – Bio-Chemical Division); Sitarganj (Udham Singh Nagar, Uttarakhand); Hulsoggi, Shiggaon (Haveri, Karnataka); Chalisgaon (Jalgaon, Maharashtra); Malda Industrial Growth Centre (West Bengal). Which unit makes crystalline dextrose not stated. | P13: https://www.ambujagroup.com/ | Q13: Certificates page exists on company site (contents not read) | T13: Listed (NSE: GAEL; BSE) | V13: Company's own site lists both dextrose monohydrate and dextrose anhydrous powder. Pharma grade (IP/BP/USP), pyrogen-free status and certifications not verified in this pass – request spec sheets/CoA and certificates. | W13: High | X13: Corn/Maize | Y13: 5 | Z13: https://www.ambujagroup.com/ https://www.ambujagroup.com/starch-derivatives https://www.ambujagroup.com/dextrose-anhydrous-powder https://www.ambujagroup.com/dextrose-monohydrate-powder https://www.wrightresearch.in/stocks/stock/GAEL/
A14: C0075 | B14: Sayaji Industries Limited | C14: Maize Products (Sayaji Group) | D14: Yes | E14: Dextrose – grade unspecified | F14: Dextrose Monohydrate (industry-solutions page on maizeproducts.com) | G14: Monohydrate; feedstock maize. Grade/pharmacopoeia not verified (page not opened). | H14: Maize starch and derivatives; acacia gum powder; tomato powder; fat/oil powders; cheese powder | I14: Manufacturer; Processor (maize wet-miller) | J14: Textile, food & beverage, paper, paint, pharmaceutical, confectionery industries served (Fi Global exhibitor profile) | K14: Pharma / ORS | L14: India-West | M14: Ahmedabad, Gujarat, India | N14: India | O14: Ahmedabad, Gujarat (750 MTPD maize wet-milling plant with 5 MW captive power) | P14: https://www.maizeproducts.com/ | R14: 750 MTPD maize grinding (Fi Global exhibitor profile) | T14: Listed (BSE; ISIN INE327G01032); flagship of Sayaji Group, est. 1941 | V14: Dextrose monohydrate product page exists on maizeproducts.com (seen in search results; page could not be opened due to rate limit). Fi Global profile confirms corn wet-milling and pharma customers but does not itself mention dextrose. Verify grade (IP/BP/USP) and whether crystalline dextrose is made in-house. | W14: Medium | X14: Corn/Maize | Y14: 3 | Z14: https://www.maizeproducts.com/industry-solutions/dextrose-monohydrate/ https://exhibitors.figlobal.com/net/company/26/90/94/result269094-565.html https://upstox.com/stocks/sayaji-industries-limited/INE327G01032
A15: C0094 | B15: Universal Starch-Chem Allied Limited | D15: Yes | E15: Dextrose – grade unspecified | F15: Dextrose Monohydrate (white free-flowing crystalline powder); Dextrose Syrup; Liquid Glucose Confectionery | G15: Monohydrate crystalline powder; feedstock maize (corn wet-miller). Company states food & pharmaceutical grade starch IP/BP/USP/EP – that grade statement refers to starch; dextrose pharmacopoeial grade not stated. | H15: Dextrose syrup; liquid glucose confectionery; corn starch (food/pharma IP/BP/USP/EP, paper grade); modified starches; sweeteners | I15: Manufacturer; Processor (corn wet-miller); Exporter | J15: Food; alcoholic beverages; confectionery; pharmaceuticals (per CPHI listing) | K15: Pharma / ORS | L15: India-West | M15: Dondaicha, Shindkheda, Dhule, Maharashtra, India | N15: India | O15: Shahada Road, Rawal Industrial Estate, Dada Nagar, Dondaicha, Dhule, Maharashtra | Q15: FDA, GMP, ISO 9001 (icons on company's CPHI Online profile – claimed by company) | T15: Listed company (Bloomberg ticker UNIVSTAR:IN seen in search results) | V15: CPHI Online profile (company-supplied) lists dextrose monohydrate for pharmaceutical use; exports to Mexico, East Asia and EU claimed. Pharmacopoeial grade of dextrose and injectable/pyrogen-free status not verified. 100–249 employees per CPHI. | W15: Medium | X15: Corn/Maize | Y15: 3 | Z15: https://www.cphi-online.com/company/universal-starch-chem-allied-ltd/ https://www.cphi-online.com/product/dextrose-monohydrate-3/ https://www.bloomberg.com/profile/company/UNIVSTAR:IN
A16: C0044 | B16: Jay Somnath Starch Product | D16: Yes | E16: Dextrose – grade unspecified | F16: Dextrose Anhydrous Powder; Dextrose Monohydrate Powder | G16: Anhydrous and monohydrate powder; grade not verified | I16: Manufacturer (claimed on own site; crystallisation plant not verified) | K16: Pharma / ORS | L16: India-West | M16: Rajkot, Gujarat, India | N16: India | O16: Rajkot, Gujarat (claimed) | P16: https://www.jaysomnathstarch.in/ | T16: Private firm (GSTIN 24AASFJ8076F1ZX; PAN pattern indicates a partnership firm) | V16: Own-site page titles describe the firm as manufacturer/supplier of dextrose anhydrous and monohydrate from Rajkot; pages could not be opened. A small Rajkot firm is more likely a repacker/trader than a dextrose crystalliser – verify the plant and source mill before use. Pharma grade not verified. | W16: Low | Y16: 3 | Z16: https://www.jaysomnathstarch.in/dextrose-anhydrous-powder.htm https://www.jaysomnathstarch.in/dextrose-monohydrate-powder.htm https://piceapp.com/gst-number-search/jay-somnath-starch-product-24aasfj8076f1zx/
A17: C0006 | B17: Archer-Daniels-Midland Company | C17: ADM (CLINTOSE®) | D17: No | E17: Dextrose – grade unspecified | F17: CLINTOSE® Dextrose A; CLINTOSE® Dextrose VF; ADM Dextrose Monohydrate | G17: Monohydrate listed; other grade/pharmacopoeia details not captured | I17: Manufacturer | J17: food; beverage (pharma use not verified) | K17: Pharma / ORS | L17: International | M17: Chicago, Illinois, USA | N17: USA | P17: https://www.adm.com | T17: Listed – NYSE: ADM (general knowledge) | V17: Products seen via distributor (Tilley) and Knowde ADM storefront listings; ADM's own page not fetched. Pharma grade not verified. | W17: Medium | Y17: 3 | Z17: https://www.tilleydistributionproducts.com/products/clintose-dextrose-a https://tilleydistributionproducts.com/products/clintose-dextrose-vf https://knowde.com/stores/adm/products/adm-dextrose-monohydrate
A18: C0068 | B18: Ramshree Chemicals | D18: No | E18: Dextrose – grade unspecified | F18: Dextrose Monohydrate | G18: Monohydrate; grade not verified | I18: Trader (claims manufacturer); Supplier; Exporter | K18: Not stated in sources | L18: India-Pan | M18: India (city not verified) | N18: India | P18: https://www.ramshreechemicals.in/ | V18: Own-site page title: 'Dextrose Monohydrate Manufacturer in India, Supplier, Exporter'. No plant evidence; location and legal form not verified. Treat as trader until a plant and source mill are confirmed. | W18: Low | Y18: 1 | Z18: https://www.ramshreechemicals.in/dextrose-monohydrate-3400354.html
A19: C0008 | B19: Avantor, Inc. | C19: VWR / J.T.Baker® / Macron Fine Chemicals™ | D19: No | E19: Distributor/importer – dextrose | F19: Dextrose, anhydrous 97.5–102.0% (anhydrous basis) USP, Multi-Compendial, J.T.Baker®; Dextrose anhydrous granular GenAR® USP (Macron) | G19: Anhydrous; USP / multi-compendial; 'suitable for use as excipient' per VWR product title | I19: Supplier/repackager (J.T.Baker brand); Distributor (VWR) | J19: pharma; laboratory | K19: Pharma / ORS | L19: International | M19: Pennsylvania, USA | N19: USA | P19: https://www.avantorsciences.com | T19: Listed – NYSE: AVTR (general knowledge) | V19: Multi-compendial excipient-suitable anhydrous dextrose offered under J.T.Baker brand via VWR/Avantor; likely small-pack/repacked – not a bulk primary producer. | W19: Medium | Y19: 4 | Z19: https://b2b-ca.vwr.com/store/product/en/4541456/dextrose-anhydrous-97-5-102-0-by-anhydrous-basis-usp-multi-compendial-j-t-baker https://b2b-us.vwr.com/store/product/4541456/null https://b2b-cn.vwr.com/store/product/8030185/null https://www.avantorsciences.com/pt/en/search/USLP070318BIOP00008
A20: C0013 | B20: Biesterfeld AG | C20: Biesterfeld | D20: No | E20: Distributor/importer – dextrose | F20: Dextrose / Glucose | G20: Not captured (page not fetched) | I20: Distributor | J20: food; pharma (not verified) | K20: Pharma / ORS | L20: International | M20: Hamburg, Germany | N20: Germany | P20: https://www.biesterfeld.com | V20: Dextrose/glucose product pages on Biesterfeld country sites (AT, GB, ES, RO) surfaced in search; principals and grades not read. | W20: Medium | Y20: 2 | Z20: https://www.biesterfeld.com/en/gb/product/dextrose-glucose https://www.biesterfeld.com/en/at/product/dextrose-glucose/
A21: C0021 | B21: Cosmos (Grupo Cosmos) | C21: Cosmos | D21: No | E21: Distributor/importer – dextrose | F21: Dextrosa anhidra grado farmacéutico (pharmaceutical-grade anhydrous dextrose) | G21: Anhydrous, pharmaceutical grade (claimed by company) | I21: Distributor | J21: pharma | K21: Pharma / ORS | L21: International | M21: Mexico | N21: Mexico | P21: https://www.cosmos.com.mx | V21: Mexican chemical distributor with own product page for pharma-grade anhydrous dextrose; source manufacturer not identified. | W21: Medium | Y21: 1 | Z21: https://www.cosmos.com.mx/producto/dextrosa-4bfp/dextrosa-anhidra-d7jd/dextrosa-anhidra-grado-farmaceutico-ddbs/
A22: C0037 | B22: Hawkins, Inc. | C22: Hawkins | D22: No | E22: Distributor/importer – dextrose | F22: Dextrose (pharmaceutical group) | G22: Not captured (page not fetched) | I22: Distributor (page titled 'Dextrose Manufacturer, Supplier & Distributor'; own dextrose production not verified) | J22: pharma | K22: Pharma / ORS | L22: International | M22: Minnesota, USA | N22: USA | P22: https://www.hawkinsinc.com | T22: Listed – NASDAQ: HWKN (general knowledge) | V22: Dextrose listed under Hawkins' pharmaceutical group. | W22: Medium | Y22: 1 | Z22: https://www.hawkinsinc.com/groups/pharmaceutical/dextrose/
A23: C0055 | B23: Nordmann, Rassmann GmbH | C23: Nordmann | D23: No | E23: Distributor/importer – dextrose | F23: Dextrose | G23: Not captured (page not fetched) | I23: Distributor | J23: food; pharma (not verified) | K23: Pharma / ORS | L23: International | M23: Hamburg, Germany | N23: Germany | P23: https://www.nordmann.global | V23: Own product page for dextrose surfaced in search; grades and principal not read. | W23: Medium | Y23: 1 | Z23: https://www.nordmann.global/en/products/dextrose
A24: C0003 | B24: Apollo Healthcare Resources | D24: No | E24: Distributor/importer – dextrose | F24: Dextrose anhydrate | G24: Anhydrous; listing shows CEP, USDMF, JDMF, KDMF, EDMF/ASMF documentation (holder not identified) | I24: Distributor | J24: pharma | K24: Pharma / ORS | L24: International | M24: Singapore | N24: Singapore | Q24: GMP, CEP, USDMF, JDMF, KDMF, WC, EDMF/ASMF, FDA, ISO 9001, BSE/TSE (as listed on PharmaOffer; not verified) | V24: Asian pharma distributor; documentation list suggests it represents a Chinese CEP/DMF-holding maker (not named). | W24: Low | Y24: 1 | Z24: https://pharmaoffer.com/api-excipient-supplier/dextrose-anhydrate/cep
A25: C0007 | B25: Arshine Pharmaceutical Co., Limited | C25: Arshine | D25: No | E25: Distributor/importer – dextrose | F25: Dextrose anhydrate | G25: Anhydrous; listing shows CEP, USDMF, EDMF/ASMF documentation (holder not identified) | I25: Distributor; Exporter | J25: pharma | K25: Pharma / ORS | L25: International | M25: China | N25: China | Q25: GMP, CEP, USDMF, EDMF/ASMF, FDA, BSE/TSE (as listed on PharmaOffer; not verified) | V25: Chinese pharma-raw-material exporter; underlying manufacturer not named. | W25: Low | Y25: 1 | Z25: https://pharmaoffer.com/api-excipient-supplier/dextrose-anhydrate/cep
A26: C0017 | B26: Chr. Olesen | C26: Chr. Olesen | D26: No | E26: Distributor/importer – dextrose | F26: Glucose monohydrate (product origin China) with CEP and US DMF documentation | G26: Glucose monohydrate; CEP and USDMF listed (holder presumably the Chinese manufacturer – not identified) | I26: Distributor | J26: pharma | K26: Pharma / ORS | L26: International | M26: Denmark | N26: Denmark | Q26: FDA, USDMF, CoA listed; Eurofins GMP audit report Sep 2023 (PharmaOffer listing) | V26: European pharma-excipient distributor of Chinese-origin pharma glucose monohydrate per PharmaOffer; underlying manufacturer not named on the page. | W26: Low | Y26: 2 | Z26: https://pharmaoffer.com/api-excipient-supplier/excipients/glucose-monohydrate/cep https://pharmaoffer.com/api-excipient-supplier/glucose-monohydrate/cep
A27: C0040 | B27: Hänseler AG | C27: Hänseler | D27: No | E27: Distributor/importer – dextrose | F27: Glucose anhydrous | G27: Anhydrous; pharmacopoeia not stated on listing | I27: Distributor; CDMO (per listing) | J27: pharma | K27: Pharma / ORS | L27: International | M27: Switzerland | N27: Switzerland | Q27: GMP, FDA, MSDS, CoA (PharmaOffer listing) | V27: Swiss pharma-raw-material distributor listing glucose anhydrous; no CEP/DMF of its own listed. | W27: Low | Y27: 1 | Z27: https://pharmaoffer.com/api-excipient-supplier/glucose-anhydrous
A28: C0047 | B28: Lab Alley (Laboratory Alley LLC) | C28: Lab Alley | D28: No | E28: Distributor/importer – dextrose | F28: Dextrose, Monohydrate, FCC Grade, Powder, Kosher, Halal | G28: Monohydrate; FCC (food) grade; a country-of-origin document exists for this product (not read) | I28: Distributor; Repackager | J28: food; laboratory | K28: Pharma / ORS | L28: International | M28: Texas, USA | N28: USA | P28: https://www.laballey.com | V28: Own product page title states FCC-grade dextrose monohydrate; food grade only, not pharma. Legal name and HQ from general knowledge – not verified. | W28: Low | Y28: 2 | Z28: https://www.laballey.com/products/dextrose-monohydrate-fcc-grade-powder https://media.laballey.com/docbuilder/dextrose-monohydrate-fcc-grade-powder-country-of-origin-document-652e9c01db492.pdf
A29: C0065 | B29: Quadra (Quadra Chemicals) | C29: Quadra | D29: No | E29: Distributor/importer – dextrose | F29: Meritose 200 Pharma (dextrose) | G29: Pharma grade per product name | I29: Distributor | J29: pharma | K29: Pharma / ORS | L29: International | M29: Canada | N29: Canada | P29: https://www.quadragroup.store | V29: Online store lists 'Meritose 200 Pharma'; manufacturer attribution (Tereos) from search context only. | W29: Low | Y29: 1 | Z29: https://www.quadragroup.store/products/meritose-200-pharma-p15325
A30: C0090 | B30: Tianjia (tianjiachem.com) | C30: Tianjia | D30: No | E30: Distributor/importer – dextrose | F30: Food grade / Pharma grade Dextrose Anhydrous | G30: Anhydrous; food and pharma grades claimed on product page title | I30: Exporter; Trader (manufacturing not verified) | J30: food; pharma | K30: Pharma / ORS | L30: International | M30: China | N30: China | P30: https://www.tianjiachem.com | V30: Own site lists dextrose anhydrous in food and pharma grades (claimed by company); legal entity and whether it manufactures not established. | W30: Low | Y30: 1 | Z30: https://www.tianjiachem.com/dextrose-anhydrous-product/
A31: C0096 | B31: Xenex Labs | C31: Xenex Labs | D31: No | E31: Distributor/importer – dextrose | F31: Dextrose Anhydrous Powder USP, 25 kg | G31: Anhydrous; USP (claimed by company); 25 kg pack | I31: Distributor | J31: pharma; food | K31: Pharma / ORS | L31: International | M31: USA | N31: USA | P31: https://www.xenexlabs.com | V31: Own product page title states USP anhydrous dextrose in 25 kg; source manufacturer not identified. | W31: Low | Y31: 1 | Z31: https://www.xenexlabs.com/products/dextrose-anhydrous-powder-usp-25kg
A32: C0091 | B32: Tilley Distribution | C32: Tilley | D32: No | E32: Distributor/importer – dextrose | F32: ADM CLINTOSE® Dextrose A; CLINTOSE® Dextrose VF | G32: Not captured | I32: Distributor | J32: food; industrial | K32: Nutrition / food / beverage | L32: International | M32: USA | N32: USA | P32: https://www.tilleydistributionproducts.com | V32: Distributes ADM dextrose (own product pages). | W32: Medium | Y32: 2 | Z32: https://www.tilleydistributionproducts.com/products/clintose-dextrose-a https://tilleydistributionproducts.com/products/clintose-dextrose-vf
A33: C0051 | B33: Monarch Chemicals Ltd | C33: Monarch Chemicals | D33: No | E33: Distributor/importer – dextrose | F33: Dextrose Monohydrate | G33: Monohydrate; grade not captured | I33: Distributor | J33: food; industrial (not verified) | K33: Nutrition / food / beverage | L33: International | M33: United Kingdom | N33: United Kingdom | P33: https://www.monarchchemicals.co.uk | V33: Own A–Z product page lists dextrose monohydrate. | W33: Low | Y33: 1 | Z33: https://www.monarchchemicals.co.uk/Chemicals/A-to-Z/665-/Dextrose-Monohydrate
A34: C0064 | B34: PT Esco Chemicals Mitra Utama | C34: Esco Chemicals | D34: No | E34: Distributor/importer – dextrose | F34: Dextrose monohydrate | G34: Monohydrate; origin/grade not captured | I34: Distributor; Importer | J34: food (not verified) | K34: Nutrition / food / beverage | L34: International | M34: Indonesia | N34: Indonesia | V34: Indonesian B2B listing (Indotrading) for dextrose monohydrate; legal form 'PT' assumed from listing slug – not verified. | W34: Low | Y34: 1 | Z34: https://en.indotrading.com/escochemicalsmitrautama/dextrose-monohydrate-ex-p470664.aspx
A35: C0077 | B35: Shanghai Unitebiz | C35: Shanghai Unitebiz | D35: No | E35: Distributor/importer – dextrose | F35: Dextrose monohydrate food grade | G35: Monohydrate; food grade | I35: Exporter; Trader (manufacturing not verified) | J35: food | K35: Nutrition / food / beverage | L35: International | M35: Shanghai, China | N35: China | V35: Only a B2B hotsite listing (b2usa) seen; legal form unknown. | W35: Low | Y35: 1 | Z35: https://b2usa.com/hotsite/shanghaiunitebiz/dextrose-monohydrate-food-grade-high-qua
A36: C0027 | B36: Elchemy | C36: Elchemy | D36: No | E36: Distributor/importer – dextrose | F36: Dextrose Monohydrate (product listing) | G36: Grade not verified | I36: Distributor; Marketplace/platform | K36: Not stated in sources | L36: India-Pan | M36: India | N36: India | P36: https://elchemy.com/ | T36: Private | V36: B2B specialty-chemicals sourcing platform with a dextrose monohydrate product page. Source mill, grade and legal entity not verified; useful only as a back-up sourcing channel. | W36: Low | Y36: 1 | Z36: https://elchemy.com/product/dextrose-monohydrate-1509
A37: C0058 | B37: PCIPL (pciplindia.com) | C37: PCIPL | D37: No | E37: Distributor/importer – dextrose | F37: Dextrose Monohydrate (product-detail page) | G37: Grade not verified | I37: Distributor (presumed; not verified) | K37: Not stated in sources | L37: India-Pan | M37: India (not verified) | N37: India | P37: https://pciplindia.com/ | V37: Only a search result titled 'Dextrose Monohydrate' on pciplindia.com was seen; the page could not be opened, so the legal entity, location, source mill and grade are all unverified. Weak lead. | W37: Low | Y37: 1 | Z37: https://pciplindia.com/product-detail/dextrose-monohydrate
A38: C0069 | B38: Regaal Resources Limited | C38: Regaal | D38: No | E38: Starch processor – no crystalline dextrose found | F38: Maize starch / corn starch / food-grade starches; liquid glucose (LG); maltodextrin powder (MPD) | G38: Feedstock maize; food-grade starches | H38: Liquid glucose; maltodextrin powder; maize starch | I38: Processor (maize wet-miller); Manufacturer | J38: Food (food-grade starches) | K38: Nutrition / food / beverage | L38: India-East | M38: India (corporate office not verified) | N38: India | O38: Kishanganj, Bihar (maize processing; new liquid glucose and maltodextrin powder facility commissioned) | P38: https://regaalresources.com/ | R38: 1,650 TPD maize crushing after doubling (Rs 389 crore Kishanganj expansion; trade-press headlines) | S38: Full-year revenue ~Rs 1,134 crore (Trade Brains headline; fiscal year not stated in headline) | T38: Listed after IPO (IPO coverage by Samco/JK BFSL) | V38: Large maize processor in eastern India; no crystalline dextrose seen (LG and MPD only). Possible back-up for maize-derived inputs or a future dextrose source. | W38: Medium | X38: Corn/Maize | Y38: 5 | Z38: https://regaalresources.com/ https://agrospectrumindia.com/news/5/34078/regaal-resources-doubles-capacity-to-1650-tpd-commissions-new-lg-and-mpd-facility-in-bihar-with-rs-389-cr-investment.html https://tradebrains.in/regaal-resources-doubles-crushing-capacity-to-1650-tpd-full-year-revenue-touches-1134-crore/ https://www.outlookbusiness.com/news/regaal-resources-doubles-maize-processing-capacity-with-389-cr-expansion-at-kishanganj-bihar https://www.samco.in/ipo/regaal-resources-ipo
A39: C0089 | B39: The Sukhjit Starch and Chemicals Limited | C39: Sukhjit Group | D39: Yes | E39: Starch processor – no crystalline dextrose found | F39: Maize starch and derivatives (exact dextrose products not verified in this pass) | G39: Feedstock maize | I39: Processor (maize wet-miller); Manufacturer | K39: Not stated in sources | L39: India-North | M39: Phagwara, Punjab, India | N39: India | O39: Phagwara, Punjab (unit confirmed in May 2026 maintenance-shutdown filing); other plants not verified here | P39: https://www.sukhjitgroup.com/ | T39: Listed (NSE: SUKHJITS; BSE) | U39: CRISIL rating rationales dated 12 Jun 2026, 8 Aug 2025, 9 Aug 2024 and others exist; CARE rationales 2019/2022 (rating values not read) | V39: Not checked: the company website and CRISIL rationale could not be opened because of tool rate limits. Its dextrose monohydrate/anhydrous output is therefore unconfirmed – high-priority candidate to check (sukhjitgroup.com; CRISIL rationale gives capacity). | W39: Low | X39: Corn/Maize | Y39: 4 | Z39: https://www.crisil.com/mnt/winshare/Ratings/RatingList/RatingDocs/TheSukhjitStarchandChemicalsLimited_June 12_ 2026_RR_394602.html https://www.careratings.com/upload/CompanyFiles/PR/20092022074241_The_Sukhjit_Starch_&_Chemicals_Limited.pdf https://filingreader.com/news-wire/mumbai/2026-05-06/sukhjit-starch-to-shut-phagwara-unit-for-maintenance https://www.morningstar.com.au/investments/security/NSE/SUKHJITS

Sheet Maize
A1: Maize — 13 supplier lines. Upstream input to starch/dextrose; FDC is not assumed to buy maize directly.
A2: Company ID | B2: Company (legal / registered name) | C2: Trade / brand name | D2: Legal name verified | E2: Subcategory | F2: Relevant products | G2: Grades / specs / sizes / materials | H2: Related products kept separate (out of scope) | I2: Role | J2: Applications | K2: Priority match (keyword-derived) | L2: Region | M2: HQ | N2: Country | O2: Plants | P2: Website | Q2: Certifications (as stated) | R2: Capacity (published) | S2: Revenue (published) | T2: Ownership | U2: Credit rating | V2: Suitability / verification notes | W2: Evidence confidence | X2: Also listed under | Y2: No. of sources | Z2: Sources
A3: C0034 | B3: Gujarat Ambuja Exports Limited | C3: GAEL / Ambuja Group | D3: Yes | E3: Starch wet-miller (maize processor) | F3: Maize wet-milling into starch derivatives (starch, liquid glucose, maltodextrin, sorbitol), feed ingredients and fermentation products | G3: Maize procured as raw material for wet milling; NSE disclosure (26-Mar-2025) titled 'Commercial Production 1200TPD Maize' for a new maize processing unit; per-plant grind capacities not confirmed in this session | H3: Soya derivatives, edible oils, cotton yarn; dextrose/liquid glucose (covered under Dextrose/Glucose) | I3: Processor (maize wet-miller); Manufacturer | J3: food; pharma; paper; textile; feed | K3: Upstream input (n/a) | L3: India-West | M3: Ahmedabad, Gujarat, India | N3: India | O3: Maize processing (Bio-Chemical Division): Village Dalpur, Himmatnagar, Dist. Sabarkantha, Gujarat; Village Hulsoggi, Taluka Shiggaon, Dist. Haveri, Karnataka; Chalisgaon, Dist. Jalgaon, Maharashtra; also Sitarganj (Uttarakhand) and Malda (West Bengal) | P3: https://www.ambujagroup.com/ | R3: New 1,200 TPD maize processing unit commenced commercial production Mar-2025 (NSE filing title); group total not verified this session | T3: Listed (NSE: GAEL; BSE: 524226) | U3: CARE press releases Jan-2025, Aug-2025, Sep-2025, Dec-2025 and CRISIL rationales Apr-2023 exist; ratings not read (fetch rate-limited) | V3: One of India's largest maize processors; plants sit in the maize belts covered here (Sabarkantha, Haveri, Jalgaon). Large maize buyer rather than a maize seller; relevant as an upstream benchmark and for its dextrose/starch output. Maize spec (moisture/aflatoxin) not published. | W3: High | X3: Dextrose/Glucose | Y3: 3 | Z3: https://www.ambujagroup.com/ https://nsearchives.nseindia.com/corporate/GAEL_26032025100331_Commercial_Production_1200TPD_Maize.pdf https://www.careratings.com/upload/CompanyFiles/PR/202512121257_Gujarat_Ambuja_Exports_Limited.pdf
A4: C0071 | B4: Riddhi Siddhi Gluco Biols Limited | C4: RSGBL | D4: No | E4: Starch wet-miller (maize processor) | F4: Corn wet milling (maize starch and derivatives) at the ex-Cargill Karnataka plant | G4: Plant reported as a 300,000 MT corn milling facility (trade press headline) | H4: Starch derivatives, glucose (Dextrose/Glucose category) | I4: Processor (maize wet-miller) | J4: food; industrial | K4: Upstream input (n/a) | L4: India-West | M4: Ahmedabad, Gujarat, India | N4: India | O4: Corn wet-milling facility in Karnataka acquired from Cargill India (Davangere location from general knowledge; not re-verified) | P4: https://riddhisiddhi.co.in/ | R4: 300,000 MT corn milling facility (Karnataka) per trade-press headline | T4: Listed (BSE); acquired Cargill India's corn wet-milling division | V4: Company press release dated 19-Jan-2026 on RSGBL site plus trade press (World Grain, Papermart, The Machine Maker) report completion of the acquisition. Press release content not read (fetch rate-limited). | W4: Medium | Y4: 4 | Z4: https://riddhisiddhi.co.in/pdf/other-events-and-disclosure/press-release-19-01-2026.pdf https://www.world-grain.com/articles/22710-rsgbl-acquires-cargill-corn-mill-in-india https://insights.munich-startup.de/news/feed/riddhi-siddhi-gluco-biols-acquires-cargill-s-300-000-mt-corn-milling-facility-in-karnataka https://themachinemaker.com/news/rsgbl-completes-acquisition-of-corn-wet-milling-facility-from-cargill-in-karnataka/
A5: C0073 | B5: Roquette India Private Limited | C5: Roquette India | D5: No | E5: Starch wet-miller (maize processor) | F5: Maize starch and starch derivatives | H5: Polyols, dextrose, pharma excipients (other categories) | I5: Processor (maize wet-miller); Manufacturer | J5: pharma; food; nutrition; industrial | K5: Upstream input (n/a) | L5: India-West | M5: India | N5: India | O5: Viramgam, Gujarat (unit inaugurated Aug-2019); other Indian starch sites acquired in 2012 (seller named as Riddhi Siddhi Gluco Biols in general knowledge; not confirmed in pages read) | P5: https://www.roquette.com/ | T5: MNC subsidiary (Roquette Freres, France) | V5: Roquette press releases cover Viramgam capabilities and the 2019 unit inauguration; 2012 acquisition of Indian starch assets reported by FoodNavigator, EUWID and PotatoPro. Indian legal entity name not verified this session. Maize buyer rather than seller. | W5: Medium | X5: Dextrose/Glucose | Y5: 3 | Z5: https://www.roquette.com/press-releases/product-capabilities-viramgam-india https://www.roquette.com/media-center/press-center/2019-08-28-roquette-india-viramgam-s-unit-inauguration https://www.foodnavigator.com/Article/2012/06/01/Roquette-Indian-starch-JV-to-drive-market-traction
A6: C0094 | B6: Universal Starch-Chem Allied Limited | C6: Universal Starch | D6: Yes | E6: Starch wet-miller (maize processor) | F6: Maize (corn) starch and derivatives; pharma-industry starch products (IndiaMART catalogue) | H6: Liquid glucose, dextrose, sizing agents (other categories) | I6: Processor (maize wet-miller); Manufacturer | J6: pharma; food; textile; paper | K6: Upstream input (n/a) | L6: India-West | M6: Maharashtra, India | N6: India | O6: Dondaicha, Dist. Dhule, Maharashtra (not re-verified this session) | P6: https://www.universalstarch.com/ | T6: Listed (BSE: 524408); founded 1973 | V6: CPHI-Online lists the company, which suggests pharma-ingredient positioning. Plant location comes from general knowledge and was not re-verified; capacity not verified. Maize buyer. | W6: Medium | X6: Dextrose/Glucose | Y6: 3 | Z6: https://www.cphi-online.com/company/universal-starch-chem-allied-ltd/ https://m.indiamart.com/universalstarch/corn-starch.html https://www.sharescart.com/company/univer-starch-chem/
A7: C0075 | B7: Sayaji Industries Limited | C7: Sayaji | D7: Yes | E7: Starch wet-miller (maize processor) | F7: Maize processing into starches and derivatives | H7: Dextrose, liquid glucose, sorbitol (other categories) | I7: Processor (maize wet-miller); Manufacturer | J7: food; pharma; paper; textile | K7: Upstream input (n/a) | L7: India-West | M7: Ahmedabad, Gujarat, India | N7: India | O7: Kathwada, Ahmedabad, Gujarat (general knowledge; not re-verified) | P7: https://www.sayajigroup.in/ | T7: Listed (BSE) | U7: CARE press releases Oct-2018 and Nov-2019 exist; current rating not read | V7: Listed ingredients company (Fi Global exhibitor; CARE-rated). Maize processing comes from general knowledge and was not confirmed on a page read this session (fetches rate-limited); plant location and capacity not confirmed. Maize buyer. | W7: Low | X7: Dextrose/Glucose | Y7: 3 | Z7: https://www.careratings.com/upload/CompanyFiles/PR/Sayaji Industries Limited-03-11-2019.pdf https://www.kotaksecurities.com/stocks/bse-sayaji-industries-ltd https://exhibitors.figlobal.com/net/company/26/90/94/result269094-565.html
A8: C0026 | B8: EICL Limited | C8: Bharat Starch Industries (starch division); 'Haathi' brand | D8: Yes | E8: Starch wet-miller (maize processor) | F8: Maize starch, corn syrup, refined corn oil, gluten, maize oil cake (company 'Starch Story' page) | G8: Installed base 80,000 MTPA, processing potato, maize and tapioca (company page, (c)2015) | H8: corn syrup, modified starches, refined corn oil, clays/kaolin | I8: Processor (starch wet-miller); Manufacturer | J8: paper, paint, inks, pharmaceuticals, rubber, oil drilling, textiles (company page) | K8: Upstream input (n/a) | L8: India-North | M8: Gurugram, Haryana, India (office listed on company site) | N8: India | O8: Yamunanagar, Haryana (original corn wet-milling starch plant); Shimoga, Karnataka (value-added modified starches) | P8: https://eicl.in | R8: 80,000 MTPA starch processing base, multi-feedstock (company page, dated (c)2015) | T8: Thapar Group lineage; Indian Starch & Chemicals Ltd (1937), later renamed Bharat Starch Industries Ltd, became part of EICL in 2001 (company page) | V8: Yamunanagar (Haryana) unit began as a corn wet-milling plant, so it buys maize in the North. The company page is dated ((c)2015), so whether it still grinds maize and at what capacity needs re-checking. Pharma end-use is claimed by the company. Maize consumer, not a maize seller. | W8: Medium | Y8: 2 | Z8: https://eicl.in/?p=284 https://eicl.in/?p=572
A9: C0035 | B9: Gulshan Polyols Limited | C9: Gulshan Polyols | D9: Yes | E9: Starch wet-miller (maize processor) | F9: Native corn starch and starch derivatives (dextrose monohydrate, maltodextrin powder, liquid glucose); corn-based sorbitol; grain-based ethanol/ENA (grain-agnostic incl. maize) | G9: Corn grinding 300 TPD (Muzaffarnagar); planned 1,000 TPD maize grinding (Bihar); sorbitol 45,000 MTPA; distilleries run on damaged food grains, broken rice and maize/corn | H9: dextrose monohydrate, maltodextrin, liquid glucose, sorbitol, ethanol/ENA, PCC/GCC calcium carbonate | I9: Processor (starch wet-miller); Manufacturer | J9: starch derivatives (food/pharma/industrial), sorbitol, ethanol blending, calcium carbonate for paper | K9: Upstream input (n/a) | L9: India-North | N9: India | O9: Muzaffarnagar, Uttar Pradesh (native corn starch, 300 tonnes corn/day since Aug 2016; dextrose monohydrate, maltodextrin, liquid glucose); Goalpara, Assam (grain-based ethanol, 500 KLPD from June 2024 plus 250 KLPD commissioned 2025); Boregaon/Chhindwara, MP (grain distillery); Bharuch, Gujarat (sorbitol); Bihar: ~100 acres allotted by BIADA for a planned 1,000 TPD maize grinding project | R9: 300 TPD corn grinding (UP); planned 1,000 TPD maize grinding (Bihar); ethanol 560 KLPD+ total (Assam 500 KLPD added June 2024) | T9: Listed (BSE: 532457) | V9: Uses maize at its UP starch/dextrose unit and its Assam grain ethanol plant, with a planned Bihar maize-grinding project. It buys maize rather than selling it. A useful lead: a dextrose maker that also processes its own maize. Bihar project status not confirmed. Pharma grade of its dextrose not verified in this slice. | W9: Medium | Y9: 3 | Z9: https://www.indiainfoline.com/company/gulshan-polyols-ltd/summary https://www.gurufocus.com/stock/BOM:532457/transcripts/8616616 https://www.plindia.com/stocks/gulshan-polyols-ltd/
A10: C0089 | B10: The Sukhjit Starch and Chemicals Limited | C10: Sukhjit Starch (SSCL) | Sukhjit Starch; Sukhjit Biocorn (Nashik/Yeola project) | D10: Yes | E10: Starch wet-miller (maize processor) | F10: Maize starch and derivatives: liquid glucose, sorbitol 70%, monohydrate dextrose, dextrin; maize by-products for poultry and cattle feed and partly maize oil (CRISIL rationale) | Maize processing (starch and derivatives); Nashik maize unit under development | G10: Total maize grinding capacity 1,600 TPD across four plants; about 400 TPD expansion expected in FY2025 (CRISIL, Aug 2024). Specs for incoming maize (moisture/aflatoxin) not published in sources seen. | H10: liquid glucose, sorbitol 70%, dextrose monohydrate, dextrin (Dextrose/Glucose slice) | I10: Processor (starch wet-miller); Manufacturer | Processor (maize wet-miller); Manufacturer | J10: starch and starch derivatives; by-products to poultry/cattle feed and food (maize oil) | food; pharma; industrial | K10: Upstream input (n/a) | L10: India-North | M10: Phagwara, Punjab, India (general knowledge) | N10: India | O10: Phagwara, Punjab (in mega food park, operational since Nov 2020); Tahiwal, Himachal Pradesh; Malda, West Bengal; Nizamabad, Telangana | Planned maize processing plant at Yeola MIDC, Dist. Nashik, Maharashtra (MoU with Govt of Maharashtra); existing plants mostly North/East | P10: https://www.sukhjitgroup.com/ | R10: 1,600 TPD maize grinding (CRISIL rationale, 9 Aug 2024) | Rs 500 crore MoU for Nashik maize unit (Indian Chemical News); Rs 760 crore Yeola MIDC agro-processing plant (Free Press Journal) | S10: Operating income Rs 1,370.86 crore FY2024 (FY2023: Rs 1,435.25 crore); PAT Rs 55.62 crore FY2024 (CRISIL) | T10: Promoted by the Sardana family and associates; subsidiary Sukhjit Mega Food Park & Infra Ltd; publicly traded (stock pages on IIFL/Arihant Capital) | Listed (BSE) | U10: CRISIL A+/Stable (long term) and CRISIL A1 (short term), reaffirmed, 9 Aug 2024 | CRISIL rationales Feb-2023 and Jul-2023 exist; not read | V10: Large maize processor: CRISIL notes plants in North, South and East India sit close to maize sources, so different weather patterns allow steady procurement through the year; maize makes up about 70% of operating income. Upstream maize-to-dextrose processor (makes monohydrate dextrose), not a seller of raw maize: no evidence it resells grain. Pharma grade of its dextrose not verified in this slice. | Legal name taken from CRISIL rationale titles. Whether Sukhjit Biocorn is a separate subsidiary was not verified, and the Rs 500 crore (MoU) and Rs 760 crore (Yeola) figures may describe the same project. The Maharashtra unit is a project, not yet operating; it will become a large maize buyer in the Nashik belt. HQ and main plants are covered by the North researcher. | W10: Medium | X10: Dextrose/Glucose | Y10: 7 | Z10: https://www.crisil.com/mnt/winshare/Ratings/RatingList/RatingDocs/TheSukhjitStarchandChemicalsLimited_August 09_ 2024_RR_350173.html https://www.crisil.com/mnt/winshare/Ratings/RatingList/RatingDocs/TheSukhjitStarchandChemicalsLimited_July 18_ 2024_RR_347845.html https://www.careratings.com/upload/CompanyFiles/PR/The Sukhjit Starch & Chemicals Limited-10-09-2017.pdf https://www.indiainfoline.com/company/sukhjit-starch-chemicals-ltd/summary https://www.indianchemicalnews.com/general/sukhjit-starch-signs-rs-500-crore-mou-with-maharashtra-for-nashik-maize-unit-31805 https://www.freepressjournal.in/pune/nashik-sukhjit-biocorn-to-invest-760-crore-in-yeola-midc-agro-processing-plant https://www.crisil.com/mnt/winshare/Ratings/RatingList/RatingDocs/TheSukhjitStarchandChemicalsLimited_July 20, 2023_RR_323242.html
A11: C0092 | B11: Tirupati Starch & Chemicals Limited | C11: Tirupati Starch | D11: Yes | E11: Starch wet-miller (maize processor) | F11: Maize starch and derivatives (maize processing) | H11: Liquid glucose, dextrose (other categories) | I11: Processor (maize wet-miller); Manufacturer | J11: food; pharma; paper; textile | K11: Upstream input (n/a) | L11: India-Central | M11: Indore, Madhya Pradesh, India (not re-verified) | N11: India | O11: Madhya Pradesh (not re-verified) | T11: Listed (BSE: 524582) | V11: Listed starch company; its link to maize processing comes only from search context (it surfaced in maize-starch searches), and the location comes from general knowledge. Capacity, specs and rating not verified (an Acuite rationale ID 27656 surfaced in the search but was not read and is not confirmed to be this company). | W11: Low | Y11: 2 | Z11: https://musaffa.com/stock/524582.BO/ https://www.indiainfoline.com/company/tirupati-starch-chemicals-ltd-management/summary/3872
A12: C0069 | B12: Regaal Resources Limited | C12: Regaal Resources | D12: Yes | E12: Starch wet-miller (maize processor) | F12: Native maize starch, modified starch, maize flour, custard powder, baking powder, icing sugar, gluten, germ, enriched fibre; liquid glucose (LG) and MPD facility commissioned at Bihar plant (trade-press headline) | G12: Crushing capacity 750 TPD, expanded to 1,650 TPD (2026 announcements); 65,000 MT maize storage. Incoming maize specs not published in sources seen. | H12: modified starch, dextrins, liquid glucose, maltodextrin, maize flour, custard/baking powder | I12: Processor (starch wet-miller); Manufacturer | J12: paper, animal feed, food processing, textiles, adhesives; food-grade starches for bakery/confectionery | K12: Upstream input (n/a) | L12: India-East | M12: Kolkata, West Bengal, India (corporate office) | N12: India | O12: Kishanganj, Bihar (54-acre maize milling complex with 7.1 MW cogeneration and ZLD; 65,000 MT maize storage) | R12: 750 TPD maize crushing installed; doubled to 1,650 TPD at Kishanganj (Business Upturn / TipRanks headlines) | T12: Incorporated 2012, converted to public company 2022; IPO opened 12 Aug 2025 (Business Today); listed | V12: Large maize wet-miller in the Bihar/Seemanchal maize belt. Per IPO coverage it sources maize directly from farmers and aggregators in Bihar and West Bengal and keeps 65,000 MT of maize storage, so its buying network is a useful map of the regional supply base. Makes liquid glucose, but no evidence of dextrose monohydrate or pharma grade. Processor that consumes maize; no evidence it resells raw maize. | W12: Medium | X12: Dextrose/Glucose | Y12: 6 | Z12: https://x.com/LnprCapital/status/1957687364702335124?lang=en https://www.businessupturn.com/business/corporates/regaal-resources-doubles-maize-processing-capacity-to-1650-tpd-in-kishanganj https://www.tipranks.com/news/company-announcements/regaal-resources-doubles-maize-capacity-becomes-eastern-indias-largest-specialty-producer https://chemindigest.com/regaal-resources-commissions-lg-and-mpd-facility-in-bihar/ https://www.outlookbusiness.com/news/regaal-resources-doubles-maize-processing-capacity-with-389-cr-expansion-at-kishanganj-bihar https://www.businesstoday.in/amp/markets/ipo-corner/story/regaal-resources-ipo-opens-today-check-reviews-ratings-latest-gmp-more-488973-2025-08-12
A13: C0087 | B13: Telangana State Co-operative Marketing Federation Limited | C13: TS MARKFED | D13: No | E13: Cooperative/government procurement agency | F13: Maize procured at MSP from farmers (in coordination with NAFED) | G13: FAQ (fair average quality) maize under MSP norms (general MSP practice; specs not read) | I13: Cooperative/Government agency; Aggregator | J13: feed; industrial | K13: Upstream input (n/a) | L13: India-South | M13: Hyderabad, Telangana, India | N13: India | O13: Maize procurement centres across Telangana | V13: Indian Cooperative reports that MARKFED is coordinating maize procurement with NAFED; Siasat and South First cover the opening of procurement centres. Stocks are disposed of by auction or tender, not by spot sale. Exact legal name not verified. | W13: Medium | Y13: 3 | Z13: https://www.indiancooperative.com/co-op-news-snippets/maize-procurement-telangana-markfed-coordinating-with-nafed/ https://www.siasat.com/telangana-govt-opens-maize-procurement-centres-after-brs-pressure-harish-rao-3438607/ https://www.siasat.com/telanganas-maize-crisis-exposes-gaps-in-procurement-storage-systems-3468406/
A14: C0052 | B14: National Agricultural Cooperative Marketing Federation of India Ltd | C14: NAFED | D14: No | E14: Cooperative/government procurement agency | F14: Maize procured at MSP and supplied to ethanol distilleries (per trade press) | Maize procurement at MSP (e.g. 1 lakh tonnes from Telangana) | G14: FAQ (fair average quality) maize under MSP norms; detailed specs not seen | FAQ maize under MSP norms | H14: pulses, oilseeds, other agri commodities | I14: Cooperative/Government agency; Aggregator | J14: ethanol feedstock; price support | feed; ethanol; industrial | K14: Upstream input (n/a) | L14: India-Pan | M14: New Delhi, India | N14: India | O14: Procurement centres in maize states incl. Telangana | P14: https://www.nafed-india.com | R14: Agreed to procure 1 lakh tonnes of maize from Telangana (CropGPT report) | T14: National-level cooperative under Govt of India Ministry of Cooperation | National cooperative under the Multi-State Co-operative Societies Act | V14: Reported as a central agency allowed to procure maize at MSP and sell it to ethanol makers at a base rate (SOP for corn procurement for ethanol). Sales go to distilleries; whether it sells to starch processors was not verified. Seen only in news headlines, not fetched. | Sells procured stocks through open-market sale or e-auction; usable as a bulk source in surplus years. | W14: Medium | Y14: 5 | Z14: https://iamrenew.com/green-energy/nafed-nccf-can-sell-maize-to-ethanol-makers-at-base-rate/amp https://advancedbiofuelsusa.info/govt-to-buy-maize-at-msp-raise-output-to-meet-biofuel-needs https://www.qcintel.com/biofuels/article/indian-goverment-issues-sop-for-corn-procurement-for-ethanol-output-21584.html https://cropgpt.ai/nafed-agrees-to-procure-1-lakh-tonnes-of-maize-from-telangana-sets-up-procurement-centres-and-assures-minimum-support-price-for-farmers https://www.indiancooperative.com/co-op-news-snippets/price-fall-triggers-msp-push-by-nafed-nccf/
A15: C0053 | B15: National Cooperative Consumers' Federation of India Ltd | C15: NCCF | D15: No | E15: Cooperative/government procurement agency | F15: Maize procured at MSP and sold to ethanol distilleries (per trade press) | MSP procurement push alongside NAFED amid price fall; maize MSP procurement deadline for kharif 2025-26 extended to 30-Apr | I15: Cooperative/Government agency; Aggregator | J15: ethanol feedstock | feed; ethanol | K15: Upstream input (n/a) | L15: India-Pan | M15: New Delhi, India | N15: India | P15: https://nccf-india.com | T15: National-level cooperative (Govt of India) | National cooperative | V15: Named alongside NAFED as an agency that may sell MSP-procured maize to ethanol makers at a base rate. Seen only in news headlines; actual maize volumes and states not verified. | Named with NAFED in an Indian Cooperative report on an MSP procurement push; the extent of its maize-specific role was not verified. | W15: Low | Y15: 4 | Z15: https://iamrenew.com/green-energy/nafed-nccf-can-sell-maize-to-ethanol-makers-at-base-rate/amp https://krishijagran.com/news/maize-to-be-procured-by-govt-at-msp-increased-production-targeted-to-meet-biofuel-requirements/?amp=1 https://www.indiancooperative.com/co-op-news-snippets/price-fall-triggers-msp-push-by-nafed-nccf/ https://www.angelone.in/news/economy/centre-extends-maize-msp-procurement-deadline-for-kharif-2025-26-till-april-30

Sheet PET Resin
A1: PET Resin — 7 supplier lines. Virgin vs recycled and bottle- vs film-grade are separated by subcategory.
A2: Company ID | B2: Company (legal / registered name) | C2: Trade / brand name | D2: Legal name verified | E2: Subcategory | F2: Relevant products | G2: Grades / specs / sizes / materials | H2: Related products kept separate (out of scope) | I2: Role | J2: Applications | K2: Priority match (keyword-derived) | L2: Region | M2: HQ | N2: Country | O2: Plants | P2: Website | Q2: Certifications (as stated) | R2: Capacity (published) | S2: Revenue (published) | T2: Ownership | U2: Credit rating | V2: Suitability / verification notes | W2: Evidence confidence | X2: Also listed under | Y2: No. of sources | Z2: Sources
A3: C0070 | B3: Reliance Industries Limited | C3: Relpet | D3: Yes | E3: Virgin bottle-grade resin manufacturer | F3: Relpet PET resin (polyester); grade Relpet G5801 (RIL-hosted spec sheet 'py_rpt_g5801_spec.pdf'). Also runs PET bottle recycling (trade press: 'Reliance to double PET recycling capacity to 5 bn bottles'). | G3: Relpet G5801 (spec sheet on RIL's asset server and datasheets on UL Prospector, SpecialChem and Knowde). IV, copolymer type and food-contact statements were NOT read in this pass because the page fetches were blocked. | H3: Recycled polyester fibre (R|Elan) from PET bottle recycling; it is not shown to be food-grade rPET resin | I3: Manufacturer; Recycler | J3: PET packaging resin (application per grade not verified in this pass) | K3: Pharma / ORS | L3: India-Pan | M3: Mumbai, Maharashtra, India | N3: India | P3: https://www.ril.com | T3: Listed (NSE: RELIANCE) | V3: Food/pharma-contact compliance of Relpet grades not verified (spec sheet not readable this session). The FSSAI rPET authorisation status of Reliance's recycling units was not checked. | W3: Medium | Y3: 6 | Z3: https://rilstaticasset.akamaized.net/sites/default/files/2022-12/py_rpt_g5801_spec.pdf https://plastics.ulprospector.com/plastics/en/generics/37/materials/4048 https://www.specialchem.com/plastics/supplier/reliance-industries/relpet https://Knowde.com/stores/reliance-industries-ltd/products/relpet-g5801 https://www.indianchemicalnews.com/petro-chemical/lite/reliance-to-double-its-pet-recycling-capacity-to-5-bn-bottles-9971 https://petpla.net/2023/02/01/pet-raw-material-and-recyclate-from-india/
A4: C0043 | B4: IVL Dhunseri Petrochem Industries Private Limited | C4: IVL Dhunseri | D4: Yes | E4: Virgin bottle-grade resin manufacturer | F4: PET resin (JV formed in 2016 by Indorama Ventures and Dhunseri for PET manufacturing in India) | G4: Not verified in this pass | I4: Manufacturer | J4: PET packaging resin | K4: Nutrition / food / beverage | L4: India-East | N4: India | O4: Haldia, West Bengal (from caller's brief; not confirmed in the sources read) | P4: https://www.indoramaventures.com/en/worldwide/2001/ivl-dhunseri-petrochem-industries-private-limited | T4: JV of Indorama Ventures PCL (Thailand) and Dhunseri group; the legal name appears on Indorama's worldwide-sites page | V4: Food-contact grade claims not verified (the Indorama page could not be fetched; HTTP 429). | W4: Medium | Y4: 3 | Z4: https://www.indoramaventures.com/en/worldwide/2001/ivl-dhunseri-petrochem-industries-private-limited https://www.textileworld.com/textile-world/fiber-world/2016/02/indorama-ventures-and-dhunseri-form-joint-venture-in-india/ https://chemengonline.com/indorama-to-form-pet-manufacturing-joint-venture-in-india
A5: C0016 | B5: Chemco Plastic Industries | C5: Chemco | D5: No | E5: Recycled PET – food-grade (bottle-to-bottle) recycler | F5: rPET recycling plant in Gujarat (packaging-gateway headline 'Chemco Gujarat rPET recycling plant') | G5: Not verified | I5: Recycler | K5: Nutrition / food / beverage | L5: India-West | N5: India | O5: Gujarat (rPET recycling plant) | P5: https://www.chemcogroup.com | V5: Article not read. Whether the plant is bottle-to-bottle/food-grade and whether it holds FSSAI authorisation are UNVERIFIED, and the subcategory is provisional. | W5: Low | X5: PET Bottles & Preforms | Y5: 1 | Z5: https://www.packaging-gateway.com/news/chemco-gujarat-rpet-recycling-plant/
A6: C0085 | B6: Srichakra Polyplast | C6: Srichakra | D6: No | E6: Recycled PET – food-grade (bottle-to-bottle) recycler | F6: Food-grade recycled PET (rPET) resin made on Starlinger bottle-to-bottle equipment; supplied rPET for 'India's first 100% rPET beverage bottle' | G6: Bottle-grade food-contact rPET (IV not verified) | I6: Recycler; Manufacturer | J6: Beverage and food packaging | K6: Nutrition / food / beverage | L6: India-South | N6: India | R6: Trade press (petpla.net, Apr 2025) reports bottle-grade rPET capacity tripled; figure not read | T6: Private; investee of Circulate Capital (press release Mar 2022) | V6: Trade press (Mar 2022) reports a positive EFSA safety assessment for its rPET process, the first for an Indian recycler. Not checked against the EFSA Journal itself. FSSAI authorisation and US FDA no-objection letter status were not verified. | W6: Medium | Y6: 6 | Z6: https://www.indianpharmapost.com/sustainability/srichakra-receives-european-food-safety-approval-for-its-food-grade-recycled-rpet-11622 https://www.petnology.com/magazine/article/srichakra-becomes-the-first-indian-recycling-company-to-receive-a-positive-safety-assessment-from-european-food-safety-authority https://petpla.net/2025/04/28/srichakra-triples-bottle-grade-rpet-production-capacities/ https://www.foodanddrinktechnology.com/news/48696/recycled-pet-for-indias-first-100-rpet-beverage-bottle-produced-by-srichakra-polyplast/ https://petpla.net/2021/11/08/bottle-to-bottle-recycling-line-at-srichakra-polyplast-in-india/ https://www.circulatecapital.com/wp-content/uploads/2022/11/Srichakra_Press-Release_March-9-2022.docx.pdf
A7: C0024 | B7: Dalmia Polypro Industries Private Limited | C7: Dalmia Polypro | D7: No | E7: Recycled PET – food-grade (bottle-to-bottle) recycler | F7: PET recycling on EREMA systems (PET and PO recycling); food-grade rPET (Packaging South Asia item 'Dalmia Polypro's food-grade') | G7: Not verified | H7: Recycled polyolefins (PO) | I7: Recycler | J7: Food/beverage packaging (claimed in trade press) | K7: Nutrition / food / beverage | L7: India-Pan | N7: India | O7: New facility planned in Maharashtra (DFC-funded, per Outlook Business) | T7: Private; investee of Circulate Capital (2020); raising USD 30 mn from US DFC | V7: Food-grade claim comes from trade press and was NOT verified against FSSAI, US FDA or EFSA. A packaging-gateway item on an 'SLMG–Dalmia India plant' was seen but not read. The legal name rests on the filename of a Circulate Capital press release ('DalmiaPolyproIndustriesPL'). | W7: Medium | Y7: 5 | Z7: https://www.erema.com/en/public-relations-news/dalmia-polypro-to-install-erema-systems-for-pet-und-fuer-po-recycling--3233/ https://packagingsouthasia.com/application/dalmia-polypros-food-grade/ https://www.outlookbusiness.com/news/dalmia-polypro-to-raise-usd-30-mn-from-us-dfc-to-build-facility-in-maharashtra https://www.circulatecapital.com/wp-content/uploads/2022/12/DalmiaPolyproIndustriesPL-x-CC_-Press-Release_2020-12-10-.pdf https://www.packaging-gateway.com/news/slmg-dalmia-india-plant/
A8: C0029 | B8: Ganesha Ecosphere Limited | C8: GO Rewise | D8: No | E8: Recycled PET – food-grade (bottle-to-bottle) recycler | F8: Recycled PET: Starlinger bottle-to-fibre and bottle-to-bottle recycling lines for 'Indian recycling brand Go Rewise' (trade press) | G8: Bottle-to-bottle rPET (grade/IV not verified) | H8: Recycled polyester staple fibre / yarn (bottle-to-fibre) | I8: Recycler; Manufacturer | J8: Beverage/food packaging rPET (bottle-to-bottle); fibre | K8: Nutrition / food / beverage | L8: India-Pan | N8: India | O8: Warangal, Telangana bottle-to-bottle unit via subsidiary Ganesha Ecopet (from caller's brief; not confirmed in the sources read) | T8: Listed (NSE: GANECOS) | V8: Food-contact status of the bottle-to-bottle rPET (FSSAI authorisation, US FDA no-objection letter) NOT verified in this pass. Linking the GO Rewise brand to Ganesha Ecosphere comes from the search context; the article itself was not read. | W8: Medium | Y8: 4 | Z8: https://nsearchives.nseindia.com/corporate/GANECOS_03092025232921_annual_report.pdf https://recyclinginside.com/news/bottle-to-fibre-and-bottle-to-bottle-two-starlinger-pet-recycling-lines-for-indian-recycling-brand-go-rewise/ https://www.wasterecyclingmag.com/news/plastic-recycling/bottle-to-fibre-and-bottle-to-bottle-two-starlinger-pet-recycling-lines-for-indian-recycling-brand-go-rewise https://www.innovationintextiles.com/trailblazing-pet-recycling-in-india
A9: C0074 | B9: rPET InWaste, s.r.o. | C9: rPET InWaste | D9: Yes | E9: Recycled PET – food-grade (bottle-to-bottle) recycler | F9: PET bottle-to-bottle recycling (EU Circular Economy Stakeholder Platform good-practice entry) | G9: Not verified | I9: Recycler | J9: Beverage bottles | K9: Nutrition / food / beverage | L9: International | N9: Czech Republic | V9: EU food-contact status (EFSA opinion / Reg. (EU) 2022/1616 authorisation) NOT verified in this pass. | W9: Medium | Y9: 1 | Z9: https://circulareconomy.europa.eu/platform/en/good-practices/rpet-inwaste-sro-enabling-pet-bottle-bottle-recycling

Sheet PET Bottles & Preforms
A1: PET Bottles & Preforms — 19 supplier lines. Subcategory says preforms, bottles or both; HDPE/PP lines are noted separately.
A2: Company ID | B2: Company (legal / registered name) | C2: Trade / brand name | D2: Legal name verified | E2: Subcategory | F2: Relevant products | G2: Grades / specs / sizes / materials | H2: Related products kept separate (out of scope) | I2: Role | J2: Applications | K2: Priority match (keyword-derived) | L2: Region | M2: HQ | N2: Country | O2: Plants | P2: Website | Q2: Certifications (as stated) | R2: Capacity (published) | S2: Revenue (published) | T2: Ownership | U2: Credit rating | V2: Suitability / verification notes | W2: Evidence confidence | X2: Also listed under | Y2: No. of sources | Z2: Sources
A3: C0016 | B3: Chemco Plastic Industries | C3: Chemco Group | D3: No | E3: Preforms & bottles | F3: PET bottles; in-house food-grade rPET for bottle production (Rs 125 crore rPET bottle recycling plant in Gujarat) | G3: Food-grade rPET (FSSAI nod per Packaging South Asia headline) | I3: Manufacturer; Recycler | J3: food; beverage; personal care (not verified) | K3: Pharma / ORS | L3: India-West | N3: India | O3: Sanand, Gujarat (food-grade rPET bottle recycling facility, per Industrial Automation India URL); Daman/Silvassa operations not verified | Q3: FSSAI approval for food-grade rPET (trade press headline 'Chemco gets FSSAI nod') | T3: Private group (Chemco Group) | V3: Evidence is search-result titles/URLs only (WebFetch rate-limited, search budget exhausted in this session); pages not read. Multiple trade-press headlines confirm a Rs 125 crore food-grade rPET bottle recycling plant at Sanand, Gujarat and FSSAI nod. Chemco's IndiaMART storefront surfaced for 'PET preform manufacturer Daman Silvassa', but plant locations, legal entity and pharma suitability not verified. | W3: Medium | X3: PET Resin | Y3: 6 | Z3: https://www.packaginginsights.com/news/chemco-pet-bottle-recycling-india.html https://www.plastemart.com/news-plastics-information/chemco-group-pioneering-circularity-with-in-house-rpet-production/75112 https://www.industrialautomationindia.in/news/chemco-group-food-grade-rpet-facility-sanand https://themachinemaker.com/news/chemco-group-launches-%e2%82%b9125-crore-food-grade-rpet-bottle-recycling-plant-in-gujarat/ https://packagingsouthasia.com/type-of-article/industry-news/chemco-gets-fssai-nod/ https://m.indiamart.com/chemcoplastic
A4: C0059 | B4: Pearl Polymers Ltd | C4: Pearl Pet | D4: Yes | E4: Preforms & bottles | F4: PET packaging (bottles/jars) - Packaging South Asia profile titled 'PET pioneer Pearl'; product list not read this session | PET containers/bottles (described as 'PET pioneer' by Packaging South Asia) | I4: Manufacturer (per trade-press title; not verified this session) | K4: Pharma / ORS | L4: India-North | M4: New Delhi, Delhi, India | N4: India | T4: Listed on BSE and NSE (ticker PEARLPOLY); founded 1971 (per Kotak Securities stock page title) | Listed (BSE/NSE: PEARLPOLY); founded 1971 (per Kotak Securities page title) | V4: Delhi HQ and the 'Pearl Pet' brand come from the caller's candidate list and were not confirmed from a fetched page. No pharma/food-contact certification verified. The company pages and filings could not be opened (HTTP 429), so the current operating status, plants and product range are unverified. Check the latest BSE/NSE filings before shortlisting. | Evidence is search-result titles/URLs only (WebFetch rate-limited, search budget exhausted in this session); pages not read. Listed company; Packaging South Asia feature 'PET pioneer Pearl'. HQ/plant locations (Daman etc.) and current product range/operating scale NOT verified this session; region set India-Pan pending verification. | W4: Medium | Y4: 5 | Z4: https://packagingsouthasia.com/packaging-production/pet-pioneer-pearl/ https://www.roic.ai/quote/PEARLPOLY.BO https://www.screener.in/company/PEARLPOLY https://kotaksecurities.com/stocks/bse-pearl-polymers-ltd https://www.tickertape.in/stocks/pearl-polymers-PRLP
A5: C0048 | B5: Manjushree Technopack Limited | C5: Manjushree | D5: Yes | E5: Preforms & bottles | F5: PET preforms (the company site hosts a 'Preforms' brochure PDF); rigid plastic packaging (per acquisition news) | PET preforms (company-hosted 'Preforms' brochure PDF); PET bottles and PET jars (TradeIndia 'Pet Bisleri Bottles' and 'Plastic Pet Jars' listings, Bengaluru); rigid plastic packaging (corporate presentation) | PET preforms (company-hosted 'Preforms' brochure); rigid plastic packaging per corporate presentation | G5: Neck finishes, preform weights, sizes not captured (brochure PDF could not be read this session). | Not captured (preform brochure and corporate presentation could not be read in this session) | H5: Flexible packaging (per Labels & Labeling headline 'Manjushree diversifies into flexible packaging') | Other rigid plastic packaging (HDPE/PP) likely but not verified | I5: Manufacturer | J5: beverage; food; pharma (pharma segment not verified this session) | beverage; food; pharma (not verified this session) | K5: Pharma / ORS | L5: India-Pan | M5: Bengaluru, Karnataka, India | N5: India | O5: New plant at Silvassa (per Packaging South Asia headline); plant planned at Chamarajanagar, Karnataka (per Mysuru Infra Hub headline); Delhi-region operations through the acquisition of Delhi-based Varahi Limited, a rigid plastic packaging maker (2016, per PrintWeek/PETplanet headlines). No North, East or Northeast plant addresses (e.g. Pantnagar, Guwahati) were verified. | Bengaluru area (per IndiaMART/TradeIndia seller pages 'Manufacturer from Bengaluru'); new plastic packaging plant planned at Chamarajanagar, Karnataka (Mysuru Infra Hub headline). Other plant locations not verified this session. | P5: https://www.manjushreeindia.com/ | T5: Private, unlisted (shares trade on unlisted platforms); Advent International exited per an Altius Investech blog title. The current owner was not verified this session. | Private; Advent International-backed (per other team file citing Advent case page; not re-verified here). An IndiaMART storefront at the URL slug 'manjushree-technopark-limited' is titled 'Alternicq Limited - Manufacturer of Plastic Container & Pet Bottles from Bengaluru', and an IndiaInfoline 'alternicq-ltd' summary surfaced in a Manjushree search, suggesting a possible change of name to Alternicq Limited - NOT verified. | Private; backed by Advent International (per PrintWeek headline 'Manjushree Technopack backed by Advent to acquire Hitesh Plastics' and Advent International case page); acquired Hitesh Plastics (2022) | V5: The company's own site hosts a preform brochure (Preforms.pdf), but the brochure, the corporate presentation and the website could not be read (HTTP 429). Neck finishes, pharma grades and certifications were not verified. An IndiaMART listing is titled 'Manjushree Technopack Limited - Manufacturer from New Delhi'. Bengaluru HQ is from general knowledge and was not confirmed from a fetched page. | Evidence is search-result titles/URLs only (WebFetch rate-limited and shared search budget exhausted this session); pages not read. Largest South-India-based rigid PET packaging maker by reputation; company hosts preform brochure on own domain. Possible renaming to 'Alternicq Limited' needs MCA check. Pharma/ISO 15378 not verified. | Evidence is search-result titles/URLs only (WebFetch rate-limited, search budget exhausted in this session); pages not read. Company hosts a 'Preforms.pdf' and corporate presentations on its own domain. West-India plant locations (asked for in slice) NOT verified this session; HQ believed to be Bengaluru (prior knowledge, unverified) so region set India-Pan. Pharma grade/ISO 15378 not verified. | W5: Medium | X5: Caps & Closures | Y5: 17 | Z5: https://manjushreeindia.com/wp-content/uploads/2024/10/Preforms.pdf https://www.manjushreeindia.com/wp-content/uploads/2023/07/MTL-Corporate-Presentation.pdf https://www.printweek.in/news/india-packaging-leader-manjushree-technopack-acquires-delhi-varahi-22700 https://petpla.net/?p=3756 https://packagingsouthasia.com/packaging-production/manjushree-technopack-commissions-new-plant-at-silvassa/ https://www.indiamart.com/manjushree-technopack-ltd/aboutus.html https://altiusinvestech.com/blog/advent-internationals-3x-bagger-a-strategic-exit-from-manjushree-in-5-years/ https://en.wikipedia.org/wiki/Manjushree_Technopack https://www.indiamart.com/manjushree-techno-pack-limited/profile.html https://www.indiamart.com/manjushree-technopark-limited/ https://www.tradeindia.com/Seller-2683598-MANJUSHREE-TECHNOPACK-LTD-/ https://www.tradeindia.com/products/pet-bisleri-bottles-6089274.html https://mysuruinfrahub.com/manjushree-technopack-limited-to-setup-a-plastic-packaging-plant-at-chamarajanagar/ https://www.indiainfoline.com/company/alternicq-ltd/summary https://www.manjushreeindia.com/wp-content/uploads/2024/03/Manjushree-Corporate-Presentation.pdf https://www.adventinternational.com/ideas/the-endless-life-cycle-of-plastic-manjushree-technopack/ https://sbnri.com/p/pre-ipo/Manjushree-Technopack-Ltd.-jxbE69gV
A6: C0060 | B6: Petainer | C6: Petainer | D6: No | E6: Preforms & bottles | F6: PET plastic preforms incl. 'bottle preform 28mm PCO' (company product page) | G6: 28 mm PCO bottle preform (per product-page URL/title); weights not captured | I6: Manufacturer | J6: beverage (not verified for pharma) | K6: Pharma / ORS | L6: International | P6: https://www.petainer.com | V6: Evidence is search-result titles/URLs only (WebFetch rate-limited and shared search budget exhausted this session); pages not read. Company's own product page exists for a 28 mm PCO preform. HQ/plants not verified this session. | W6: Medium | Y6: 1 | Z6: https://www.petainer.com/pet-plastic-preforms/bottle-preform-28mm-pco
A7: C0078 | B7: Sheth PET Polymers Private Limited | C7: Sheth PET | D7: No | E7: Bottles only | F7: Pharmaceutical PET Bottle (e.g. 40 ml pharma PET bottle) | G7: 40 ml (from page title); neck finishes/colours not captured | I7: Manufacturer (claimed by company site title) | J7: pharma | K7: Pharma / ORS | L7: India-West | M7: Thane, Maharashtra, India | N7: India | O7: Thane, Maharashtra (per site title) | P7: https://www.shethpet.in | V7: Evidence is search-result titles/URLs only (WebFetch rate-limited, search budget exhausted in this session); pages not read. Site page title: 'Pharmaceutical PET Bottle - 40ml Pharma PET Bottle Manufacturer from Thane'. Link between shethpet.in and the registered entity Sheth PET Polymers Pvt Ltd (GlobalLinker) inferred from name, not confirmed. Pharma claims are company's own. | W7: Medium | Y7: 2 | Z7: https://www.shethpet.in/pharma-pet-bottle.html https://th.globallinker.com/network/rubber-plastics-polymers/sme/sheth-pet-polymers-private-limited-241415
A8: C0050 | B8: Megapet Containers Pvt Ltd | C8: Megapet Containers | D8: No | E8: Bottles only | F8: PET containers/bottles (implied by name and listing surfaced for pharma PET bottle Vapi searches) | I8: Manufacturer (claims, unverified) | K8: Pharma / ORS | L8: India-West | M8: Pardi, Vapi, Gujarat, India | N8: India | V8: Evidence is search-result titles/URLs only (WebFetch rate-limited, search budget exhausted in this session); pages not read. Only an IndianYellowPages directory title ('Megapet Containers Pvt Ltd Pardi, Vapi, Gujarat') seen; products, pharma suitability and manufacturing status unverified. 'Pvt Ltd' is from the directory, not MCA. | W8: Low | Y8: 1 | Z8: https://www.indianyellowpages.com/vapi/megapet-containers-pvt-ltd-9175302
A9: C0063 | B9: Pranav Plastics | C9: Pranav Plastics | D9: No | E9: Bottles only | F9: Pharma PET bottles - Amber PET Bottle 60 mL | G9: 60 mL amber PET, 25 mm neck (from page title) | I9: Trader; Retailer | J9: pharma | K9: Pharma / ORS | L9: India-West | M9: Nashik, Maharashtra, India | N9: India | P9: https://www.pranavplasticsindia.com | V9: Evidence is search-result titles/URLs only (WebFetch rate-limited, search budget exhausted in this session); pages not read. Page title describes the firm as 'Trader - Retailer from Nashik' - not a manufacturer; useful only as a distribution source. Legal entity not verified. | W9: Low | Y9: 1 | Z9: https://www.pranavplasticsindia.com/pharma-pet-bottles.html
A10: C0066 | B10: Radcom Packaging Private Limited | C10: Radcom Packaging | D10: No | E10: Bottles only | F10: HDPE & PET containers for nutraceuticals/supplements; PET cream jars and PP cream jars | H10: HDPE containers; PP cream jars | I10: Manufacturer (claims, unverified) | J10: nutraceuticals; supplements; pharma; cosmetics | K10: Pharma / ORS | L10: India-West | N10: India | V10: Evidence is search-result titles/URLs only (WebFetch rate-limited, search budget exhausted in this session); pages not read. Listed in PharmaSource directory and CPHI Online (CPHI exhibitor) - pharma-packaging focus. Surfaced for 'pharmaceutical PET bottles manufacturer Mumbai ISO 15378' but HQ/plant location and ISO 15378 NOT verified; region India-West assumed. | W10: Low | Y10: 4 | Z10: https://pharmasource.global/directory/radcom-packaging-pvt-ltd/ https://www.cphi-online.com/company/radcom-packaging-pvt-ltd/ https://m.indiamart.com/radcompackaging/hdpe-pet-containers-4-nutraceuticals-supplements.html https://m.indiamart.com/radcompackaging/pet-cream-jars-and-pp-cream-jars.html
A11: C0049 | B11: Mark Pack | C11: Markpack | Mark Pack | D11: No | E11: Bottles only | F11: PET bottles; PET plastic bottles; PET jars; round containers (IndiaMART storefront pages) | G11: Not captured | I11: Manufacturer (claimed on B2B listing; not verified) | Trader (claims manufacturer) | J11: pharma (search context only; not verified) | K11: Pharma / ORS | L11: India-South | N11: India | P11: https://m.indiamart.com/markpack | V11: Evidence is search-result titles/URLs only (WebFetch rate-limited and shared search budget exhausted this session); pages not read. Storefront ranked top for 'PET bottle manufacturer Hyderabad pharma syrup bottles' and 'Hyderabad ... amber PET bottle' searches, but its city is NOT verified; region India-South is provisional. | Evidence is search-result titles/URLs only (WebFetch rate-limited, search budget exhausted in this session); pages not read. IndiaMART storefront with a 'pet bottles' product page surfaced for pharma PET bottle Vapi searches; location, manufacturing status and pharma suitability NOT verified. | W11: Low | Y11: 5 | Z11: https://m.indiamart.com/mark-pack/pet-bottles.html https://m.indiamart.com/markpack/pet-plastic-bottles.html https://m.indiamart.com/markpack/pet-jars.html https://m.indiamart.com/mark-pack/plastic-bottle.html https://m.indiamart.com/markpack
A12: C0079 | B12: Sibi Polymers | D12: No | E12: Bottles only | F12: Garment Packing PET Jars (IndiaMART storefront title) | G12: Not captured | I12: Manufacturer (claimed on B2B listing; not verified) | J12: garment packaging (non-pharma) | K12: Pharma / ORS | L12: India-South | N12: India | P12: https://m.indiamart.com/sibi-polymers/ | V12: Evidence is search-result titles/URLs only (WebFetch rate-limited and shared search budget exhausted this session); pages not read. Surfaced in a Coimbatore PET-jar search; city NOT verified. Stated application is garment packing, so low relevance to pharma/food. | W12: Low | Y12: 1 | Z12: https://m.indiamart.com/sibi-polymers/
A13: C0081 | B13: Sonapet Industries | D13: No | E13: Bottles only | F13: PET jars / plastic containers (IndiaMART storefront 'plastic container' page) | G13: Not captured | I13: Manufacturer (claimed on B2B listing; not verified) | J13: food; general packaging (not verified) | K13: Nutrition / food / beverage | L13: India-South | N13: India | P13: https://m.indiamart.com/sonapetindustries | V13: Evidence is search-result titles/URLs only (WebFetch rate-limited and shared search budget exhausted this session); pages not read. Surfaced as top result for a Coimbatore PET-jar manufacturer search; city NOT verified. | W13: Low | Y13: 3 | Z13: https://m.indiamart.com/sonapetindustries https://m.indiamart.com/sonapetindustries/about-us.html https://m.indiamart.com/sonapetindustries/plastic-container.html
A14: C0038 | B14: Hitesh Plastics | C14: Hitesh Plastics | D14: No | E14: Bottles only | F14: Plastic (reportedly PET) packaging; acquisition covered by PET trade press | I14: Manufacturer | K14: Not stated in sources | L14: India-West | N14: India | T14: Acquired by Manjushree Technopack Ltd (Advent International-backed), Aug 2022 per petpla.net/PrintWeek | V14: Evidence is search-result titles/URLs only (WebFetch rate-limited, search budget exhausted in this session); pages not read. Known only via acquisition news headlines in PET-focused trade press (Petnology, PETplanet); product range, PET share, plant locations and legal suffix NOT verified. Region India-West assumed from caller's candidate list, not from a source. Now operates under Manjushree. | W14: Low | X14: Caps & Closures | Y14: 4 | Z14: https://www.printweek.in/news/manjushree-technopack-backed-by-advent-to-acquire-hitesh-plastics-56469 https://www.petnology.com/online/news-detail/manjushree-technopack-acquires-hitesh-plastics https://petpla.net/2022/08/08/manjushree-technopack-acquires-hitesh-plastics/ https://packagingsouthasia.com/type-of-article/manjushree-technopack-plant/
A15: C0042 | B15: Innopac Packagings | C15: Petainer | D15: No | E15: Bottles only | F15: PET containers (Petainer) - plant at Bhiwandi | I15: Manufacturer | K15: Not stated in sources | L15: India-West | N15: India | O15: Bhiwandi, Maharashtra (per Packaging South Asia archive headline) | V15: Evidence is search-result titles/URLs only (WebFetch rate-limited, search budget exhausted in this session); pages not read. Only an archived trade-press headline 'Petainer Innopac Packagings plant at Bhiwandi' seen; current operating status, ownership and product range NOT verified - may be historical. | W15: Low | Y15: 1 | Z15: https://packagingsouthasia.com/zarchive/petainer-innopac-packagings-plant-at-bhiwandi/
A16: C0001 | B16: Ahimsa Industries Limited | C16: Ahimsa Industries | D16: No | E16: Preforms only | F16: PET preforms | I16: Manufacturer (claims, unverified) | K16: Pharma / ORS | L16: India-West | N16: India | V16: Evidence is search-result titles/URLs only (WebFetch rate-limited, search budget exhausted in this session); pages not read. Dial4Trade product listing 'PET preforms' and a PETplanet WikiPETia entry ('Ahmisa Industries Limited', spelling as shown). HQ believed to be Ahmedabad (prior knowledge, unverified). Pharma suitability not verified. | W16: Low | Y16: 2 | Z16: https://www.dial4trade.com/ahimsa-industries/pet-preforms-pdid-744484.htm https://petpla.net/wikipetia/index.php/Ahmisa_Industries_Limited
A17: C0036 | B17: Harsh Impex | D17: No | E17: Preforms only | F17: PET preforms (B2B listing title 'trusted pet preform manufacturers in odisha harsh impex') | I17: Claims manufacturer (B2B listing only; plant not verified) | K17: Pharma / ORS | L17: India-East | M17: Odisha, India | N17: India | V17: The only evidence is a GlobalLinker B2B listing title, and the page could not be read. Legal entity, city, neck finishes and any pharma or food suitability are unverified. | W17: Low | Y17: 3 | Z17: https://www.globallinker.com/products/trusted-pet-preform-manufacturers-in-odisha-harsh-impex-best-price-8457231 https://www.globallinker.com/seller/harsh-impex https://yourstory.com/companies/harsh-impex
A18: C0057 | B18: Parle Agro | C18: Parle Agro | D18: No | E18: Preforms only | F18: PET preforms (the company site has a 'preforms' page; its content was not read) | H18: Beverages (core business) | I18: Manufacturer (in-house preforms; third-party sale implied by the site page, not verified) | J18: beverage | K18: Nutrition / food / beverage | L18: India-Pan | M18: Mumbai, Maharashtra, India | N18: India | P18: https://parleagro.com/ | T18: Private | V18: Outside this slice's regions (a lead for the West/Pan-India researcher). Found only via a URL on the company's own domain (parleagro.com/preforms). The page could not be read, so product specs, plant locations and the legal name are unverified. Mumbai HQ is not confirmed from a fetched page. | W18: Low | Y18: 1 | Z18: https://parleagro.com/preforms
A19: C0022 | B19: Crystal Polymers | D19: No | E19: Preforms only | F19: PET preforms (surfaced in PET preform manufacturer search; IndiaMART profile) | G19: Not captured | I19: Manufacturer (claimed on B2B listing; not verified) | K19: Not stated in sources | L19: India-South | N19: India | P19: https://m.indiamart.com/crystal-poly/ | V19: Evidence is search-result titles/URLs only (WebFetch rate-limited and shared search budget exhausted this session); pages not read. Surfaced in a Bengaluru PET-preform search; city and product range NOT verified. | W19: Low | Y19: 1 | Z19: https://m.indiamart.com/crystal-poly/profile.html
A20: C0054 | B20: Nishant Mouldings Private Limited | D20: Yes | E20: Preforms only | F20: PET preforms (Dial4Trade listing 'pet preforms'; IndiaMART storefront) | G20: Not captured | I20: Manufacturer (per company name/listings; plant not verified) | K20: Not stated in sources | L20: India-South | N20: India | P20: https://m.indiamart.com/nishantmouldings | V20: Evidence is search-result titles/URLs only (WebFetch rate-limited and shared search budget exhausted this session); pages not read. Surfaced in a search for PET preform manufacturers in Bengaluru, Karnataka; HQ city NOT verified, region set India-South provisionally. Legal-entity form 'Private Limited' appears in ExportHub listing title. | W20: Low | Y20: 3 | Z20: https://m.indiamart.com/nishantmouldings https://www.exporthub.com/nishant-mouldings/ https://www.dial4trade.com/nishant-moulding/pet-preforms-pdid-6788384.htm
A21: C0062 | B21: Pondicherry Polymers | D21: No | E21: Preforms only | F21: PET preforms (Dial4Trade listing titled 'pet performs') | G21: Not captured | I21: Manufacturer (claimed on B2B listing; not verified) | K21: Not stated in sources | L21: India-South | M21: Puducherry, India (inferred from company name; not verified) | N21: India | V21: Evidence is search-result titles/URLs only (WebFetch rate-limited and shared search budget exhausted this session); pages not read. Single B2B listing; surfaced in a Chennai 25/28 mm PCO preform search. | W21: Low | Y21: 1 | Z21: https://www.dial4trade.com/pondicherry-polymers/pet-performs-pdid-1228244.htm

Sheet Caps & Closures
A1: Caps & Closures — 19 supplier lines. Materials (PP/HDPE/aluminium) recorded only where a source stated them.
A2: Company ID | B2: Company (legal / registered name) | C2: Trade / brand name | D2: Legal name verified | E2: Subcategory | F2: Relevant products | G2: Grades / specs / sizes / materials | H2: Related products kept separate (out of scope) | I2: Role | J2: Applications | K2: Priority match (keyword-derived) | L2: Region | M2: HQ | N2: Country | O2: Plants | P2: Website | Q2: Certifications (as stated) | R2: Capacity (published) | S2: Revenue (published) | T2: Ownership | U2: Credit rating | V2: Suitability / verification notes | W2: Evidence confidence | X2: Also listed under | Y2: No. of sources | Z2: Sources
A3: C0031 | B3: Gerresheimer (India operations) | C3: Gerresheimer | D3: No | E3: Child-resistant closures (CRC) | F3: Child-resistant pharmaceutical packaging promoted at CPHI India | H3: Pharma glass and plastic primary containers | I3: Manufacturer | J3: pharma | K3: Pharma / ORS | L3: India-Pan | M3: Düsseldorf, Germany (India operations) | N3: Germany | P3: https://www.gerresheimer.com | T3: MNC; Gerresheimer AG (listed, Frankfurt) | V3: Company news ties its child-resistant packaging to the Indian market (CPHI India); Indian legal entity and plant not verified this session. | W3: Medium | Y3: 1 | Z3: https://gerresheimer.com/en/company/newsroom/corporate-news/detail/cphi-india-gerresheimer-customers-value-child-resistant-pharmaceutical-packaging-1
A4: C0009 | B4: BERICAP GmbH & Co. KG | C4: Bericap | D4: No | E4: Child-resistant closures (CRC) | F4: Closure solutions for OTC pharmaceuticals ('Protect products from unauthorized access' landing page); closure solutions for home care and pharma supplies | G4: Materials, neck finishes and features not verified (pages not fetched). Bericap is generally a PP/HDPE closure maker (not verified this session). | I4: Manufacturer | J4: OTC pharma; home care; food; beverage | K4: Pharma / ORS | L4: International | M4: Budenheim, Germany | N4: Germany | P4: https://bericap.com | T4: Private | V4: Verification limited: page content could not be fetched this session (WebFetch rate-limited); record rests on search-result titles/URLs only. Company landing page explicitly targets OTC pharmaceuticals. Compliance not verified. | W4: Medium | Y4: 3 | Z4: https://bericap.com/home-care-pharma-supplies/landingpage-otc-pharmaceuticals/ https://www.packaging-gateway.com/products/bericap-closure-solutions-home-care-pharma-supplies/ https://packagingeurope.com/bericap-presents-closure-solutions-at-packaging-innovations/5782.article
A5: C0012 | B5: Berry Global, Inc. | C5: Berry Global Healthcare | D5: No | E5: Child-resistant closures (CRC) | F5: Two-piece Child-resistant Closures for Pharmaceutical and Healthcare Packaging (product items 13191479, 13567185); PET bottle and closure solutions for child-safe and tamper-evident medicine packaging; new child-resistant range (Berry Healthcare, 2023) | G5: Two-piece CRC design (per product page titles); tamper-evident options; sold alongside PET and HDPE pharma bottles (e.g. 50 ml 1797 HDPE item). Closure material, neck finishes and liner options not verified. | H5: HDPE and PET pharma bottles | I5: Manufacturer | J5: pharma; healthcare; OTC medicines | K5: Pharma / ORS | L5: International | M5: Evansville, Indiana, USA | N5: USA | P5: https://www.berryglobal.com | T5: Berry Global Group, Inc. (SEC registrant, CIK 1378992). Berry agreed a merger with Amcor in 2024-25; current ownership status not verified in this session. | V5: Verification limited: page content could not be fetched this session (WebFetch rate-limited); record rests on search-result titles/URLs only. Company product-page titles explicitly say 'for Pharmaceutical and Healthcare Packaging'. Compliance (DMF/ISO 15378) not verified. | W5: Medium | Y5: 5 | Z5: https://www.berryglobal.com/en/product/product-item/13191479 https://www.berryglobal.com/en/product/product-item/13567185 https://packagingeurope.com/news/berry-global-offers-range-of-pet-bottle-and-closure-solutions-for-child-safe-and-tamper-evident-medicine-packaging/9429.article https://packagingscotland.com/2023/02/berry-group-healthcare-launches-comprehensive-new-child-resistant-range/ https://www.sec.gov/Archives/edgar/data/0001378992/000137899218000039/form10k.htm
A6: C0018 | B6: Closure Systems International | C6: CSI | D6: No | E6: Child-resistant closures (CRC) | F6: Defender-Lok child-resistant closure (CRC) product line; child-resistant closure platform for nutraceuticals | G6: Not verified. | H6: Beverage closures (CSI core business, not verified this session) | I6: Manufacturer | J6: nutraceuticals; consumer health | K6: Pharma / ORS | L6: International | V6: Verification limited: page content could not be fetched this session (WebFetch rate-limited); record rests on search-result titles/URLs only. Trade press confirms CRC launch aimed at nutraceuticals. Pharma compliance not verified. | W6: Medium | Y6: 3 | Z6: https://www.packaginginsights.com/news/closure-systems-international-child-resistant-closure.html https://www.silicon.co.uk/press-release/closure-systems-international-launches-defender-lok-crc-product-line https://finance.yahoo.com/news/closure-systems-international-introduces-child-142709276.html
A7: C0019 | B7: Comar | C7: Comar | D7: No | E7: Child-resistant closures (CRC) | F7: Child-resistant closures | G7: Not verified. | I7: Manufacturer | J7: pharma; healthcare | K7: Pharma / ORS | L7: International | N7: USA | V7: Verification limited: page content could not be fetched this session (WebFetch rate-limited); record rests on search-result titles/URLs only. Trade press (Healthcare Packaging / Packaging World) item 'Comar: Child-resistant closures'; listed in Qualifyze supplier directory. HQ not verified. | W7: Medium | Y7: 3 | Z7: https://www.healthcarepackaging.com/industries/pharmaceuticals/press-release/13287374/comar-childresistant-closures https://app.qualifyze.com/directory/supplier/comar-71f904da https://directory.designnews.com/comar-inc-comp225738.html
A8: C0032 | B8: Global Closure Systems | C8: GCS | D8: No | E8: Child-resistant closures (CRC) | F8: PharmaSafe child-resistant closure; pharma closures exhibited at Pharmapack Europe 2016 and CPhI 2015 | G8: Not verified. | I8: Manufacturer | J8: pharma | K8: Pharma / ORS | L8: International | V8: Verification limited: page content could not be fetched this session (WebFetch rate-limited); record rests on search-result titles/URLs only. Trade press (Manufacturing Chemist, Healthcare Packaging, PharmTech) reports GCS pharma closure launches/exhibits. HQ country and current ownership not verified this session. | W8: Medium | Y8: 4 | Z8: https://manufacturingchemist.com/global-closure-systems-gcs-launches-pharmasafe-child-resistant-closure-91334 https://www.healthcarepackaging.com/home/press-release/13290585/global-closure-systems-exhibits-at-pharmapack-europe-2016 https://pharmtech.com/view/global-closure-systems-exhibits-cphi-2015 https://www.plasteurope.com/news/GLOBAL_CLOSURE_SYSTEMS_t228478
A9: C0005 | B9: AptarGroup, Inc. | C9: Aptar Pharma | D9: No | E9: Child-resistant closures (CRC) | F9: Child-resistant / senior-friendly closure technologies (Aptar Pharma) | G9: Not verified (page could not be fetched). | I9: Manufacturer | J9: pharma | K9: Pharma / ORS | L9: International | M9: Crystal Lake, Illinois, USA | N9: USA | P9: https://www.aptar.com | T9: Listed (NYSE: ATR) | V9: Verification limited: page content could not be fetched this session (WebFetch rate-limited); record rests on search-result titles/URLs only. Aptar Pharma technology page URL is for child-resistant/senior-friendly closures. Materials, neck finishes and compliance not verified. | W9: Low | Y9: 1 | Z9: https://www.aptar.com/pharmaceutical/technologies/child-resistant-senior-friendly/
A10: C0011 | B10: Berlin Packaging | C10: Berlin Packaging EU | D10: No | E10: Child-resistant closures (CRC) | F10: Child-resistant closures (healthcare packaging range, EU) | G10: Not verified. | I10: Distributor | J10: healthcare; pharma | K10: Pharma / ORS | L10: International | M10: Chicago, Illinois, USA | N10: USA | P10: https://berlinpackaging.eu | V10: Verification limited: page content could not be fetched this session (WebFetch rate-limited); record rests on search-result titles/URLs only. Company's EU site has a healthcare 'child-resistant closures' range page; distributor, not manufacturer. | W10: Low | Y10: 1 | Z10: https://berlinpackaging.eu/en-be/markets/healthcare/packaging/child-resistant-closures
A11: C0025 | B11: Drug Plastics & Glass Company, Inc. | C11: Drug Plastics | D11: Yes | E11: Child-resistant closures (CRC) | F11: Pharmaceutical plastic bottles and closures (supplier listings) | G11: Not verified. | H11: HDPE/PET pharma bottles | I11: Manufacturer | J11: pharma; nutraceutical | K11: Pharma / ORS | L11: International | N11: USA | V11: Verification limited: page content could not be fetched this session (WebFetch rate-limited); record rests on search-result titles/URLs only. Legal name from USPTO trademark owner listing (Justia). Closure range not confirmed from company site this session. | W11: Low | Y11: 3 | Z11: https://trademarks.justia.com/owners/drug-plastics-glass-company-inc-135913 https://www.pharmaceutical-tech.com/suppliers/drug-plastics-glass-co-inc https://niemagazine.com/resources/sourcebook/6455/drug-plastics-glass-co-inc/
A12: C0056 | B12: Origin Pharma Packaging | C12: Origin | D12: No | E12: Child-resistant closures (CRC) | F12: Child-safety / child-resistant pharma packaging; packaging designs launched at CPhI Barcelona | G12: Not verified. | I12: Supplier (manufacturing status not verified) | J12: pharma | K12: Pharma / ORS | L12: International | V12: Verification limited: page content could not be fetched this session (WebFetch rate-limited); record rests on search-result titles/URLs only. Pharmaceutical-Technology.com contractor press releases on Origin child-safety packaging. Whether Origin manufactures closures itself is not verified. | W12: Low | Y12: 3 | Z12: https://www.pharmaceutical-technology.com/contractors/packaging/origin/pressreleases/pressorigin-pharma-packaging-child-safety https://pharmaceutical-technology.com/contractors/cleanroom/origin/pressreleases/child-resistant-packaging https://www.pharmaceutical-technology.com/contractors/packaging/origin/
A13: C0004 | B13: Aptar Pharma India Private Limited | C13: Aptar Pharma | D13: No | E13: Dispensing closures | F13: Pharma drug-delivery/dispensing systems; Mumbai operations expanded with local production of pharma inhalation technology | G13: India SKU-level closure specs not verified this session | H13: Inhalation devices, nasal spray pumps (dispensing systems rather than simple caps) | I13: Manufacturer | J13: pharma | K13: Pharma / ORS | L13: India-West | M13: Mumbai, Maharashtra, India | N13: India | O13: Mumbai region, Maharashtra (expanded operations per trade press) | P13: https://aptar.com | T13: MNC subsidiary of AptarGroup Inc. (NYSE: ATR) | V13: Pharma-focused dispensing systems; relevance to ORS/oral-liquid screw caps not verified. Legal name taken from an IndiaMART profile title only (not MCA-verified). | W13: Medium | Y13: 3 | Z13: https://m.indiamart.com/aptar/aboutus.html https://www.indianpharmapost.com/news/aptar-expands-mumbai-operations-as-it-adds-local-production-of-pharma-inhalation-tech-22137 https://www.packaginginsights.com/news/aptar-pharma-expands-presence-in-india.html
A14: C0080 | B14: Silgan Dispensing Systems | C14: Silgan Dispensing (Silgan Holdings) | D14: No | E14: Dispensing closures | F14: Dispensing Closures Catalogue (2025, 2026 editions); Closures Product Guide | G14: Not verified (catalogue PDFs not opened). | I14: Manufacturer | J14: personal care; home care; food; healthcare (not verified) | K14: Pharma / ORS | L14: International | N14: USA | P14: https://silgandispensing.com | T14: Silgan Holdings Inc. (listed, NASDAQ: SLGN) - parent relationship from general knowledge, not verified this session | V14: Verification limited: page content could not be fetched this session (WebFetch rate-limited); record rests on search-result titles/URLs only. Company-hosted closure catalogues exist; pharma suitability not verified. | W14: Low | Y14: 3 | Z14: https://silgandispensing.com/wp-content/uploads/2026/07/260504-Dispensing-Closures-Catalogue-HR-1.pdf https://silgandispensing.com/wp-content/uploads/2026/01/Dispensing-Closures-Catalogue-06.25-HR.pdf https://silgandispensing.com/wp-content/uploads/2018/01/20SDS0755_Closures-Product-Guide_r3.pdf
A15: C0010 | B15: Bericap India Private Limited | C15: BERICAP | D15: Yes | E15: Multiple closure types | F15: Plastic closures (BERICAP global range, e.g. HC EV 28/27 tamper-evident cap for PCO 1881 necks); India SKU list not verified | G15: Global range includes HC EV 28/27 for PCO 1881 28 mm PET necks (tamper-evident). India-specific SKU list not verified this session. | I15: Manufacturer | K15: Pharma / ORS | L15: India-West | M15: Pune, Maharashtra, India (RoC Pune per CIN) | N15: India | O15: India plant (location not verified this session; CIN registered with RoC Pune) | P15: https://bericap.com | R15: Trade press (Aug 2018) reported Bericap doubling its India plant; figure not captured | T15: MNC subsidiary of BERICAP GmbH & Co. KG (Germany); former JV with Essel Propack, Bericap acquired Essel's stake | V15: Global closure maker; product page is the global catalogue, not India-specific. Pharma suitability not verified. CIN U25202PN2001PTC140929 per InstaFinancials. | W15: Medium | Y15: 4 | Z15: https://www.InstaFinancials.com/company/bericap-india-private-limited/U25202PN2001PTC140929 https://www.plasticsnews.com/article/20180828/NEWS/180829902/bericap-doubling-india-plant/ https://www.plastemart.com/news-plastics-information/bericap-to-acquire-essel-propack´s-share-in-indian-jv/8930 https://bericap.com/product/hc-ev-28-27-pco-1881/
A16: C0048 | B16: Manjushree Technopack Limited | C16: Manjushree | D16: No | E16: Multiple closure types | F16: Caps & closures (company product brochure 'Caps-Closures'); PET preforms | G16: Company publishes a dedicated caps & closures brochure; neck sizes/materials not extracted this session (fetch refused) | H16: PET preforms, rigid plastic packaging | I16: Manufacturer | K16: Pharma / ORS | L16: India-Pan | M16: Bengaluru, Karnataka, India | N16: India | O16: Multiple Indian plants (list not captured this session); includes closures capacity acquired with Hitesh Plastics (2022) | P16: https://www.manjushreeindia.com | T16: Private; backed by Advent International; acquired Hitesh Plastics (caps maker) 2022 and Oricon Enterprises' plastics packaging business | V16: Company site hosts a dedicated 'Caps-Closures' brochure, but its contents could not be read this session (fetch rate-limited); neck sizes, materials and pharma suitability not verified. | W16: Medium | X16: PET Bottles & Preforms | Y16: 4 | Z16: https://manjushreeindia.com/wp-content/uploads/2024/10/Caps-Closures.pdf https://www.manjushreeindia.com/wp-content/uploads/2024/03/Manjushree-Corporate-Presentation.pdf https://news.ventureintelligence.com/ma/manjushree-technopack-to-acquire-caps-maker-hitesh-plastics https://petpla.net/2022/08/08/manjushree-technopack-acquires-hitesh-plastics/
A17: C0033 | B17: Guala Closures S.p.A. | C17: Guala Closures | D17: Yes | E17: Multiple closure types | F17: Pharma closures (Guala Closures Pharma page; entered pharmaceutical closures market via KWK acquisition, Oct 2025; exhibited with KWK at Pharmapack); aluminium closures for spirits/wine | G17: Pharma closure range from KWK is plastic (per Il Giornale d'Italia headline). Aluminium ROPP/pharma specifics not verified. | I17: Manufacturer | J17: pharma; spirits; wine; beverage | K17: Pharma / ORS | L17: International | M17: Alessandria, Italy | N17: Italy | P17: https://www.gualaclosures.com | V17: Verification limited: page content could not be fetched this session (WebFetch rate-limited); record rests on search-result titles/URLs only. Legal name 'Guala Closures S.p.A.' per Wolf Theiss deal note. Has a dedicated pharma page and acquired pharma closure maker KWK (Austria). | W17: Medium | Y17: 4 | Z17: https://www.gualaclosures.com/pharma https://www.gualaclosures.com/sites/default/files/files/allegati/2025-10/PR%20-%20GUALA%20CLOSURES%20ENTERS%20INTO%20PHARMACEUTICAL%20CLOSURES%20MARKET%20_%20Final.pdf https://www.gualaclosures.com/guala-closures-pharmapack-kwk-strengthening-its-presence-pharmaceutical-sector https://www.wolftheiss.com/insights/wolf-theiss-advises-guala-closures-s-p-a-on-the-acquisition-of-austrian-packaging-company-kunststoffwerk-kremsmunster-gmbh/
A18: C0046 | B18: Kunststoffwerk Kremsmünster GmbH | C18: KWK | D18: Yes | E18: Multiple closure types | F18: Plastic closures for the pharmaceutical sector | G18: Plastic pharma closures (per press headlines); specific types/materials not verified. | I18: Manufacturer | J18: pharma | K18: Pharma / ORS | L18: International | M18: Kremsmünster, Austria | N18: Austria | P18: https://www.kwk.at | S18: c. EUR 18 million over 12 months (per Il Giornale d'Italia report on acquisition, 2025) | T18: Acquired by Guala Closures S.p.A. (2025) | V18: Verification limited: page content could not be fetched this session (WebFetch rate-limited); record rests on search-result titles/URLs only. Described in press as a leader in plastic closures for the pharmaceutical sector. | W18: Medium | Y18: 4 | Z18: https://www.wolftheiss.com/insights/wolf-theiss-advises-guala-closures-s-p-a-on-the-acquisition-of-austrian-packaging-company-kunststoffwerk-kremsmunster-gmbh/ https://www.ilgiornaleditalia.it/news/mondo-imprese/739210/guala-closures-acquisisce-kwk-leader-del-settore-del-packaging-farmaceutico-con-ricavi-di-18-milioni-di-euro-in-12-mesi.html https://plasticker.de/Plastics_News_47298_Guala_Closures_Packaging_Specialist_Acquires_KWK_Kunststoffwerk_Kremsmnster__Entry_into_the_Pharmaceutical_Closure_Market https://www.kwk.at/
A19: C0038 | B19: Hitesh Plastics | C19: Hitesh Plastics | D19: No | E19: Multiple closure types | F19: Plastic caps & closures (described as 'caps maker' in M&A coverage) | I19: Manufacturer | K19: Not stated in sources | L19: India-Pan | M19: India (location not verified this session) | N19: India | T19: Acquired by Manjushree Technopack (Advent International-backed), 2022 | V19: Now part of Manjushree; source the closures through Manjushree. Product range and plant locations not verified this session. | W19: Medium | X19: PET Bottles & Preforms | Y19: 3 | Z19: https://news.ventureintelligence.com/ma/manjushree-technopack-to-acquire-caps-maker-hitesh-plastics https://www.printweek.in/News/manjushree-technopack-backed-by-advent-to-acquire-hitesh-plastics-56469 https://www.petnology.com/online/news-detail/manjushree-technopack-acquires-hitesh-plastics
A20: C0067 | B20: Raja Tradelinks Pvt Ltd | C20: RTL | D20: No | E20: ROPP aluminium caps | F20: Aluminium ROPP caps | G20: Aluminium ROPP | I20: Supplier (role not verified) | J20: pharma | K20: Pharma / ORS | L20: India-Pan | M20: India (city not verified this session) | N20: India | V20: Listed on a pharma-technology product portal; manufacturer vs trader status not verified. | W20: Low | Y20: 1 | Z20: https://www.pharmaceutical-tech.com/products/raja-tradelinks-pvt-ltd-rtl/aluminium-ropp-caps
A21: C0086 | B21: Tekni-Plex, Inc. | C21: Tri-Seal (a Tekni-Plex company) | D21: No | E21: Liners & induction seals | F21: Induction seal closure liners incl. Luxe Seal two-piece embossed induction seal liners; pouch and lidding structures for medical device and pharma | G21: Two-piece (induction foil seal + secondary backing) embossed liners; exact laminate structures not verified. | I21: Manufacturer | J21: pharma; healthcare; food; personal care | K21: Pharma / ORS | L21: International | N21: USA | P21: https://tekni-plex.com | V21: Verification limited: page content could not be fetched this session (WebFetch rate-limited); record rests on search-result titles/URLs only. Company's own news pages confirm induction seal liners and pharma lidding structures. | W21: Medium | Y21: 4 | Z21: https://tekni-plex.com/en/articles/tri-seal-luxe-seal-2-pc-embossed-induction-seal-closer-liners https://www.healthcarepackaging.com/home/press-release/13289282/tekniplex-induction-seals https://www.oemmagazine.org/home/product/15693541/triseal-a-tekniplex-co-triseal-embossed-induction-seal-closure-liners https://tekni-plex.com/en/articles/tri-seal-unveils-latest-pouch-lidding-structures-for-medical-device-and-pharma-applications-at-mdm-west

Sheet BOPET Base Film
A1: BOPET Base Film — 7 supplier lines. Base-film makers, metallizers and film distributors; laminate converters are on their own sheet.
A2: Company ID | B2: Company (legal / registered name) | C2: Trade / brand name | D2: Legal name verified | E2: Subcategory | F2: Relevant products | G2: Grades / specs / sizes / materials | H2: Related products kept separate (out of scope) | I2: Role | J2: Applications | K2: Priority match (keyword-derived) | L2: Region | M2: HQ | N2: Country | O2: Plants | P2: Website | Q2: Certifications (as stated) | R2: Capacity (published) | S2: Revenue (published) | T2: Ownership | U2: Credit rating | V2: Suitability / verification notes | W2: Evidence confidence | X2: Also listed under | Y2: No. of sources | Z2: Sources
A3: C0061 | B3: Polyplex Corporation Limited | C3: Polyplex | D3: Yes | E3: BOPET base film manufacturer | F3: BOPET (polyester) film; new BOPET film plant in India announced | G3: Not verified this run | H3: BOPP, CPP (group also runs these - not verified this run) | I3: Manufacturer | J3: flexible packaging (food) - general; not verified for pharma | K3: Pharma / ORS | L3: India-North | N3: India | O3: India (new BOPET plant announced); overseas operations referenced in 2025 global-expansion filing - locations not verified this run | P3: https://www.polyplex.com | T3: Listed (NSE: POLYPLEX; BSE: 524051) | V3: Company/product pages could not be fetched during this run (proxy HTTP 429 rate-limit); record built from search-result titles/URLs only - verify grades and food-contact status directly. | W3: Medium | Y3: 3 | Z3: https://www.angelone.in/news/stocks-share-market/polyplex-corporation-expands-its-horizons-with-new-bopet-film-plant-in-india https://filingreader.com/news-wire/mumbai/2025-09-15/polyplex-highlights-global-expansion-sustainable-growth-strategy https://www.screener.in/company/524051
A4: C0030 | B4: Garware Hi-Tech Films Limited | C4: Garware | D4: Yes | E4: BOPET base film manufacturer | F4: Polyester films (focus on value-added: sun-control film, paint protection film, specialty/industrial polyester film) | G4: Packaging-grade polyester not confirmed this run - business now skewed to specialty/industrial films | H4: Sun control film; paint protection film (PPF) | I4: Manufacturer | J4: industrial/specialty; packaging grades unverified | K4: Nutrition / food / beverage | L4: India-West | N4: India | O4: Waluj, Chhatrapati Sambhajinagar, Maharashtra | P4: https://www.garwarehitechfilms.com | T4: Listed (NSE: GRWRHITECH) | V4: Company/product pages could not be fetched during this run (proxy HTTP 429 rate-limit); record built from search-result titles/URLs only - verify grades and food-contact status directly. Check whether thin packaging-grade BOPET is still offered. | W4: Medium | Y4: 2 | Z4: https://machinist.in/2025/09/garware-hi-tech-films-starts-commercial-production-of-new-ppf-line-at-waluj-facility/ https://www.garwarehitechfilms.com/wp-content/uploads/2023/03/Investors-Presentation-May-2021.pdf.pdf
A5: C0082 | B5: SRF Limited | C5: SRF Packaging Films | D5: No | E5: BOPET base film manufacturer | F5: BOPET film (packaging films business); BOPP film | G5: Not verified this run | H5: BOPP film; technical textiles; chemicals | I5: Manufacturer | J5: flexible packaging | K5: Nutrition / food / beverage | L5: India-Central | N5: India | O5: Indore, Madhya Pradesh (BOPET project per IFC disclosure); BOPET plants in Thailand and Hungary (Plasteurope) | P5: https://www.srf.com | T5: Listed (NSE: SRF) | V5: Company/product pages could not be fetched during this run (proxy HTTP 429 rate-limit); record built from search-result titles/URLs only - verify grades and food-contact status directly. IFC disclosure confirms Indore BOPET project. | W5: Medium | Y5: 3 | Z5: https://disclosures.ifc.org/project-detail/ESRS/37933/srf-india-bopet https://www.packaging-gateway.com/news/srf-plans-to-invest-58m-in-bopet-production-facility-in-indore-india-090216-4805002/ https://www.plasteurope.com/news/detail.asp?id=246416
A6: C0028 | B6: Ester Industries Limited | C6: Ester | D6: Yes | E6: BOPET base film manufacturer | F6: Polyester (BOPET) films; specialty polymers | G6: Not verified this run | I6: Manufacturer | J6: flexible packaging | K6: Nutrition / food / beverage | L6: India-Pan | N6: India | P6: https://www.esterindustries.com | T6: Listed (NSE: ESTER) | U6: CRISIL - rationales dated 13 May 2024 and 22 Jul 2025 (rating level not read this run) | V6: Company/product pages could not be fetched during this run (proxy HTTP 429 rate-limit); record built from search-result titles/URLs only - verify grades and food-contact status directly. | W6: Medium | Y6: 2 | Z6: https://www.crisil.com/mnt/winshare/Ratings/RatingList/RatingDocs/EsterIndustriesLimited_July 22_ 2025_RR_374336.html https://www.crisil.com/mnt/winshare/Ratings/RatingList/RatingDocs/EsterIndustriesLimited_May 13_ 2024_RR_343559.html
A7: C0045 | B7: Jindal Poly Films Limited | C7: Jindal Poly Films | D7: Yes | E7: BOPET base film manufacturer | F7: BOPET film (with BOPP) - per CRISIL rating rationale series | G7: Not verified this run | H7: BOPP film | I7: Manufacturer | J7: flexible packaging | K7: Nutrition / food / beverage | L7: India-Pan | N7: India | P7: https://www.jindalpoly.com | T7: Listed (NSE: JINDALPOLY) | U7: CRISIL - rationales dated 30 May 2025, 18 May 2026, 14 Aug 2026 (rating level not read this run) | V7: Company/product pages could not be fetched during this run (proxy HTTP 429 rate-limit); record built from search-result titles/URLs only - verify grades and food-contact status directly. | W7: Medium | Y7: 2 | Z7: https://www.crisil.com/mnt/winshare/Ratings/RatingList/RatingDocs/JindalPolyFilmsLimited_August 14_ 2026_RR_401765.html https://www.crisil.com/mnt/winshare/Ratings/RatingList/RatingDocs/JindalPolyFilmsLimited_May 18_ 2026_RR_395327.html
A8: C0083 | B8: SRF Limited - Hungary BOPET operation | C8: SRF Hungary | D8: No | E8: BOPET base film manufacturer | F8: BOPET film (SRF Hungary plant) | G8: Not verified this run | I8: Manufacturer | J8: flexible packaging | K8: Nutrition / food / beverage | L8: International | N8: Hungary | O8: Hungary | P8: https://www.srf.com | T8: Subsidiary of SRF Limited (India) | V8: Company/product pages could not be fetched during this run (proxy HTTP 429 rate-limit); record built from search-result titles/URLs only - verify grades and food-contact status directly. Plasteurope headline: 'Plants for BOPET films in operation in Hungary and Thailand'. | W8: Medium | Y8: 1 | Z8: https://www.plasteurope.com/news/detail.asp?id=246416
A9: C0084 | B9: SRF Limited - Thailand BOPET operation | C9: SRF Thailand | D9: No | E9: BOPET base film manufacturer | F9: BOPET film (SRF Thailand plant) | G9: Not verified this run | I9: Manufacturer | J9: flexible packaging | K9: Nutrition / food / beverage | L9: International | N9: Thailand | O9: Thailand | P9: https://www.srf.com | T9: Subsidiary of SRF Limited (India) | V9: Company/product pages could not be fetched during this run (proxy HTTP 429 rate-limit); record built from search-result titles/URLs only - verify grades and food-contact status directly. Plasteurope headline: 'Plants for BOPET films in operation in Hungary and Thailand'. | W9: Medium | Y9: 1 | Z9: https://www.plasteurope.com/news/detail.asp?id=246416

Sheet Laminate Converters
A1: Laminate Converters — 4 supplier lines. Printed multilayer laminates, sachets, pouches and rollstock; 'PET use not confirmed' is flagged where the source did not state PET.
A2: Company ID | B2: Company (legal / registered name) | C2: Trade / brand name | D2: Legal name verified | E2: Subcategory | F2: Relevant products | G2: Grades / specs / sizes / materials | H2: Related products kept separate (out of scope) | I2: Role | J2: Applications | K2: Priority match (keyword-derived) | L2: Region | M2: HQ | N2: Country | O2: Plants | P2: Website | Q2: Certifications (as stated) | R2: Capacity (published) | S2: Revenue (published) | T2: Ownership | U2: Credit rating | V2: Suitability / verification notes | W2: Evidence confidence | X2: Also listed under | Y2: No. of sources | Z2: Sources
A3: C0093 | B3: UFlex Limited | C3: UFlex | D3: Yes | E3: Pharma laminate converter (sachet/strip) | F3: Flexible packaging laminates and pouches; pharma packaging solutions showcased at CPHI/P-MEC 2019 including stick-pack packaging (trade-press headlines) | G3: Laminate structures not verified in this pass (company site blocked in this session) | H3: Packaging films (BOPET/BOPP base films) per 'Global Leader in Flexible Packaging Films' trade-press headline; packaging machines (stick-pack machine launch, 2019) | I3: Manufacturer; Converter | J3: pharma; food; FMCG | K3: Pharma / ORS | L3: India-North | M3: Noida, Uttar Pradesh, India | N3: India | O3: Noida, Uttar Pradesh (HQ/converting); other plant locations not verified in this pass | P3: https://www.uflexltd.com | T3: Listed company (BSE corporate filings seen) | V3: Trade-press headlines (PrintWeek India, Packaging South Asia) report UFlex showcasing pharma packaging solutions and a stick-pack machine at CPHI & P-MEC India 2019. PET use in converted laminates not confirmed from a fetched page in this pass (company also makes films). Structures/certifications not verified. | W3: Medium | Y3: 4 | Z3: https://www.printweek.in/news/uflex-highlights-its-pharma-packaging-solutions-at-cphi-2019-42519 https://packagingsouthasia.com/events/uflex-launches-stick-pack-machine-at-cphi-and-p-mec-2019/ https://www.plastemart.com/news-plastics-information/UFlex-Limited-A-Global-Leader-in-Flexible-Packaging-Films/75103 https://www.packaginginsights.com/profile-directory/uflex-limited.html
A4: C0020 | B4: Constantia Flexibles (India operations; registered entity not verified) | C4: Constantia Flexibles | D4: No | E4: Laminate/pouch/sachet converter | F4: Flexible packaging (production capacity expansion in India per company newsroom headline) | I4: Converter | K4: Pharma / ORS | L4: India-West | M4: Ahmedabad, Gujarat, India | N4: India | O4: Ahmedabad, Gujarat (Rs 100-crore plant investment / capacity expansion per PrintWeek India and Packaging South Asia headlines) | P4: https://cflex.com | T4: MNC subsidiary - Constantia Flexibles group | V4: PET use not confirmed. Coverage of the India expansion by DCAT (pharma supply-chain body) and by confectionery/beverage trade press suggests pharma and food relevance, but the Indian plant's products, laminate structures and certifications were not verified (pages rate-limited). Search for 'Parikh Packaging Ahmedabad' returned these Constantia Ahmedabad items plus a Packaging Gateway 'Parikh Packaging facility' project page; any Parikh-Constantia link was not verified in this pass. | W4: Medium | Y4: 6 | Z4: https://cflex.com/newsroom/constantia-flexibles-to-expand-production-capacity-in-india https://www.printweek.in/News/constantia-flexibles-invest-rs-100-crore-ahmedabad-plant-28024 https://packagingsouthasia.com/packaging-production/constantia-flexibles-to-invest-inr-100-crore-in-a-new-india-plant/ https://www.dcatvci.org/?p=6358 https://www.packaging-gateway.com/news/constantia-flexibles-expand-production-capacity-indian-facility/ https://www.packaging-gateway.com/projects/parikhpackagingfacil/
A5: C0039 | B5: Huhtamaki India Limited | C5: Huhtamaki India (formerly Huhtamaki PPL) | D5: No | E5: Laminate/pouch/sachet converter | F5: Flexible packaging (described as 'a leading flexible packaging converter for FMCG and food brands' in Plastemart headline) | I5: Converter | J5: FMCG; food | K5: Pharma / ORS | L5: India-West | M5: Thane, Maharashtra, India | N5: India | P5: https://www.huhtamaki.com/en/flexible-packaging/about-us/india/ | T5: Listed in India (NSE: HUHTAMAKI per Morningstar listing URL); part of the Huhtamaki group (company India page on huhtamaki.com) | V5: PET use not confirmed. Laminate structures, pharma/ORS sachet capability, plant list and certifications not verified: company pages could not be fetched (proxy rate-limit), so evidence is search-result titles/URLs only. Former name Huhtamaki PPL (Wikipedia result title). HQ city taken from task brief, not re-verified. Legal name per trade-press headline and listing-data title, not checked against filing. | W5: Medium | Y5: 5 | Z5: https://www.huhtamaki.com/en/flexible-packaging/about-us/india/ https://www.plastemart.com/news-plastics-information/huhtamaki-india-limited-a-leading-flexible-packaging-converter-for-fmcg-and-food-brands/75108 https://en.wikipedia.org/wiki/Huhtamaki_PPL https://dfd.dr.morningstar.com.au/investments/security/NSE/HUHTAMAKI https://production.huhtamaki.com/en-in/flexible-packaging
